package com.alipay.b.b.a.a;

import android.content.Context;
import android.text.TextUtils;
import android.webkit.CookieManager;
import java.io.ByteArrayOutputStream;
import java.io.IOException;
import java.io.InputStream;
import java.io.OutputStream;
import java.net.URI;
import java.net.URL;
import java.util.HashMap;
import java.util.concurrent.Callable;
import org.apache.http.Header;
import org.apache.http.HttpEntity;
import org.apache.http.HttpHost;
import org.apache.http.HttpResponse;
import org.apache.http.StatusLine;
import org.apache.http.client.CookieStore;
import org.apache.http.client.HttpRequestRetryHandler;
import org.apache.http.client.methods.HttpGet;
import org.apache.http.client.methods.HttpPost;
import org.apache.http.client.methods.HttpUriRequest;
import org.apache.http.entity.AbstractHttpEntity;
import org.apache.http.entity.ByteArrayEntity;
import org.apache.http.impl.client.BasicCookieStore;
import org.apache.http.protocol.BasicHttpContext;
import org.apache.http.protocol.HttpContext;

public final class aa
  implements Callable<ae>
{
  private static final HttpRequestRetryHandler e = new h();
  protected v a;
  protected Context b;
  protected y c;
  String d;
  private HttpUriRequest f;
  private HttpContext g = new BasicHttpContext();
  private CookieStore h = new BasicCookieStore();
  private CookieManager i;
  private AbstractHttpEntity j;
  private HttpHost k;
  private URL l;
  private int m = 0;
  private boolean n = false;
  private boolean o = false;
  private String p = null;
  private String q;
  
  public aa(v paramv, y paramy)
  {
    this.a = paramv;
    this.b = this.a.a;
    this.c = paramy;
  }
  
  private static long a(String[] paramArrayOfString)
  {
    int i1 = 0;
    while (i1 < paramArrayOfString.length)
    {
      if (("max-age".equalsIgnoreCase(paramArrayOfString[i1])) && (paramArrayOfString[(i1 + 1)] != null)) {
        try
        {
          long l1 = Long.parseLong(paramArrayOfString[(i1 + 1)]);
          return l1;
        }
        catch (Exception localException) {}
      }
      i1 += 1;
    }
    return 0L;
  }
  
  private ae a(HttpResponse paramHttpResponse, int paramInt, String paramString)
  {
    localByteArrayOutputStream = null;
    localObject2 = null;
    new StringBuilder("开始handle，handleResponse-1,").append(Thread.currentThread().getId());
    Object localObject1 = paramHttpResponse.getEntity();
    if ((localObject1 != null) && (paramHttpResponse.getStatusLine().getStatusCode() == 200))
    {
      new StringBuilder("200，开始处理，handleResponse-2,threadid = ").append(Thread.currentThread().getId());
      long l1;
      label217:
      try
      {
        localByteArrayOutputStream = new ByteArrayOutputStream();
      }
      finally {}
    }
    try
    {
      l1 = System.currentTimeMillis();
      a((HttpEntity)localObject1, localByteArrayOutputStream);
      localObject1 = localByteArrayOutputStream.toByteArray();
      this.o = false;
      this.a.c(System.currentTimeMillis() - l1);
      this.a.a(localObject1.length);
      new StringBuilder("res:").append(localObject1.length);
      localObject1 = new z(a(paramHttpResponse), paramInt, paramString, (byte[])localObject1);
      l1 = b(paramHttpResponse);
      paramHttpResponse = paramHttpResponse.getEntity().getContentType();
      if (paramHttpResponse == null) {
        break label326;
      }
      paramString = a(paramHttpResponse.getValue());
      paramHttpResponse = (String)paramString.get("charset");
      paramString = (String)paramString.get("Content-Type");
    }
    finally
    {
      for (;;)
      {
        paramString = localByteArrayOutputStream;
      }
      paramString = null;
      paramHttpResponse = (HttpResponse)localObject2;
      break label217;
    }
    ((z)localObject1).b(paramString);
    ((z)localObject1).a(paramHttpResponse);
    ((z)localObject1).a(System.currentTimeMillis());
    ((z)localObject1).b(l1);
    do
    {
      try
      {
        localByteArrayOutputStream.close();
        paramString = (String)localObject1;
        return paramString;
      }
      catch (IOException paramHttpResponse)
      {
        throw new RuntimeException("ArrayOutputStream close error!", paramHttpResponse.getCause());
      }
      if (paramString != null) {}
      try
      {
        paramString.close();
        throw paramHttpResponse;
      }
      catch (IOException paramHttpResponse)
      {
        throw new RuntimeException("ArrayOutputStream close error!", paramHttpResponse.getCause());
      }
      paramString = localByteArrayOutputStream;
    } while (localObject1 != null);
    paramHttpResponse.getStatusLine().getStatusCode();
    return null;
  }
  
  private static b a(HttpResponse paramHttpResponse)
  {
    b localb = new b();
    paramHttpResponse = paramHttpResponse.getAllHeaders();
    int i2 = paramHttpResponse.length;
    int i1 = 0;
    while (i1 < i2)
    {
      Object localObject = paramHttpResponse[i1];
      localb.a(((Header)localObject).getName(), ((Header)localObject).getValue());
      i1 += 1;
    }
    return localb;
  }
  
  private static HashMap<String, String> a(String paramString)
  {
    HashMap localHashMap = new HashMap();
    String[] arrayOfString = paramString.split(";");
    int i2 = arrayOfString.length;
    int i1 = 0;
    if (i1 < i2)
    {
      String str = arrayOfString[i1];
      if (str.indexOf('=') == -1)
      {
        paramString = new String[2];
        paramString[0] = "Content-Type";
        paramString[1] = str;
      }
      for (;;)
      {
        localHashMap.put(paramString[0], paramString[1]);
        i1 += 1;
        break;
        paramString = str.split("=");
      }
    }
    return localHashMap;
  }
  
  private void a(HttpEntity paramHttpEntity, OutputStream paramOutputStream)
  {
    InputStream localInputStream = i.a(paramHttpEntity);
    long l1 = paramHttpEntity.getContentLength();
    try
    {
      paramHttpEntity = new byte['ࠀ'];
      for (;;)
      {
        int i1 = localInputStream.read(paramHttpEntity);
        if ((i1 == -1) || (this.c.h())) {
          break;
        }
        paramOutputStream.write(paramHttpEntity, 0, i1);
        if ((this.c.f() != null) && (l1 > 0L))
        {
          this.c.f();
          y localy = this.c;
        }
      }
      paramOutputStream.flush();
      return;
    }
    catch (Exception paramHttpEntity)
    {
      paramHttpEntity.getCause();
      throw new IOException("HttpWorker Request Error!" + paramHttpEntity.getLocalizedMessage());
    }
    finally
    {
      ab.a(localInputStream);
    }
  }
  
  private static long b(HttpResponse paramHttpResponse)
  {
    long l1 = 0L;
    Object localObject = paramHttpResponse.getFirstHeader("Cache-Control");
    if (localObject != null)
    {
      localObject = ((Header)localObject).getValue().split("=");
      if (localObject.length < 2) {}
    }
    do
    {
      try
      {
        long l2 = a((String[])localObject);
        l1 = l2;
        return l1;
      }
      catch (NumberFormatException localNumberFormatException) {}
      paramHttpResponse = paramHttpResponse.getFirstHeader("Expires");
    } while (paramHttpResponse == null);
    return i.b(paramHttpResponse.getValue()) - System.currentTimeMillis();
  }
  
  private URI b()
  {
    String str = this.c.a();
    if (this.d != null) {
      str = this.d;
    }
    if (str == null) {
      throw new RuntimeException("url should not be null");
    }
    return new URI(str);
  }
  
  private HttpUriRequest c()
  {
    if (this.f != null) {
      return this.f;
    }
    Object localObject2;
    if (this.j == null)
    {
      localObject1 = this.c.b();
      localObject2 = this.c.b("gzip");
      if (localObject1 != null)
      {
        if (!TextUtils.equals((CharSequence)localObject2, "true")) {
          break label110;
        }
        this.j = i.a((byte[])localObject1);
        this.j.setContentType(this.c.c());
      }
    }
    Object localObject1 = this.j;
    if (localObject1 != null)
    {
      localObject2 = new HttpPost(b());
      ((HttpPost)localObject2).setEntity((HttpEntity)localObject1);
    }
    for (this.f = ((HttpUriRequest)localObject2);; this.f = new HttpGet(b()))
    {
      return this.f;
      label110:
      this.j = new ByteArrayEntity((byte[])localObject1);
      break;
    }
  }
  
  /* Error */
  private ae d()
  {
    // Byte code:
    //   0: aload_0
    //   1: getfield 76	com/alipay/b/b/a/a/aa:b	Landroid/content/Context;
    //   4: ldc_w 401
    //   7: invokevirtual 407	android/content/Context:getSystemService	(Ljava/lang/String;)Ljava/lang/Object;
    //   10: checkcast 409	android/net/ConnectivityManager
    //   13: invokevirtual 413	android/net/ConnectivityManager:getAllNetworkInfo	()[Landroid/net/NetworkInfo;
    //   16: astore_1
    //   17: aload_1
    //   18: ifnonnull +78 -> 96
    //   21: iconst_0
    //   22: istore 5
    //   24: iload 5
    //   26: ifne +113 -> 139
    //   29: new 377	com/alipay/b/b/a/a/a
    //   32: dup
    //   33: iconst_1
    //   34: invokestatic 419	java/lang/Integer:valueOf	(I)Ljava/lang/Integer;
    //   37: ldc_w 421
    //   40: invokespecial 424	com/alipay/b/b/a/a/a:<init>	(Ljava/lang/Integer;Ljava/lang/String;)V
    //   43: athrow
    //   44: astore_1
    //   45: aload_0
    //   46: invokespecial 426	com/alipay/b/b/a/a/aa:e	()V
    //   49: aload_0
    //   50: getfield 78	com/alipay/b/b/a/a/aa:c	Lcom/alipay/b/b/a/a/y;
    //   53: invokevirtual 279	com/alipay/b/b/a/a/y:f	()Lcom/alipay/b/b/a/a/g;
    //   56: ifnull +26 -> 82
    //   59: aload_0
    //   60: getfield 78	com/alipay/b/b/a/a/aa:c	Lcom/alipay/b/b/a/a/y;
    //   63: invokevirtual 279	com/alipay/b/b/a/a/y:f	()Lcom/alipay/b/b/a/a/g;
    //   66: pop
    //   67: aload_0
    //   68: getfield 78	com/alipay/b/b/a/a/aa:c	Lcom/alipay/b/b/a/a/y;
    //   71: astore_2
    //   72: aload_1
    //   73: invokevirtual 428	com/alipay/b/b/a/a/a:a	()I
    //   76: pop
    //   77: aload_1
    //   78: invokevirtual 430	com/alipay/b/b/a/a/a:b	()Ljava/lang/String;
    //   81: pop
    //   82: new 100	java/lang/StringBuilder
    //   85: dup
    //   86: invokespecial 431	java/lang/StringBuilder:<init>	()V
    //   89: aload_1
    //   90: invokevirtual 434	java/lang/StringBuilder:append	(Ljava/lang/Object;)Ljava/lang/StringBuilder;
    //   93: pop
    //   94: aload_1
    //   95: athrow
    //   96: aload_1
    //   97: arraylength
    //   98: istore 6
    //   100: iconst_0
    //   101: istore 5
    //   103: iload 5
    //   105: iload 6
    //   107: if_icmpge +1631 -> 1738
    //   110: aload_1
    //   111: iload 5
    //   113: aaload
    //   114: astore_2
    //   115: aload_2
    //   116: ifnull +1628 -> 1744
    //   119: aload_2
    //   120: invokevirtual 439	android/net/NetworkInfo:isAvailable	()Z
    //   123: ifeq +1621 -> 1744
    //   126: aload_2
    //   127: invokevirtual 442	android/net/NetworkInfo:isConnectedOrConnecting	()Z
    //   130: ifeq +1614 -> 1744
    //   133: iconst_1
    //   134: istore 5
    //   136: goto -112 -> 24
    //   139: aload_0
    //   140: getfield 78	com/alipay/b/b/a/a/aa:c	Lcom/alipay/b/b/a/a/y;
    //   143: invokevirtual 279	com/alipay/b/b/a/a/y:f	()Lcom/alipay/b/b/a/a/g;
    //   146: ifnull +16 -> 162
    //   149: aload_0
    //   150: getfield 78	com/alipay/b/b/a/a/aa:c	Lcom/alipay/b/b/a/a/y;
    //   153: invokevirtual 279	com/alipay/b/b/a/a/y:f	()Lcom/alipay/b/b/a/a/g;
    //   156: pop
    //   157: aload_0
    //   158: getfield 78	com/alipay/b/b/a/a/aa:c	Lcom/alipay/b/b/a/a/y;
    //   161: astore_1
    //   162: aload_0
    //   163: getfield 78	com/alipay/b/b/a/a/aa:c	Lcom/alipay/b/b/a/a/y;
    //   166: invokevirtual 445	com/alipay/b/b/a/a/y:d	()Ljava/util/ArrayList;
    //   169: astore_1
    //   170: aload_1
    //   171: ifnull +63 -> 234
    //   174: aload_1
    //   175: invokevirtual 450	java/util/ArrayList:isEmpty	()Z
    //   178: ifne +56 -> 234
    //   181: aload_1
    //   182: invokevirtual 454	java/util/ArrayList:iterator	()Ljava/util/Iterator;
    //   185: astore_1
    //   186: aload_1
    //   187: invokeinterface 459 1 0
    //   192: ifeq +42 -> 234
    //   195: aload_1
    //   196: invokeinterface 463 1 0
    //   201: checkcast 181	org/apache/http/Header
    //   204: astore_2
    //   205: aload_0
    //   206: invokespecial 465	com/alipay/b/b/a/a/aa:c	()Lorg/apache/http/client/methods/HttpUriRequest;
    //   209: aload_2
    //   210: invokeinterface 471 2 0
    //   215: goto -29 -> 186
    //   218: astore_1
    //   219: new 210	java/lang/RuntimeException
    //   222: dup
    //   223: ldc_w 473
    //   226: aload_1
    //   227: invokevirtual 474	java/net/URISyntaxException:getCause	()Ljava/lang/Throwable;
    //   230: invokespecial 219	java/lang/RuntimeException:<init>	(Ljava/lang/String;Ljava/lang/Throwable;)V
    //   233: athrow
    //   234: aload_0
    //   235: invokespecial 465	com/alipay/b/b/a/a/aa:c	()Lorg/apache/http/client/methods/HttpUriRequest;
    //   238: invokestatic 477	com/alipay/b/b/a/a/i:a	(Lorg/apache/http/HttpRequest;)V
    //   241: aload_0
    //   242: invokespecial 465	com/alipay/b/b/a/a/aa:c	()Lorg/apache/http/client/methods/HttpUriRequest;
    //   245: invokestatic 479	com/alipay/b/b/a/a/i:b	(Lorg/apache/http/HttpRequest;)V
    //   248: aload_0
    //   249: invokespecial 465	com/alipay/b/b/a/a/aa:c	()Lorg/apache/http/client/methods/HttpUriRequest;
    //   252: ldc_w 481
    //   255: aload_0
    //   256: invokespecial 484	com/alipay/b/b/a/a/aa:i	()Landroid/webkit/CookieManager;
    //   259: aload_0
    //   260: getfield 78	com/alipay/b/b/a/a/aa:c	Lcom/alipay/b/b/a/a/y;
    //   263: invokevirtual 317	com/alipay/b/b/a/a/y:a	()Ljava/lang/String;
    //   266: invokevirtual 489	android/webkit/CookieManager:getCookie	(Ljava/lang/String;)Ljava/lang/String;
    //   269: invokeinterface 491 3 0
    //   274: aload_0
    //   275: getfield 55	com/alipay/b/b/a/a/aa:g	Lorg/apache/http/protocol/HttpContext;
    //   278: ldc_w 493
    //   281: aload_0
    //   282: getfield 60	com/alipay/b/b/a/a/aa:h	Lorg/apache/http/client/CookieStore;
    //   285: invokeinterface 499 3 0
    //   290: aload_0
    //   291: getfield 70	com/alipay/b/b/a/a/aa:a	Lcom/alipay/b/b/a/a/v;
    //   294: invokevirtual 502	com/alipay/b/b/a/a/v:a	()Lcom/alipay/b/b/a/a/i;
    //   297: getstatic 47	com/alipay/b/b/a/a/aa:e	Lorg/apache/http/client/HttpRequestRetryHandler;
    //   300: invokevirtual 505	com/alipay/b/b/a/a/i:a	(Lorg/apache/http/client/HttpRequestRetryHandler;)V
    //   303: invokestatic 145	java/lang/System:currentTimeMillis	()J
    //   306: lstore 7
    //   308: new 100	java/lang/StringBuilder
    //   311: dup
    //   312: ldc_w 507
    //   315: invokespecial 105	java/lang/StringBuilder:<init>	(Ljava/lang/String;)V
    //   318: aload_0
    //   319: invokespecial 509	com/alipay/b/b/a/a/aa:f	()Ljava/lang/String;
    //   322: invokevirtual 296	java/lang/StringBuilder:append	(Ljava/lang/String;)Ljava/lang/StringBuilder;
    //   325: ldc_w 511
    //   328: invokevirtual 296	java/lang/StringBuilder:append	(Ljava/lang/String;)Ljava/lang/StringBuilder;
    //   331: aload_0
    //   332: getfield 328	com/alipay/b/b/a/a/aa:f	Lorg/apache/http/client/methods/HttpUriRequest;
    //   335: invokeinterface 514 1 0
    //   340: invokevirtual 515	java/net/URI:toString	()Ljava/lang/String;
    //   343: invokevirtual 296	java/lang/StringBuilder:append	(Ljava/lang/String;)Ljava/lang/StringBuilder;
    //   346: pop
    //   347: aload_0
    //   348: getfield 70	com/alipay/b/b/a/a/aa:a	Lcom/alipay/b/b/a/a/v;
    //   351: invokevirtual 502	com/alipay/b/b/a/a/v:a	()Lcom/alipay/b/b/a/a/i;
    //   354: invokevirtual 519	com/alipay/b/b/a/a/i:getParams	()Lorg/apache/http/params/HttpParams;
    //   357: astore_3
    //   358: aload_0
    //   359: getfield 76	com/alipay/b/b/a/a/aa:b	Landroid/content/Context;
    //   362: ldc_w 401
    //   365: invokevirtual 407	android/content/Context:getSystemService	(Ljava/lang/String;)Ljava/lang/Object;
    //   368: checkcast 409	android/net/ConnectivityManager
    //   371: invokevirtual 523	android/net/ConnectivityManager:getActiveNetworkInfo	()Landroid/net/NetworkInfo;
    //   374: astore_1
    //   375: aload_1
    //   376: ifnull +1357 -> 1733
    //   379: aload_1
    //   380: invokevirtual 439	android/net/NetworkInfo:isAvailable	()Z
    //   383: ifeq +1350 -> 1733
    //   386: invokestatic 528	android/net/Proxy:getDefaultHost	()Ljava/lang/String;
    //   389: astore_1
    //   390: invokestatic 531	android/net/Proxy:getDefaultPort	()I
    //   393: istore 5
    //   395: aload_1
    //   396: ifnull +1337 -> 1733
    //   399: new 533	org/apache/http/HttpHost
    //   402: dup
    //   403: aload_1
    //   404: iload 5
    //   406: invokespecial 536	org/apache/http/HttpHost:<init>	(Ljava/lang/String;I)V
    //   409: astore_1
    //   410: aload_1
    //   411: astore_2
    //   412: aload_1
    //   413: ifnull +32 -> 445
    //   416: aload_1
    //   417: astore_2
    //   418: aload_1
    //   419: invokevirtual 539	org/apache/http/HttpHost:getHostName	()Ljava/lang/String;
    //   422: ldc_w 541
    //   425: invokestatic 345	android/text/TextUtils:equals	(Ljava/lang/CharSequence;Ljava/lang/CharSequence;)Z
    //   428: ifeq +17 -> 445
    //   431: aload_1
    //   432: astore_2
    //   433: aload_1
    //   434: invokevirtual 544	org/apache/http/HttpHost:getPort	()I
    //   437: sipush 8087
    //   440: if_icmpne +5 -> 445
    //   443: aconst_null
    //   444: astore_2
    //   445: aload_3
    //   446: ldc_w 546
    //   449: aload_2
    //   450: invokeinterface 552 3 0
    //   455: pop
    //   456: aload_0
    //   457: getfield 554	com/alipay/b/b/a/a/aa:k	Lorg/apache/http/HttpHost;
    //   460: ifnull +302 -> 762
    //   463: aload_0
    //   464: getfield 554	com/alipay/b/b/a/a/aa:k	Lorg/apache/http/HttpHost;
    //   467: astore_1
    //   468: aload_0
    //   469: invokespecial 556	com/alipay/b/b/a/a/aa:g	()I
    //   472: bipush 80
    //   474: if_icmpne +18 -> 492
    //   477: new 533	org/apache/http/HttpHost
    //   480: dup
    //   481: aload_0
    //   482: invokespecial 559	com/alipay/b/b/a/a/aa:h	()Ljava/net/URL;
    //   485: invokevirtual 564	java/net/URL:getHost	()Ljava/lang/String;
    //   488: invokespecial 565	org/apache/http/HttpHost:<init>	(Ljava/lang/String;)V
    //   491: astore_1
    //   492: aload_0
    //   493: getfield 70	com/alipay/b/b/a/a/aa:a	Lcom/alipay/b/b/a/a/v;
    //   496: invokevirtual 502	com/alipay/b/b/a/a/v:a	()Lcom/alipay/b/b/a/a/i;
    //   499: aload_1
    //   500: aload_0
    //   501: getfield 328	com/alipay/b/b/a/a/aa:f	Lorg/apache/http/client/methods/HttpUriRequest;
    //   504: aload_0
    //   505: getfield 55	com/alipay/b/b/a/a/aa:g	Lorg/apache/http/protocol/HttpContext;
    //   508: invokevirtual 569	com/alipay/b/b/a/a/i:execute	(Lorg/apache/http/HttpHost;Lorg/apache/http/HttpRequest;Lorg/apache/http/protocol/HttpContext;)Lorg/apache/http/HttpResponse;
    //   511: astore_2
    //   512: invokestatic 145	java/lang/System:currentTimeMillis	()J
    //   515: lstore 9
    //   517: aload_0
    //   518: getfield 70	com/alipay/b/b/a/a/aa:a	Lcom/alipay/b/b/a/a/v;
    //   521: lload 9
    //   523: lload 7
    //   525: lsub
    //   526: invokevirtual 570	com/alipay/b/b/a/a/v:b	(J)V
    //   529: aload_0
    //   530: getfield 60	com/alipay/b/b/a/a/aa:h	Lorg/apache/http/client/CookieStore;
    //   533: invokeinterface 576 1 0
    //   538: astore_1
    //   539: aload_0
    //   540: getfield 78	com/alipay/b/b/a/a/aa:c	Lcom/alipay/b/b/a/a/y;
    //   543: invokevirtual 578	com/alipay/b/b/a/a/y:e	()Z
    //   546: ifeq +10 -> 556
    //   549: aload_0
    //   550: invokespecial 484	com/alipay/b/b/a/a/aa:i	()Landroid/webkit/CookieManager;
    //   553: invokevirtual 581	android/webkit/CookieManager:removeAllCookie	()V
    //   556: aload_1
    //   557: invokeinterface 584 1 0
    //   562: ifne +236 -> 798
    //   565: aload_1
    //   566: invokeinterface 585 1 0
    //   571: astore_3
    //   572: aload_3
    //   573: invokeinterface 459 1 0
    //   578: ifeq +220 -> 798
    //   581: aload_3
    //   582: invokeinterface 463 1 0
    //   587: checkcast 587	org/apache/http/cookie/Cookie
    //   590: astore_1
    //   591: aload_1
    //   592: invokeinterface 590 1 0
    //   597: ifnull -25 -> 572
    //   600: new 100	java/lang/StringBuilder
    //   603: dup
    //   604: invokespecial 431	java/lang/StringBuilder:<init>	()V
    //   607: aload_1
    //   608: invokeinterface 591 1 0
    //   613: invokevirtual 296	java/lang/StringBuilder:append	(Ljava/lang/String;)Ljava/lang/StringBuilder;
    //   616: ldc -7
    //   618: invokevirtual 296	java/lang/StringBuilder:append	(Ljava/lang/String;)Ljava/lang/StringBuilder;
    //   621: aload_1
    //   622: invokeinterface 592 1 0
    //   627: invokevirtual 296	java/lang/StringBuilder:append	(Ljava/lang/String;)Ljava/lang/StringBuilder;
    //   630: ldc_w 594
    //   633: invokevirtual 296	java/lang/StringBuilder:append	(Ljava/lang/String;)Ljava/lang/StringBuilder;
    //   636: aload_1
    //   637: invokeinterface 590 1 0
    //   642: invokevirtual 296	java/lang/StringBuilder:append	(Ljava/lang/String;)Ljava/lang/StringBuilder;
    //   645: astore 4
    //   647: aload_1
    //   648: invokeinterface 597 1 0
    //   653: ifeq +1100 -> 1753
    //   656: ldc_w 599
    //   659: astore_1
    //   660: aload 4
    //   662: aload_1
    //   663: invokevirtual 296	java/lang/StringBuilder:append	(Ljava/lang/String;)Ljava/lang/StringBuilder;
    //   666: invokevirtual 299	java/lang/StringBuilder:toString	()Ljava/lang/String;
    //   669: astore_1
    //   670: aload_0
    //   671: invokespecial 484	com/alipay/b/b/a/a/aa:i	()Landroid/webkit/CookieManager;
    //   674: aload_0
    //   675: getfield 78	com/alipay/b/b/a/a/aa:c	Lcom/alipay/b/b/a/a/y;
    //   678: invokevirtual 317	com/alipay/b/b/a/a/y:a	()Ljava/lang/String;
    //   681: aload_1
    //   682: invokevirtual 602	android/webkit/CookieManager:setCookie	(Ljava/lang/String;Ljava/lang/String;)V
    //   685: invokestatic 608	android/webkit/CookieSyncManager:getInstance	()Landroid/webkit/CookieSyncManager;
    //   688: invokevirtual 611	android/webkit/CookieSyncManager:sync	()V
    //   691: goto -119 -> 572
    //   694: astore_1
    //   695: aload_0
    //   696: invokespecial 426	com/alipay/b/b/a/a/aa:e	()V
    //   699: aload_0
    //   700: getfield 78	com/alipay/b/b/a/a/aa:c	Lcom/alipay/b/b/a/a/y;
    //   703: invokevirtual 279	com/alipay/b/b/a/a/y:f	()Lcom/alipay/b/b/a/a/g;
    //   706: ifnull +28 -> 734
    //   709: aload_0
    //   710: getfield 78	com/alipay/b/b/a/a/aa:c	Lcom/alipay/b/b/a/a/y;
    //   713: invokevirtual 279	com/alipay/b/b/a/a/y:f	()Lcom/alipay/b/b/a/a/g;
    //   716: pop
    //   717: aload_0
    //   718: getfield 78	com/alipay/b/b/a/a/aa:c	Lcom/alipay/b/b/a/a/y;
    //   721: astore_2
    //   722: new 100	java/lang/StringBuilder
    //   725: dup
    //   726: invokespecial 431	java/lang/StringBuilder:<init>	()V
    //   729: aload_1
    //   730: invokevirtual 434	java/lang/StringBuilder:append	(Ljava/lang/Object;)Ljava/lang/StringBuilder;
    //   733: pop
    //   734: new 100	java/lang/StringBuilder
    //   737: dup
    //   738: invokespecial 431	java/lang/StringBuilder:<init>	()V
    //   741: aload_1
    //   742: invokevirtual 434	java/lang/StringBuilder:append	(Ljava/lang/Object;)Ljava/lang/StringBuilder;
    //   745: pop
    //   746: new 377	com/alipay/b/b/a/a/a
    //   749: dup
    //   750: iconst_2
    //   751: invokestatic 419	java/lang/Integer:valueOf	(I)Ljava/lang/Integer;
    //   754: aload_1
    //   755: invokestatic 614	java/lang/String:valueOf	(Ljava/lang/Object;)Ljava/lang/String;
    //   758: invokespecial 424	com/alipay/b/b/a/a/a:<init>	(Ljava/lang/Integer;Ljava/lang/String;)V
    //   761: athrow
    //   762: aload_0
    //   763: invokespecial 559	com/alipay/b/b/a/a/aa:h	()Ljava/net/URL;
    //   766: astore_1
    //   767: aload_0
    //   768: new 533	org/apache/http/HttpHost
    //   771: dup
    //   772: aload_1
    //   773: invokevirtual 564	java/net/URL:getHost	()Ljava/lang/String;
    //   776: aload_0
    //   777: invokespecial 556	com/alipay/b/b/a/a/aa:g	()I
    //   780: aload_1
    //   781: invokevirtual 617	java/net/URL:getProtocol	()Ljava/lang/String;
    //   784: invokespecial 620	org/apache/http/HttpHost:<init>	(Ljava/lang/String;ILjava/lang/String;)V
    //   787: putfield 554	com/alipay/b/b/a/a/aa:k	Lorg/apache/http/HttpHost;
    //   790: aload_0
    //   791: getfield 554	com/alipay/b/b/a/a/aa:k	Lorg/apache/http/HttpHost;
    //   794: astore_1
    //   795: goto -327 -> 468
    //   798: aload_0
    //   799: getfield 78	com/alipay/b/b/a/a/aa:c	Lcom/alipay/b/b/a/a/y;
    //   802: astore_1
    //   803: aload_2
    //   804: invokeinterface 129 1 0
    //   809: invokeinterface 135 1 0
    //   814: istore 6
    //   816: aload_2
    //   817: invokeinterface 129 1 0
    //   822: invokeinterface 623 1 0
    //   827: astore_1
    //   828: iload 6
    //   830: sipush 200
    //   833: if_icmpeq +126 -> 959
    //   836: iload 6
    //   838: sipush 304
    //   841: if_icmpne +112 -> 953
    //   844: iconst_1
    //   845: istore 5
    //   847: iload 5
    //   849: ifne +110 -> 959
    //   852: new 377	com/alipay/b/b/a/a/a
    //   855: dup
    //   856: aload_2
    //   857: invokeinterface 129 1 0
    //   862: invokeinterface 135 1 0
    //   867: invokestatic 419	java/lang/Integer:valueOf	(I)Ljava/lang/Integer;
    //   870: aload_2
    //   871: invokeinterface 129 1 0
    //   876: invokeinterface 623 1 0
    //   881: invokespecial 424	com/alipay/b/b/a/a/a:<init>	(Ljava/lang/Integer;Ljava/lang/String;)V
    //   884: athrow
    //   885: astore_1
    //   886: aload_0
    //   887: invokespecial 426	com/alipay/b/b/a/a/aa:e	()V
    //   890: aload_0
    //   891: getfield 78	com/alipay/b/b/a/a/aa:c	Lcom/alipay/b/b/a/a/y;
    //   894: invokevirtual 279	com/alipay/b/b/a/a/y:f	()Lcom/alipay/b/b/a/a/g;
    //   897: ifnull +28 -> 925
    //   900: aload_0
    //   901: getfield 78	com/alipay/b/b/a/a/aa:c	Lcom/alipay/b/b/a/a/y;
    //   904: invokevirtual 279	com/alipay/b/b/a/a/y:f	()Lcom/alipay/b/b/a/a/g;
    //   907: pop
    //   908: aload_0
    //   909: getfield 78	com/alipay/b/b/a/a/aa:c	Lcom/alipay/b/b/a/a/y;
    //   912: astore_2
    //   913: new 100	java/lang/StringBuilder
    //   916: dup
    //   917: invokespecial 431	java/lang/StringBuilder:<init>	()V
    //   920: aload_1
    //   921: invokevirtual 434	java/lang/StringBuilder:append	(Ljava/lang/Object;)Ljava/lang/StringBuilder;
    //   924: pop
    //   925: new 100	java/lang/StringBuilder
    //   928: dup
    //   929: invokespecial 431	java/lang/StringBuilder:<init>	()V
    //   932: aload_1
    //   933: invokevirtual 434	java/lang/StringBuilder:append	(Ljava/lang/Object;)Ljava/lang/StringBuilder;
    //   936: pop
    //   937: new 377	com/alipay/b/b/a/a/a
    //   940: dup
    //   941: iconst_2
    //   942: invokestatic 419	java/lang/Integer:valueOf	(I)Ljava/lang/Integer;
    //   945: aload_1
    //   946: invokestatic 614	java/lang/String:valueOf	(Ljava/lang/Object;)Ljava/lang/String;
    //   949: invokespecial 424	com/alipay/b/b/a/a/a:<init>	(Ljava/lang/Integer;Ljava/lang/String;)V
    //   952: athrow
    //   953: iconst_0
    //   954: istore 5
    //   956: goto -109 -> 847
    //   959: aload_0
    //   960: aload_2
    //   961: iload 6
    //   963: aload_1
    //   964: invokespecial 625	com/alipay/b/b/a/a/aa:a	(Lorg/apache/http/HttpResponse;ILjava/lang/String;)Lcom/alipay/b/b/a/a/ae;
    //   967: astore_1
    //   968: ldc2_w 626
    //   971: lstore 9
    //   973: lload 9
    //   975: lstore 7
    //   977: aload_1
    //   978: ifnull +22 -> 1000
    //   981: lload 9
    //   983: lstore 7
    //   985: aload_1
    //   986: invokevirtual 630	com/alipay/b/b/a/a/ae:b	()[B
    //   989: ifnull +11 -> 1000
    //   992: aload_1
    //   993: invokevirtual 630	com/alipay/b/b/a/a/ae:b	()[B
    //   996: arraylength
    //   997: i2l
    //   998: lstore 7
    //   1000: lload 7
    //   1002: ldc2_w 626
    //   1005: lcmp
    //   1006: ifne +29 -> 1035
    //   1009: aload_1
    //   1010: instanceof 164
    //   1013: ifeq +22 -> 1035
    //   1016: aload_1
    //   1017: checkcast 164	com/alipay/b/b/a/a/z
    //   1020: astore_2
    //   1021: aload_2
    //   1022: invokevirtual 633	com/alipay/b/b/a/a/z:a	()Lcom/alipay/b/b/a/a/b;
    //   1025: ldc_w 635
    //   1028: invokevirtual 637	com/alipay/b/b/a/a/b:a	(Ljava/lang/String;)Ljava/lang/String;
    //   1031: invokestatic 95	java/lang/Long:parseLong	(Ljava/lang/String;)J
    //   1034: pop2
    //   1035: aload_0
    //   1036: getfield 78	com/alipay/b/b/a/a/aa:c	Lcom/alipay/b/b/a/a/y;
    //   1039: invokevirtual 317	com/alipay/b/b/a/a/y:a	()Ljava/lang/String;
    //   1042: astore_2
    //   1043: aload_2
    //   1044: ifnull +38 -> 1082
    //   1047: aload_0
    //   1048: invokespecial 509	com/alipay/b/b/a/a/aa:f	()Ljava/lang/String;
    //   1051: invokestatic 640	android/text/TextUtils:isEmpty	(Ljava/lang/CharSequence;)Z
    //   1054: ifne +28 -> 1082
    //   1057: new 100	java/lang/StringBuilder
    //   1060: dup
    //   1061: invokespecial 431	java/lang/StringBuilder:<init>	()V
    //   1064: aload_2
    //   1065: invokevirtual 296	java/lang/StringBuilder:append	(Ljava/lang/String;)Ljava/lang/StringBuilder;
    //   1068: ldc_w 642
    //   1071: invokevirtual 296	java/lang/StringBuilder:append	(Ljava/lang/String;)Ljava/lang/StringBuilder;
    //   1074: aload_0
    //   1075: invokespecial 509	com/alipay/b/b/a/a/aa:f	()Ljava/lang/String;
    //   1078: invokevirtual 296	java/lang/StringBuilder:append	(Ljava/lang/String;)Ljava/lang/StringBuilder;
    //   1081: pop
    //   1082: aload_1
    //   1083: areturn
    //   1084: astore_1
    //   1085: aload_0
    //   1086: invokespecial 426	com/alipay/b/b/a/a/aa:e	()V
    //   1089: aload_0
    //   1090: getfield 78	com/alipay/b/b/a/a/aa:c	Lcom/alipay/b/b/a/a/y;
    //   1093: invokevirtual 279	com/alipay/b/b/a/a/y:f	()Lcom/alipay/b/b/a/a/g;
    //   1096: ifnull +28 -> 1124
    //   1099: aload_0
    //   1100: getfield 78	com/alipay/b/b/a/a/aa:c	Lcom/alipay/b/b/a/a/y;
    //   1103: invokevirtual 279	com/alipay/b/b/a/a/y:f	()Lcom/alipay/b/b/a/a/g;
    //   1106: pop
    //   1107: aload_0
    //   1108: getfield 78	com/alipay/b/b/a/a/aa:c	Lcom/alipay/b/b/a/a/y;
    //   1111: astore_2
    //   1112: new 100	java/lang/StringBuilder
    //   1115: dup
    //   1116: invokespecial 431	java/lang/StringBuilder:<init>	()V
    //   1119: aload_1
    //   1120: invokevirtual 434	java/lang/StringBuilder:append	(Ljava/lang/Object;)Ljava/lang/StringBuilder;
    //   1123: pop
    //   1124: new 100	java/lang/StringBuilder
    //   1127: dup
    //   1128: invokespecial 431	java/lang/StringBuilder:<init>	()V
    //   1131: aload_1
    //   1132: invokevirtual 434	java/lang/StringBuilder:append	(Ljava/lang/Object;)Ljava/lang/StringBuilder;
    //   1135: pop
    //   1136: new 377	com/alipay/b/b/a/a/a
    //   1139: dup
    //   1140: bipush 6
    //   1142: invokestatic 419	java/lang/Integer:valueOf	(I)Ljava/lang/Integer;
    //   1145: aload_1
    //   1146: invokestatic 614	java/lang/String:valueOf	(Ljava/lang/Object;)Ljava/lang/String;
    //   1149: invokespecial 424	com/alipay/b/b/a/a/a:<init>	(Ljava/lang/Integer;Ljava/lang/String;)V
    //   1152: athrow
    //   1153: astore_1
    //   1154: aload_0
    //   1155: invokespecial 426	com/alipay/b/b/a/a/aa:e	()V
    //   1158: aload_0
    //   1159: getfield 78	com/alipay/b/b/a/a/aa:c	Lcom/alipay/b/b/a/a/y;
    //   1162: invokevirtual 279	com/alipay/b/b/a/a/y:f	()Lcom/alipay/b/b/a/a/g;
    //   1165: ifnull +28 -> 1193
    //   1168: aload_0
    //   1169: getfield 78	com/alipay/b/b/a/a/aa:c	Lcom/alipay/b/b/a/a/y;
    //   1172: invokevirtual 279	com/alipay/b/b/a/a/y:f	()Lcom/alipay/b/b/a/a/g;
    //   1175: pop
    //   1176: aload_0
    //   1177: getfield 78	com/alipay/b/b/a/a/aa:c	Lcom/alipay/b/b/a/a/y;
    //   1180: astore_2
    //   1181: new 100	java/lang/StringBuilder
    //   1184: dup
    //   1185: invokespecial 431	java/lang/StringBuilder:<init>	()V
    //   1188: aload_1
    //   1189: invokevirtual 434	java/lang/StringBuilder:append	(Ljava/lang/Object;)Ljava/lang/StringBuilder;
    //   1192: pop
    //   1193: new 100	java/lang/StringBuilder
    //   1196: dup
    //   1197: invokespecial 431	java/lang/StringBuilder:<init>	()V
    //   1200: aload_1
    //   1201: invokevirtual 434	java/lang/StringBuilder:append	(Ljava/lang/Object;)Ljava/lang/StringBuilder;
    //   1204: pop
    //   1205: new 377	com/alipay/b/b/a/a/a
    //   1208: dup
    //   1209: iconst_3
    //   1210: invokestatic 419	java/lang/Integer:valueOf	(I)Ljava/lang/Integer;
    //   1213: aload_1
    //   1214: invokestatic 614	java/lang/String:valueOf	(Ljava/lang/Object;)Ljava/lang/String;
    //   1217: invokespecial 424	com/alipay/b/b/a/a/a:<init>	(Ljava/lang/Integer;Ljava/lang/String;)V
    //   1220: athrow
    //   1221: astore_1
    //   1222: aload_0
    //   1223: invokespecial 426	com/alipay/b/b/a/a/aa:e	()V
    //   1226: aload_0
    //   1227: getfield 78	com/alipay/b/b/a/a/aa:c	Lcom/alipay/b/b/a/a/y;
    //   1230: invokevirtual 279	com/alipay/b/b/a/a/y:f	()Lcom/alipay/b/b/a/a/g;
    //   1233: ifnull +28 -> 1261
    //   1236: aload_0
    //   1237: getfield 78	com/alipay/b/b/a/a/aa:c	Lcom/alipay/b/b/a/a/y;
    //   1240: invokevirtual 279	com/alipay/b/b/a/a/y:f	()Lcom/alipay/b/b/a/a/g;
    //   1243: pop
    //   1244: aload_0
    //   1245: getfield 78	com/alipay/b/b/a/a/aa:c	Lcom/alipay/b/b/a/a/y;
    //   1248: astore_2
    //   1249: new 100	java/lang/StringBuilder
    //   1252: dup
    //   1253: invokespecial 431	java/lang/StringBuilder:<init>	()V
    //   1256: aload_1
    //   1257: invokevirtual 434	java/lang/StringBuilder:append	(Ljava/lang/Object;)Ljava/lang/StringBuilder;
    //   1260: pop
    //   1261: new 100	java/lang/StringBuilder
    //   1264: dup
    //   1265: invokespecial 431	java/lang/StringBuilder:<init>	()V
    //   1268: aload_1
    //   1269: invokevirtual 434	java/lang/StringBuilder:append	(Ljava/lang/Object;)Ljava/lang/StringBuilder;
    //   1272: pop
    //   1273: new 377	com/alipay/b/b/a/a/a
    //   1276: dup
    //   1277: iconst_3
    //   1278: invokestatic 419	java/lang/Integer:valueOf	(I)Ljava/lang/Integer;
    //   1281: aload_1
    //   1282: invokestatic 614	java/lang/String:valueOf	(Ljava/lang/Object;)Ljava/lang/String;
    //   1285: invokespecial 424	com/alipay/b/b/a/a/a:<init>	(Ljava/lang/Integer;Ljava/lang/String;)V
    //   1288: athrow
    //   1289: astore_1
    //   1290: aload_0
    //   1291: invokespecial 426	com/alipay/b/b/a/a/aa:e	()V
    //   1294: aload_0
    //   1295: getfield 78	com/alipay/b/b/a/a/aa:c	Lcom/alipay/b/b/a/a/y;
    //   1298: invokevirtual 279	com/alipay/b/b/a/a/y:f	()Lcom/alipay/b/b/a/a/g;
    //   1301: ifnull +28 -> 1329
    //   1304: aload_0
    //   1305: getfield 78	com/alipay/b/b/a/a/aa:c	Lcom/alipay/b/b/a/a/y;
    //   1308: invokevirtual 279	com/alipay/b/b/a/a/y:f	()Lcom/alipay/b/b/a/a/g;
    //   1311: pop
    //   1312: aload_0
    //   1313: getfield 78	com/alipay/b/b/a/a/aa:c	Lcom/alipay/b/b/a/a/y;
    //   1316: astore_2
    //   1317: new 100	java/lang/StringBuilder
    //   1320: dup
    //   1321: invokespecial 431	java/lang/StringBuilder:<init>	()V
    //   1324: aload_1
    //   1325: invokevirtual 434	java/lang/StringBuilder:append	(Ljava/lang/Object;)Ljava/lang/StringBuilder;
    //   1328: pop
    //   1329: new 100	java/lang/StringBuilder
    //   1332: dup
    //   1333: invokespecial 431	java/lang/StringBuilder:<init>	()V
    //   1336: aload_1
    //   1337: invokevirtual 434	java/lang/StringBuilder:append	(Ljava/lang/Object;)Ljava/lang/StringBuilder;
    //   1340: pop
    //   1341: new 377	com/alipay/b/b/a/a/a
    //   1344: dup
    //   1345: iconst_4
    //   1346: invokestatic 419	java/lang/Integer:valueOf	(I)Ljava/lang/Integer;
    //   1349: aload_1
    //   1350: invokestatic 614	java/lang/String:valueOf	(Ljava/lang/Object;)Ljava/lang/String;
    //   1353: invokespecial 424	com/alipay/b/b/a/a/a:<init>	(Ljava/lang/Integer;Ljava/lang/String;)V
    //   1356: athrow
    //   1357: astore_1
    //   1358: aload_0
    //   1359: invokespecial 426	com/alipay/b/b/a/a/aa:e	()V
    //   1362: aload_0
    //   1363: getfield 78	com/alipay/b/b/a/a/aa:c	Lcom/alipay/b/b/a/a/y;
    //   1366: invokevirtual 279	com/alipay/b/b/a/a/y:f	()Lcom/alipay/b/b/a/a/g;
    //   1369: ifnull +28 -> 1397
    //   1372: aload_0
    //   1373: getfield 78	com/alipay/b/b/a/a/aa:c	Lcom/alipay/b/b/a/a/y;
    //   1376: invokevirtual 279	com/alipay/b/b/a/a/y:f	()Lcom/alipay/b/b/a/a/g;
    //   1379: pop
    //   1380: aload_0
    //   1381: getfield 78	com/alipay/b/b/a/a/aa:c	Lcom/alipay/b/b/a/a/y;
    //   1384: astore_2
    //   1385: new 100	java/lang/StringBuilder
    //   1388: dup
    //   1389: invokespecial 431	java/lang/StringBuilder:<init>	()V
    //   1392: aload_1
    //   1393: invokevirtual 434	java/lang/StringBuilder:append	(Ljava/lang/Object;)Ljava/lang/StringBuilder;
    //   1396: pop
    //   1397: new 100	java/lang/StringBuilder
    //   1400: dup
    //   1401: invokespecial 431	java/lang/StringBuilder:<init>	()V
    //   1404: aload_1
    //   1405: invokevirtual 434	java/lang/StringBuilder:append	(Ljava/lang/Object;)Ljava/lang/StringBuilder;
    //   1408: pop
    //   1409: new 377	com/alipay/b/b/a/a/a
    //   1412: dup
    //   1413: iconst_5
    //   1414: invokestatic 419	java/lang/Integer:valueOf	(I)Ljava/lang/Integer;
    //   1417: aload_1
    //   1418: invokestatic 614	java/lang/String:valueOf	(Ljava/lang/Object;)Ljava/lang/String;
    //   1421: invokespecial 424	com/alipay/b/b/a/a/a:<init>	(Ljava/lang/Integer;Ljava/lang/String;)V
    //   1424: athrow
    //   1425: astore_1
    //   1426: aload_0
    //   1427: invokespecial 426	com/alipay/b/b/a/a/aa:e	()V
    //   1430: aload_0
    //   1431: getfield 78	com/alipay/b/b/a/a/aa:c	Lcom/alipay/b/b/a/a/y;
    //   1434: invokevirtual 279	com/alipay/b/b/a/a/y:f	()Lcom/alipay/b/b/a/a/g;
    //   1437: ifnull +28 -> 1465
    //   1440: aload_0
    //   1441: getfield 78	com/alipay/b/b/a/a/aa:c	Lcom/alipay/b/b/a/a/y;
    //   1444: invokevirtual 279	com/alipay/b/b/a/a/y:f	()Lcom/alipay/b/b/a/a/g;
    //   1447: pop
    //   1448: aload_0
    //   1449: getfield 78	com/alipay/b/b/a/a/aa:c	Lcom/alipay/b/b/a/a/y;
    //   1452: astore_2
    //   1453: new 100	java/lang/StringBuilder
    //   1456: dup
    //   1457: invokespecial 431	java/lang/StringBuilder:<init>	()V
    //   1460: aload_1
    //   1461: invokevirtual 434	java/lang/StringBuilder:append	(Ljava/lang/Object;)Ljava/lang/StringBuilder;
    //   1464: pop
    //   1465: new 377	com/alipay/b/b/a/a/a
    //   1468: dup
    //   1469: bipush 8
    //   1471: invokestatic 419	java/lang/Integer:valueOf	(I)Ljava/lang/Integer;
    //   1474: aload_1
    //   1475: invokestatic 614	java/lang/String:valueOf	(Ljava/lang/Object;)Ljava/lang/String;
    //   1478: invokespecial 424	com/alipay/b/b/a/a/a:<init>	(Ljava/lang/Integer;Ljava/lang/String;)V
    //   1481: athrow
    //   1482: astore_1
    //   1483: aload_0
    //   1484: invokespecial 426	com/alipay/b/b/a/a/aa:e	()V
    //   1487: aload_0
    //   1488: getfield 78	com/alipay/b/b/a/a/aa:c	Lcom/alipay/b/b/a/a/y;
    //   1491: invokevirtual 279	com/alipay/b/b/a/a/y:f	()Lcom/alipay/b/b/a/a/g;
    //   1494: ifnull +28 -> 1522
    //   1497: aload_0
    //   1498: getfield 78	com/alipay/b/b/a/a/aa:c	Lcom/alipay/b/b/a/a/y;
    //   1501: invokevirtual 279	com/alipay/b/b/a/a/y:f	()Lcom/alipay/b/b/a/a/g;
    //   1504: pop
    //   1505: aload_0
    //   1506: getfield 78	com/alipay/b/b/a/a/aa:c	Lcom/alipay/b/b/a/a/y;
    //   1509: astore_2
    //   1510: new 100	java/lang/StringBuilder
    //   1513: dup
    //   1514: invokespecial 431	java/lang/StringBuilder:<init>	()V
    //   1517: aload_1
    //   1518: invokevirtual 434	java/lang/StringBuilder:append	(Ljava/lang/Object;)Ljava/lang/StringBuilder;
    //   1521: pop
    //   1522: new 100	java/lang/StringBuilder
    //   1525: dup
    //   1526: invokespecial 431	java/lang/StringBuilder:<init>	()V
    //   1529: aload_1
    //   1530: invokevirtual 434	java/lang/StringBuilder:append	(Ljava/lang/Object;)Ljava/lang/StringBuilder;
    //   1533: pop
    //   1534: new 377	com/alipay/b/b/a/a/a
    //   1537: dup
    //   1538: bipush 9
    //   1540: invokestatic 419	java/lang/Integer:valueOf	(I)Ljava/lang/Integer;
    //   1543: aload_1
    //   1544: invokestatic 614	java/lang/String:valueOf	(Ljava/lang/Object;)Ljava/lang/String;
    //   1547: invokespecial 424	com/alipay/b/b/a/a/a:<init>	(Ljava/lang/Integer;Ljava/lang/String;)V
    //   1550: athrow
    //   1551: astore_1
    //   1552: aload_0
    //   1553: invokespecial 426	com/alipay/b/b/a/a/aa:e	()V
    //   1556: aload_0
    //   1557: getfield 78	com/alipay/b/b/a/a/aa:c	Lcom/alipay/b/b/a/a/y;
    //   1560: invokevirtual 279	com/alipay/b/b/a/a/y:f	()Lcom/alipay/b/b/a/a/g;
    //   1563: ifnull +28 -> 1591
    //   1566: aload_0
    //   1567: getfield 78	com/alipay/b/b/a/a/aa:c	Lcom/alipay/b/b/a/a/y;
    //   1570: invokevirtual 279	com/alipay/b/b/a/a/y:f	()Lcom/alipay/b/b/a/a/g;
    //   1573: pop
    //   1574: aload_0
    //   1575: getfield 78	com/alipay/b/b/a/a/aa:c	Lcom/alipay/b/b/a/a/y;
    //   1578: astore_2
    //   1579: new 100	java/lang/StringBuilder
    //   1582: dup
    //   1583: invokespecial 431	java/lang/StringBuilder:<init>	()V
    //   1586: aload_1
    //   1587: invokevirtual 434	java/lang/StringBuilder:append	(Ljava/lang/Object;)Ljava/lang/StringBuilder;
    //   1590: pop
    //   1591: new 100	java/lang/StringBuilder
    //   1594: dup
    //   1595: invokespecial 431	java/lang/StringBuilder:<init>	()V
    //   1598: aload_1
    //   1599: invokevirtual 434	java/lang/StringBuilder:append	(Ljava/lang/Object;)Ljava/lang/StringBuilder;
    //   1602: pop
    //   1603: new 377	com/alipay/b/b/a/a/a
    //   1606: dup
    //   1607: bipush 6
    //   1609: invokestatic 419	java/lang/Integer:valueOf	(I)Ljava/lang/Integer;
    //   1612: aload_1
    //   1613: invokestatic 614	java/lang/String:valueOf	(Ljava/lang/Object;)Ljava/lang/String;
    //   1616: invokespecial 424	com/alipay/b/b/a/a/a:<init>	(Ljava/lang/Integer;Ljava/lang/String;)V
    //   1619: athrow
    //   1620: astore_1
    //   1621: aload_0
    //   1622: invokespecial 426	com/alipay/b/b/a/a/aa:e	()V
    //   1625: aload_0
    //   1626: getfield 62	com/alipay/b/b/a/a/aa:m	I
    //   1629: ifgt +16 -> 1645
    //   1632: aload_0
    //   1633: aload_0
    //   1634: getfield 62	com/alipay/b/b/a/a/aa:m	I
    //   1637: iconst_1
    //   1638: iadd
    //   1639: putfield 62	com/alipay/b/b/a/a/aa:m	I
    //   1642: goto -1642 -> 0
    //   1645: new 100	java/lang/StringBuilder
    //   1648: dup
    //   1649: invokespecial 431	java/lang/StringBuilder:<init>	()V
    //   1652: aload_1
    //   1653: invokevirtual 434	java/lang/StringBuilder:append	(Ljava/lang/Object;)Ljava/lang/StringBuilder;
    //   1656: pop
    //   1657: new 377	com/alipay/b/b/a/a/a
    //   1660: dup
    //   1661: iconst_0
    //   1662: invokestatic 419	java/lang/Integer:valueOf	(I)Ljava/lang/Integer;
    //   1665: aload_1
    //   1666: invokestatic 614	java/lang/String:valueOf	(Ljava/lang/Object;)Ljava/lang/String;
    //   1669: invokespecial 424	com/alipay/b/b/a/a/a:<init>	(Ljava/lang/Integer;Ljava/lang/String;)V
    //   1672: athrow
    //   1673: astore_1
    //   1674: aload_0
    //   1675: invokespecial 426	com/alipay/b/b/a/a/aa:e	()V
    //   1678: aload_0
    //   1679: getfield 78	com/alipay/b/b/a/a/aa:c	Lcom/alipay/b/b/a/a/y;
    //   1682: invokevirtual 279	com/alipay/b/b/a/a/y:f	()Lcom/alipay/b/b/a/a/g;
    //   1685: ifnull +28 -> 1713
    //   1688: aload_0
    //   1689: getfield 78	com/alipay/b/b/a/a/aa:c	Lcom/alipay/b/b/a/a/y;
    //   1692: invokevirtual 279	com/alipay/b/b/a/a/y:f	()Lcom/alipay/b/b/a/a/g;
    //   1695: pop
    //   1696: aload_0
    //   1697: getfield 78	com/alipay/b/b/a/a/aa:c	Lcom/alipay/b/b/a/a/y;
    //   1700: astore_2
    //   1701: new 100	java/lang/StringBuilder
    //   1704: dup
    //   1705: invokespecial 431	java/lang/StringBuilder:<init>	()V
    //   1708: aload_1
    //   1709: invokevirtual 434	java/lang/StringBuilder:append	(Ljava/lang/Object;)Ljava/lang/StringBuilder;
    //   1712: pop
    //   1713: new 377	com/alipay/b/b/a/a/a
    //   1716: dup
    //   1717: iconst_0
    //   1718: invokestatic 419	java/lang/Integer:valueOf	(I)Ljava/lang/Integer;
    //   1721: aload_1
    //   1722: invokestatic 614	java/lang/String:valueOf	(Ljava/lang/Object;)Ljava/lang/String;
    //   1725: invokespecial 424	com/alipay/b/b/a/a/a:<init>	(Ljava/lang/Integer;Ljava/lang/String;)V
    //   1728: athrow
    //   1729: astore_2
    //   1730: goto -695 -> 1035
    //   1733: aconst_null
    //   1734: astore_1
    //   1735: goto -1325 -> 410
    //   1738: iconst_0
    //   1739: istore 5
    //   1741: goto -1717 -> 24
    //   1744: iload 5
    //   1746: iconst_1
    //   1747: iadd
    //   1748: istore 5
    //   1750: goto -1647 -> 103
    //   1753: ldc_w 644
    //   1756: astore_1
    //   1757: goto -1097 -> 660
    // Local variable table:
    //   start	length	slot	name	signature
    //   0	1760	0	this	aa
    //   16	2	1	arrayOfNetworkInfo	android.net.NetworkInfo[]
    //   44	67	1	locala	a
    //   161	35	1	localObject1	Object
    //   218	9	1	localURISyntaxException	java.net.URISyntaxException
    //   374	308	1	localObject2	Object
    //   694	61	1	localSSLHandshakeException	javax.net.ssl.SSLHandshakeException
    //   766	62	1	localObject3	Object
    //   885	79	1	localSSLPeerUnverifiedException	javax.net.ssl.SSLPeerUnverifiedException
    //   967	116	1	localae	ae
    //   1084	62	1	localSSLException	javax.net.ssl.SSLException
    //   1153	61	1	localConnectionPoolTimeoutException	org.apache.http.conn.ConnectionPoolTimeoutException
    //   1221	61	1	localConnectTimeoutException	org.apache.http.conn.ConnectTimeoutException
    //   1289	61	1	localSocketTimeoutException	java.net.SocketTimeoutException
    //   1357	61	1	localNoHttpResponseException	org.apache.http.NoHttpResponseException
    //   1425	50	1	localHttpHostConnectException	org.apache.http.conn.HttpHostConnectException
    //   1482	62	1	localUnknownHostException	java.net.UnknownHostException
    //   1551	62	1	localIOException	IOException
    //   1620	46	1	localNullPointerException	NullPointerException
    //   1673	49	1	localException1	Exception
    //   1734	23	1	str	String
    //   71	1630	2	localObject4	Object
    //   1729	1	2	localException2	Exception
    //   357	225	3	localObject5	Object
    //   645	16	4	localStringBuilder	StringBuilder
    //   22	1727	5	i1	int
    //   98	864	6	i2	int
    //   306	695	7	l1	long
    //   515	467	9	l2	long
    // Exception table:
    //   from	to	target	type
    //   0	17	44	com/alipay/b/b/a/a/a
    //   29	44	44	com/alipay/b/b/a/a/a
    //   96	100	44	com/alipay/b/b/a/a/a
    //   119	133	44	com/alipay/b/b/a/a/a
    //   139	162	44	com/alipay/b/b/a/a/a
    //   162	170	44	com/alipay/b/b/a/a/a
    //   174	186	44	com/alipay/b/b/a/a/a
    //   186	215	44	com/alipay/b/b/a/a/a
    //   234	375	44	com/alipay/b/b/a/a/a
    //   379	395	44	com/alipay/b/b/a/a/a
    //   399	410	44	com/alipay/b/b/a/a/a
    //   418	431	44	com/alipay/b/b/a/a/a
    //   433	443	44	com/alipay/b/b/a/a/a
    //   445	468	44	com/alipay/b/b/a/a/a
    //   468	492	44	com/alipay/b/b/a/a/a
    //   492	556	44	com/alipay/b/b/a/a/a
    //   556	572	44	com/alipay/b/b/a/a/a
    //   572	656	44	com/alipay/b/b/a/a/a
    //   660	691	44	com/alipay/b/b/a/a/a
    //   762	795	44	com/alipay/b/b/a/a/a
    //   798	828	44	com/alipay/b/b/a/a/a
    //   852	885	44	com/alipay/b/b/a/a/a
    //   959	968	44	com/alipay/b/b/a/a/a
    //   985	1000	44	com/alipay/b/b/a/a/a
    //   1009	1021	44	com/alipay/b/b/a/a/a
    //   1021	1035	44	com/alipay/b/b/a/a/a
    //   1035	1043	44	com/alipay/b/b/a/a/a
    //   1047	1082	44	com/alipay/b/b/a/a/a
    //   0	17	218	java/net/URISyntaxException
    //   29	44	218	java/net/URISyntaxException
    //   96	100	218	java/net/URISyntaxException
    //   119	133	218	java/net/URISyntaxException
    //   139	162	218	java/net/URISyntaxException
    //   162	170	218	java/net/URISyntaxException
    //   174	186	218	java/net/URISyntaxException
    //   186	215	218	java/net/URISyntaxException
    //   234	375	218	java/net/URISyntaxException
    //   379	395	218	java/net/URISyntaxException
    //   399	410	218	java/net/URISyntaxException
    //   418	431	218	java/net/URISyntaxException
    //   433	443	218	java/net/URISyntaxException
    //   445	468	218	java/net/URISyntaxException
    //   468	492	218	java/net/URISyntaxException
    //   492	556	218	java/net/URISyntaxException
    //   556	572	218	java/net/URISyntaxException
    //   572	656	218	java/net/URISyntaxException
    //   660	691	218	java/net/URISyntaxException
    //   762	795	218	java/net/URISyntaxException
    //   798	828	218	java/net/URISyntaxException
    //   852	885	218	java/net/URISyntaxException
    //   959	968	218	java/net/URISyntaxException
    //   985	1000	218	java/net/URISyntaxException
    //   1009	1021	218	java/net/URISyntaxException
    //   1021	1035	218	java/net/URISyntaxException
    //   1035	1043	218	java/net/URISyntaxException
    //   1047	1082	218	java/net/URISyntaxException
    //   0	17	694	javax/net/ssl/SSLHandshakeException
    //   29	44	694	javax/net/ssl/SSLHandshakeException
    //   96	100	694	javax/net/ssl/SSLHandshakeException
    //   119	133	694	javax/net/ssl/SSLHandshakeException
    //   139	162	694	javax/net/ssl/SSLHandshakeException
    //   162	170	694	javax/net/ssl/SSLHandshakeException
    //   174	186	694	javax/net/ssl/SSLHandshakeException
    //   186	215	694	javax/net/ssl/SSLHandshakeException
    //   234	375	694	javax/net/ssl/SSLHandshakeException
    //   379	395	694	javax/net/ssl/SSLHandshakeException
    //   399	410	694	javax/net/ssl/SSLHandshakeException
    //   418	431	694	javax/net/ssl/SSLHandshakeException
    //   433	443	694	javax/net/ssl/SSLHandshakeException
    //   445	468	694	javax/net/ssl/SSLHandshakeException
    //   468	492	694	javax/net/ssl/SSLHandshakeException
    //   492	556	694	javax/net/ssl/SSLHandshakeException
    //   556	572	694	javax/net/ssl/SSLHandshakeException
    //   572	656	694	javax/net/ssl/SSLHandshakeException
    //   660	691	694	javax/net/ssl/SSLHandshakeException
    //   762	795	694	javax/net/ssl/SSLHandshakeException
    //   798	828	694	javax/net/ssl/SSLHandshakeException
    //   852	885	694	javax/net/ssl/SSLHandshakeException
    //   959	968	694	javax/net/ssl/SSLHandshakeException
    //   985	1000	694	javax/net/ssl/SSLHandshakeException
    //   1009	1021	694	javax/net/ssl/SSLHandshakeException
    //   1021	1035	694	javax/net/ssl/SSLHandshakeException
    //   1035	1043	694	javax/net/ssl/SSLHandshakeException
    //   1047	1082	694	javax/net/ssl/SSLHandshakeException
    //   0	17	885	javax/net/ssl/SSLPeerUnverifiedException
    //   29	44	885	javax/net/ssl/SSLPeerUnverifiedException
    //   96	100	885	javax/net/ssl/SSLPeerUnverifiedException
    //   119	133	885	javax/net/ssl/SSLPeerUnverifiedException
    //   139	162	885	javax/net/ssl/SSLPeerUnverifiedException
    //   162	170	885	javax/net/ssl/SSLPeerUnverifiedException
    //   174	186	885	javax/net/ssl/SSLPeerUnverifiedException
    //   186	215	885	javax/net/ssl/SSLPeerUnverifiedException
    //   234	375	885	javax/net/ssl/SSLPeerUnverifiedException
    //   379	395	885	javax/net/ssl/SSLPeerUnverifiedException
    //   399	410	885	javax/net/ssl/SSLPeerUnverifiedException
    //   418	431	885	javax/net/ssl/SSLPeerUnverifiedException
    //   433	443	885	javax/net/ssl/SSLPeerUnverifiedException
    //   445	468	885	javax/net/ssl/SSLPeerUnverifiedException
    //   468	492	885	javax/net/ssl/SSLPeerUnverifiedException
    //   492	556	885	javax/net/ssl/SSLPeerUnverifiedException
    //   556	572	885	javax/net/ssl/SSLPeerUnverifiedException
    //   572	656	885	javax/net/ssl/SSLPeerUnverifiedException
    //   660	691	885	javax/net/ssl/SSLPeerUnverifiedException
    //   762	795	885	javax/net/ssl/SSLPeerUnverifiedException
    //   798	828	885	javax/net/ssl/SSLPeerUnverifiedException
    //   852	885	885	javax/net/ssl/SSLPeerUnverifiedException
    //   959	968	885	javax/net/ssl/SSLPeerUnverifiedException
    //   985	1000	885	javax/net/ssl/SSLPeerUnverifiedException
    //   1009	1021	885	javax/net/ssl/SSLPeerUnverifiedException
    //   1021	1035	885	javax/net/ssl/SSLPeerUnverifiedException
    //   1035	1043	885	javax/net/ssl/SSLPeerUnverifiedException
    //   1047	1082	885	javax/net/ssl/SSLPeerUnverifiedException
    //   0	17	1084	javax/net/ssl/SSLException
    //   29	44	1084	javax/net/ssl/SSLException
    //   96	100	1084	javax/net/ssl/SSLException
    //   119	133	1084	javax/net/ssl/SSLException
    //   139	162	1084	javax/net/ssl/SSLException
    //   162	170	1084	javax/net/ssl/SSLException
    //   174	186	1084	javax/net/ssl/SSLException
    //   186	215	1084	javax/net/ssl/SSLException
    //   234	375	1084	javax/net/ssl/SSLException
    //   379	395	1084	javax/net/ssl/SSLException
    //   399	410	1084	javax/net/ssl/SSLException
    //   418	431	1084	javax/net/ssl/SSLException
    //   433	443	1084	javax/net/ssl/SSLException
    //   445	468	1084	javax/net/ssl/SSLException
    //   468	492	1084	javax/net/ssl/SSLException
    //   492	556	1084	javax/net/ssl/SSLException
    //   556	572	1084	javax/net/ssl/SSLException
    //   572	656	1084	javax/net/ssl/SSLException
    //   660	691	1084	javax/net/ssl/SSLException
    //   762	795	1084	javax/net/ssl/SSLException
    //   798	828	1084	javax/net/ssl/SSLException
    //   852	885	1084	javax/net/ssl/SSLException
    //   959	968	1084	javax/net/ssl/SSLException
    //   985	1000	1084	javax/net/ssl/SSLException
    //   1009	1021	1084	javax/net/ssl/SSLException
    //   1021	1035	1084	javax/net/ssl/SSLException
    //   1035	1043	1084	javax/net/ssl/SSLException
    //   1047	1082	1084	javax/net/ssl/SSLException
    //   0	17	1153	org/apache/http/conn/ConnectionPoolTimeoutException
    //   29	44	1153	org/apache/http/conn/ConnectionPoolTimeoutException
    //   96	100	1153	org/apache/http/conn/ConnectionPoolTimeoutException
    //   119	133	1153	org/apache/http/conn/ConnectionPoolTimeoutException
    //   139	162	1153	org/apache/http/conn/ConnectionPoolTimeoutException
    //   162	170	1153	org/apache/http/conn/ConnectionPoolTimeoutException
    //   174	186	1153	org/apache/http/conn/ConnectionPoolTimeoutException
    //   186	215	1153	org/apache/http/conn/ConnectionPoolTimeoutException
    //   234	375	1153	org/apache/http/conn/ConnectionPoolTimeoutException
    //   379	395	1153	org/apache/http/conn/ConnectionPoolTimeoutException
    //   399	410	1153	org/apache/http/conn/ConnectionPoolTimeoutException
    //   418	431	1153	org/apache/http/conn/ConnectionPoolTimeoutException
    //   433	443	1153	org/apache/http/conn/ConnectionPoolTimeoutException
    //   445	468	1153	org/apache/http/conn/ConnectionPoolTimeoutException
    //   468	492	1153	org/apache/http/conn/ConnectionPoolTimeoutException
    //   492	556	1153	org/apache/http/conn/ConnectionPoolTimeoutException
    //   556	572	1153	org/apache/http/conn/ConnectionPoolTimeoutException
    //   572	656	1153	org/apache/http/conn/ConnectionPoolTimeoutException
    //   660	691	1153	org/apache/http/conn/ConnectionPoolTimeoutException
    //   762	795	1153	org/apache/http/conn/ConnectionPoolTimeoutException
    //   798	828	1153	org/apache/http/conn/ConnectionPoolTimeoutException
    //   852	885	1153	org/apache/http/conn/ConnectionPoolTimeoutException
    //   959	968	1153	org/apache/http/conn/ConnectionPoolTimeoutException
    //   985	1000	1153	org/apache/http/conn/ConnectionPoolTimeoutException
    //   1009	1021	1153	org/apache/http/conn/ConnectionPoolTimeoutException
    //   1021	1035	1153	org/apache/http/conn/ConnectionPoolTimeoutException
    //   1035	1043	1153	org/apache/http/conn/ConnectionPoolTimeoutException
    //   1047	1082	1153	org/apache/http/conn/ConnectionPoolTimeoutException
    //   0	17	1221	org/apache/http/conn/ConnectTimeoutException
    //   29	44	1221	org/apache/http/conn/ConnectTimeoutException
    //   96	100	1221	org/apache/http/conn/ConnectTimeoutException
    //   119	133	1221	org/apache/http/conn/ConnectTimeoutException
    //   139	162	1221	org/apache/http/conn/ConnectTimeoutException
    //   162	170	1221	org/apache/http/conn/ConnectTimeoutException
    //   174	186	1221	org/apache/http/conn/ConnectTimeoutException
    //   186	215	1221	org/apache/http/conn/ConnectTimeoutException
    //   234	375	1221	org/apache/http/conn/ConnectTimeoutException
    //   379	395	1221	org/apache/http/conn/ConnectTimeoutException
    //   399	410	1221	org/apache/http/conn/ConnectTimeoutException
    //   418	431	1221	org/apache/http/conn/ConnectTimeoutException
    //   433	443	1221	org/apache/http/conn/ConnectTimeoutException
    //   445	468	1221	org/apache/http/conn/ConnectTimeoutException
    //   468	492	1221	org/apache/http/conn/ConnectTimeoutException
    //   492	556	1221	org/apache/http/conn/ConnectTimeoutException
    //   556	572	1221	org/apache/http/conn/ConnectTimeoutException
    //   572	656	1221	org/apache/http/conn/ConnectTimeoutException
    //   660	691	1221	org/apache/http/conn/ConnectTimeoutException
    //   762	795	1221	org/apache/http/conn/ConnectTimeoutException
    //   798	828	1221	org/apache/http/conn/ConnectTimeoutException
    //   852	885	1221	org/apache/http/conn/ConnectTimeoutException
    //   959	968	1221	org/apache/http/conn/ConnectTimeoutException
    //   985	1000	1221	org/apache/http/conn/ConnectTimeoutException
    //   1009	1021	1221	org/apache/http/conn/ConnectTimeoutException
    //   1021	1035	1221	org/apache/http/conn/ConnectTimeoutException
    //   1035	1043	1221	org/apache/http/conn/ConnectTimeoutException
    //   1047	1082	1221	org/apache/http/conn/ConnectTimeoutException
    //   0	17	1289	java/net/SocketTimeoutException
    //   29	44	1289	java/net/SocketTimeoutException
    //   96	100	1289	java/net/SocketTimeoutException
    //   119	133	1289	java/net/SocketTimeoutException
    //   139	162	1289	java/net/SocketTimeoutException
    //   162	170	1289	java/net/SocketTimeoutException
    //   174	186	1289	java/net/SocketTimeoutException
    //   186	215	1289	java/net/SocketTimeoutException
    //   234	375	1289	java/net/SocketTimeoutException
    //   379	395	1289	java/net/SocketTimeoutException
    //   399	410	1289	java/net/SocketTimeoutException
    //   418	431	1289	java/net/SocketTimeoutException
    //   433	443	1289	java/net/SocketTimeoutException
    //   445	468	1289	java/net/SocketTimeoutException
    //   468	492	1289	java/net/SocketTimeoutException
    //   492	556	1289	java/net/SocketTimeoutException
    //   556	572	1289	java/net/SocketTimeoutException
    //   572	656	1289	java/net/SocketTimeoutException
    //   660	691	1289	java/net/SocketTimeoutException
    //   762	795	1289	java/net/SocketTimeoutException
    //   798	828	1289	java/net/SocketTimeoutException
    //   852	885	1289	java/net/SocketTimeoutException
    //   959	968	1289	java/net/SocketTimeoutException
    //   985	1000	1289	java/net/SocketTimeoutException
    //   1009	1021	1289	java/net/SocketTimeoutException
    //   1021	1035	1289	java/net/SocketTimeoutException
    //   1035	1043	1289	java/net/SocketTimeoutException
    //   1047	1082	1289	java/net/SocketTimeoutException
    //   0	17	1357	org/apache/http/NoHttpResponseException
    //   29	44	1357	org/apache/http/NoHttpResponseException
    //   96	100	1357	org/apache/http/NoHttpResponseException
    //   119	133	1357	org/apache/http/NoHttpResponseException
    //   139	162	1357	org/apache/http/NoHttpResponseException
    //   162	170	1357	org/apache/http/NoHttpResponseException
    //   174	186	1357	org/apache/http/NoHttpResponseException
    //   186	215	1357	org/apache/http/NoHttpResponseException
    //   234	375	1357	org/apache/http/NoHttpResponseException
    //   379	395	1357	org/apache/http/NoHttpResponseException
    //   399	410	1357	org/apache/http/NoHttpResponseException
    //   418	431	1357	org/apache/http/NoHttpResponseException
    //   433	443	1357	org/apache/http/NoHttpResponseException
    //   445	468	1357	org/apache/http/NoHttpResponseException
    //   468	492	1357	org/apache/http/NoHttpResponseException
    //   492	556	1357	org/apache/http/NoHttpResponseException
    //   556	572	1357	org/apache/http/NoHttpResponseException
    //   572	656	1357	org/apache/http/NoHttpResponseException
    //   660	691	1357	org/apache/http/NoHttpResponseException
    //   762	795	1357	org/apache/http/NoHttpResponseException
    //   798	828	1357	org/apache/http/NoHttpResponseException
    //   852	885	1357	org/apache/http/NoHttpResponseException
    //   959	968	1357	org/apache/http/NoHttpResponseException
    //   985	1000	1357	org/apache/http/NoHttpResponseException
    //   1009	1021	1357	org/apache/http/NoHttpResponseException
    //   1021	1035	1357	org/apache/http/NoHttpResponseException
    //   1035	1043	1357	org/apache/http/NoHttpResponseException
    //   1047	1082	1357	org/apache/http/NoHttpResponseException
    //   0	17	1425	org/apache/http/conn/HttpHostConnectException
    //   29	44	1425	org/apache/http/conn/HttpHostConnectException
    //   96	100	1425	org/apache/http/conn/HttpHostConnectException
    //   119	133	1425	org/apache/http/conn/HttpHostConnectException
    //   139	162	1425	org/apache/http/conn/HttpHostConnectException
    //   162	170	1425	org/apache/http/conn/HttpHostConnectException
    //   174	186	1425	org/apache/http/conn/HttpHostConnectException
    //   186	215	1425	org/apache/http/conn/HttpHostConnectException
    //   234	375	1425	org/apache/http/conn/HttpHostConnectException
    //   379	395	1425	org/apache/http/conn/HttpHostConnectException
    //   399	410	1425	org/apache/http/conn/HttpHostConnectException
    //   418	431	1425	org/apache/http/conn/HttpHostConnectException
    //   433	443	1425	org/apache/http/conn/HttpHostConnectException
    //   445	468	1425	org/apache/http/conn/HttpHostConnectException
    //   468	492	1425	org/apache/http/conn/HttpHostConnectException
    //   492	556	1425	org/apache/http/conn/HttpHostConnectException
    //   556	572	1425	org/apache/http/conn/HttpHostConnectException
    //   572	656	1425	org/apache/http/conn/HttpHostConnectException
    //   660	691	1425	org/apache/http/conn/HttpHostConnectException
    //   762	795	1425	org/apache/http/conn/HttpHostConnectException
    //   798	828	1425	org/apache/http/conn/HttpHostConnectException
    //   852	885	1425	org/apache/http/conn/HttpHostConnectException
    //   959	968	1425	org/apache/http/conn/HttpHostConnectException
    //   985	1000	1425	org/apache/http/conn/HttpHostConnectException
    //   1009	1021	1425	org/apache/http/conn/HttpHostConnectException
    //   1021	1035	1425	org/apache/http/conn/HttpHostConnectException
    //   1035	1043	1425	org/apache/http/conn/HttpHostConnectException
    //   1047	1082	1425	org/apache/http/conn/HttpHostConnectException
    //   0	17	1482	java/net/UnknownHostException
    //   29	44	1482	java/net/UnknownHostException
    //   96	100	1482	java/net/UnknownHostException
    //   119	133	1482	java/net/UnknownHostException
    //   139	162	1482	java/net/UnknownHostException
    //   162	170	1482	java/net/UnknownHostException
    //   174	186	1482	java/net/UnknownHostException
    //   186	215	1482	java/net/UnknownHostException
    //   234	375	1482	java/net/UnknownHostException
    //   379	395	1482	java/net/UnknownHostException
    //   399	410	1482	java/net/UnknownHostException
    //   418	431	1482	java/net/UnknownHostException
    //   433	443	1482	java/net/UnknownHostException
    //   445	468	1482	java/net/UnknownHostException
    //   468	492	1482	java/net/UnknownHostException
    //   492	556	1482	java/net/UnknownHostException
    //   556	572	1482	java/net/UnknownHostException
    //   572	656	1482	java/net/UnknownHostException
    //   660	691	1482	java/net/UnknownHostException
    //   762	795	1482	java/net/UnknownHostException
    //   798	828	1482	java/net/UnknownHostException
    //   852	885	1482	java/net/UnknownHostException
    //   959	968	1482	java/net/UnknownHostException
    //   985	1000	1482	java/net/UnknownHostException
    //   1009	1021	1482	java/net/UnknownHostException
    //   1021	1035	1482	java/net/UnknownHostException
    //   1035	1043	1482	java/net/UnknownHostException
    //   1047	1082	1482	java/net/UnknownHostException
    //   0	17	1551	java/io/IOException
    //   29	44	1551	java/io/IOException
    //   96	100	1551	java/io/IOException
    //   119	133	1551	java/io/IOException
    //   139	162	1551	java/io/IOException
    //   162	170	1551	java/io/IOException
    //   174	186	1551	java/io/IOException
    //   186	215	1551	java/io/IOException
    //   234	375	1551	java/io/IOException
    //   379	395	1551	java/io/IOException
    //   399	410	1551	java/io/IOException
    //   418	431	1551	java/io/IOException
    //   433	443	1551	java/io/IOException
    //   445	468	1551	java/io/IOException
    //   468	492	1551	java/io/IOException
    //   492	556	1551	java/io/IOException
    //   556	572	1551	java/io/IOException
    //   572	656	1551	java/io/IOException
    //   660	691	1551	java/io/IOException
    //   762	795	1551	java/io/IOException
    //   798	828	1551	java/io/IOException
    //   852	885	1551	java/io/IOException
    //   959	968	1551	java/io/IOException
    //   985	1000	1551	java/io/IOException
    //   1009	1021	1551	java/io/IOException
    //   1021	1035	1551	java/io/IOException
    //   1035	1043	1551	java/io/IOException
    //   1047	1082	1551	java/io/IOException
    //   0	17	1620	java/lang/NullPointerException
    //   29	44	1620	java/lang/NullPointerException
    //   96	100	1620	java/lang/NullPointerException
    //   119	133	1620	java/lang/NullPointerException
    //   139	162	1620	java/lang/NullPointerException
    //   162	170	1620	java/lang/NullPointerException
    //   174	186	1620	java/lang/NullPointerException
    //   186	215	1620	java/lang/NullPointerException
    //   234	375	1620	java/lang/NullPointerException
    //   379	395	1620	java/lang/NullPointerException
    //   399	410	1620	java/lang/NullPointerException
    //   418	431	1620	java/lang/NullPointerException
    //   433	443	1620	java/lang/NullPointerException
    //   445	468	1620	java/lang/NullPointerException
    //   468	492	1620	java/lang/NullPointerException
    //   492	556	1620	java/lang/NullPointerException
    //   556	572	1620	java/lang/NullPointerException
    //   572	656	1620	java/lang/NullPointerException
    //   660	691	1620	java/lang/NullPointerException
    //   762	795	1620	java/lang/NullPointerException
    //   798	828	1620	java/lang/NullPointerException
    //   852	885	1620	java/lang/NullPointerException
    //   959	968	1620	java/lang/NullPointerException
    //   985	1000	1620	java/lang/NullPointerException
    //   1009	1021	1620	java/lang/NullPointerException
    //   1021	1035	1620	java/lang/NullPointerException
    //   1035	1043	1620	java/lang/NullPointerException
    //   1047	1082	1620	java/lang/NullPointerException
    //   0	17	1673	java/lang/Exception
    //   29	44	1673	java/lang/Exception
    //   96	100	1673	java/lang/Exception
    //   119	133	1673	java/lang/Exception
    //   139	162	1673	java/lang/Exception
    //   162	170	1673	java/lang/Exception
    //   174	186	1673	java/lang/Exception
    //   186	215	1673	java/lang/Exception
    //   234	375	1673	java/lang/Exception
    //   379	395	1673	java/lang/Exception
    //   399	410	1673	java/lang/Exception
    //   418	431	1673	java/lang/Exception
    //   433	443	1673	java/lang/Exception
    //   445	468	1673	java/lang/Exception
    //   468	492	1673	java/lang/Exception
    //   492	556	1673	java/lang/Exception
    //   556	572	1673	java/lang/Exception
    //   572	656	1673	java/lang/Exception
    //   660	691	1673	java/lang/Exception
    //   762	795	1673	java/lang/Exception
    //   798	828	1673	java/lang/Exception
    //   852	885	1673	java/lang/Exception
    //   959	968	1673	java/lang/Exception
    //   985	1000	1673	java/lang/Exception
    //   1009	1021	1673	java/lang/Exception
    //   1035	1043	1673	java/lang/Exception
    //   1047	1082	1673	java/lang/Exception
    //   1021	1035	1729	java/lang/Exception
  }
  
  private void e()
  {
    if (this.f != null) {
      this.f.abort();
    }
  }
  
  private String f()
  {
    if (!TextUtils.isEmpty(this.q)) {
      return this.q;
    }
    this.q = this.c.b("operationType");
    return this.q;
  }
  
  private int g()
  {
    URL localURL = h();
    if (localURL.getPort() == -1) {
      return localURL.getDefaultPort();
    }
    return localURL.getPort();
  }
  
  private URL h()
  {
    if (this.l != null) {
      return this.l;
    }
    this.l = new URL(this.c.a());
    return this.l;
  }
  
  private CookieManager i()
  {
    if (this.i != null) {
      return this.i;
    }
    this.i = CookieManager.getInstance();
    return this.i;
  }
  
  public final y a()
  {
    return this.c;
  }
}


/* Location:              E:\apk\dazhihui2\classes-dex2jar.jar!\com\alipay\b\b\a\a\aa.class
 * Java compiler version: 6 (50.0)
 * JD-Core Version:       0.7.1
 */