package com.tencent.beacon.b;

import android.content.Context;
import java.util.List;

public final class c
  implements Runnable
{
  private Context a;
  private List<b> b;
  
  public c(Context paramContext, List<b> paramList)
  {
    this.a = paramContext;
    this.b = paramList;
  }
  
  /* Error */
  private static byte[] a(String paramString1, byte[] paramArrayOfByte, String paramString2, int paramInt, String paramString3)
  {
    // Byte code:
    //   0: aconst_null
    //   1: astore 6
    //   3: aconst_null
    //   4: astore 5
    //   6: new 30	org/apache/http/params/BasicHttpParams
    //   9: dup
    //   10: invokespecial 31	org/apache/http/params/BasicHttpParams:<init>	()V
    //   13: astore 7
    //   15: aload 7
    //   17: ldc 32
    //   19: invokestatic 38	org/apache/http/params/HttpConnectionParams:setConnectionTimeout	(Lorg/apache/http/params/HttpParams;I)V
    //   22: aload 7
    //   24: ldc 32
    //   26: invokestatic 41	org/apache/http/params/HttpConnectionParams:setSoTimeout	(Lorg/apache/http/params/HttpParams;I)V
    //   29: new 43	org/apache/http/entity/ByteArrayEntity
    //   32: dup
    //   33: aload_1
    //   34: invokespecial 46	org/apache/http/entity/ByteArrayEntity:<init>	([B)V
    //   37: astore 8
    //   39: aload_2
    //   40: invokevirtual 52	java/lang/String:toLowerCase	()Ljava/lang/String;
    //   43: ldc 54
    //   45: invokevirtual 58	java/lang/String:equals	(Ljava/lang/Object;)Z
    //   48: ifeq +174 -> 222
    //   51: new 60	org/apache/http/client/methods/HttpPost
    //   54: dup
    //   55: aload_0
    //   56: invokespecial 63	org/apache/http/client/methods/HttpPost:<init>	(Ljava/lang/String;)V
    //   59: astore_0
    //   60: aload_0
    //   61: checkcast 60	org/apache/http/client/methods/HttpPost
    //   64: aload 8
    //   66: invokevirtual 67	org/apache/http/client/methods/HttpPost:setEntity	(Lorg/apache/http/HttpEntity;)V
    //   69: aload 6
    //   71: astore_2
    //   72: new 69	org/apache/http/impl/client/DefaultHttpClient
    //   75: dup
    //   76: aload 7
    //   78: invokespecial 72	org/apache/http/impl/client/DefaultHttpClient:<init>	(Lorg/apache/http/params/HttpParams;)V
    //   81: astore_1
    //   82: aload 4
    //   84: ifnull +81 -> 165
    //   87: aload 6
    //   89: astore_2
    //   90: aload 4
    //   92: invokevirtual 52	java/lang/String:toLowerCase	()Ljava/lang/String;
    //   95: ldc 74
    //   97: invokevirtual 78	java/lang/String:contains	(Ljava/lang/CharSequence;)Z
    //   100: ifeq +65 -> 165
    //   103: aload 6
    //   105: astore_2
    //   106: new 80	java/lang/StringBuilder
    //   109: dup
    //   110: ldc 82
    //   112: invokespecial 83	java/lang/StringBuilder:<init>	(Ljava/lang/String;)V
    //   115: aload 4
    //   117: invokevirtual 87	java/lang/StringBuilder:append	(Ljava/lang/String;)Ljava/lang/StringBuilder;
    //   120: invokevirtual 90	java/lang/StringBuilder:toString	()Ljava/lang/String;
    //   123: iconst_0
    //   124: anewarray 4	java/lang/Object
    //   127: invokestatic 95	com/tencent/beacon/e/b:a	(Ljava/lang/String;[Ljava/lang/Object;)V
    //   130: aload 6
    //   132: astore_2
    //   133: new 97	org/apache/http/HttpHost
    //   136: dup
    //   137: invokestatic 102	android/net/Proxy:getDefaultHost	()Ljava/lang/String;
    //   140: invokestatic 106	android/net/Proxy:getDefaultPort	()I
    //   143: invokespecial 109	org/apache/http/HttpHost:<init>	(Ljava/lang/String;I)V
    //   146: astore 4
    //   148: aload 6
    //   150: astore_2
    //   151: aload_1
    //   152: invokevirtual 113	org/apache/http/impl/client/DefaultHttpClient:getParams	()Lorg/apache/http/params/HttpParams;
    //   155: ldc 115
    //   157: aload 4
    //   159: invokeinterface 121 3 0
    //   164: pop
    //   165: aload 6
    //   167: astore_2
    //   168: ldc 123
    //   170: iconst_0
    //   171: anewarray 4	java/lang/Object
    //   174: invokestatic 95	com/tencent/beacon/e/b:a	(Ljava/lang/String;[Ljava/lang/Object;)V
    //   177: aload 6
    //   179: astore_2
    //   180: aload_1
    //   181: aload_0
    //   182: invokevirtual 127	org/apache/http/impl/client/DefaultHttpClient:execute	(Lorg/apache/http/client/methods/HttpUriRequest;)Lorg/apache/http/HttpResponse;
    //   185: astore_0
    //   186: aload 6
    //   188: astore_2
    //   189: aload_0
    //   190: invokeinterface 133 1 0
    //   195: invokeinterface 138 1 0
    //   200: sipush 200
    //   203: if_icmpeq +82 -> 285
    //   206: aload 6
    //   208: astore_2
    //   209: ldc -116
    //   211: iconst_0
    //   212: anewarray 4	java/lang/Object
    //   215: invokestatic 143	com/tencent/beacon/e/b:d	(Ljava/lang/String;[Ljava/lang/Object;)V
    //   218: aconst_null
    //   219: astore_2
    //   220: aload_2
    //   221: areturn
    //   222: aload_1
    //   223: ifnonnull +35 -> 258
    //   226: ldc -111
    //   228: astore_1
    //   229: new 147	org/apache/http/client/methods/HttpGet
    //   232: dup
    //   233: new 80	java/lang/StringBuilder
    //   236: dup
    //   237: invokespecial 148	java/lang/StringBuilder:<init>	()V
    //   240: aload_0
    //   241: invokevirtual 87	java/lang/StringBuilder:append	(Ljava/lang/String;)Ljava/lang/StringBuilder;
    //   244: aload_1
    //   245: invokevirtual 87	java/lang/StringBuilder:append	(Ljava/lang/String;)Ljava/lang/StringBuilder;
    //   248: invokevirtual 90	java/lang/StringBuilder:toString	()Ljava/lang/String;
    //   251: invokespecial 149	org/apache/http/client/methods/HttpGet:<init>	(Ljava/lang/String;)V
    //   254: astore_0
    //   255: goto -186 -> 69
    //   258: new 80	java/lang/StringBuilder
    //   261: dup
    //   262: ldc -105
    //   264: invokespecial 83	java/lang/StringBuilder:<init>	(Ljava/lang/String;)V
    //   267: new 48	java/lang/String
    //   270: dup
    //   271: aload_1
    //   272: invokespecial 152	java/lang/String:<init>	([B)V
    //   275: invokevirtual 87	java/lang/StringBuilder:append	(Ljava/lang/String;)Ljava/lang/StringBuilder;
    //   278: invokevirtual 90	java/lang/StringBuilder:toString	()Ljava/lang/String;
    //   281: astore_1
    //   282: goto -53 -> 229
    //   285: aload 6
    //   287: astore_2
    //   288: aload_0
    //   289: invokeinterface 156 1 0
    //   294: astore_0
    //   295: aload_0
    //   296: ifnonnull +17 -> 313
    //   299: aload 6
    //   301: astore_2
    //   302: ldc -98
    //   304: iconst_0
    //   305: anewarray 4	java/lang/Object
    //   308: invokestatic 143	com/tencent/beacon/e/b:d	(Ljava/lang/String;[Ljava/lang/Object;)V
    //   311: aconst_null
    //   312: areturn
    //   313: aload 6
    //   315: astore_2
    //   316: ldc -96
    //   318: iconst_0
    //   319: anewarray 4	java/lang/Object
    //   322: invokestatic 95	com/tencent/beacon/e/b:a	(Ljava/lang/String;[Ljava/lang/Object;)V
    //   325: aload 6
    //   327: astore_2
    //   328: new 162	java/io/DataInputStream
    //   331: dup
    //   332: aload_0
    //   333: invokeinterface 168 1 0
    //   338: invokespecial 171	java/io/DataInputStream:<init>	(Ljava/io/InputStream;)V
    //   341: astore_0
    //   342: new 173	java/io/ByteArrayOutputStream
    //   345: dup
    //   346: invokespecial 174	java/io/ByteArrayOutputStream:<init>	()V
    //   349: astore_1
    //   350: aload_0
    //   351: invokevirtual 177	java/io/DataInputStream:read	()I
    //   354: istore_3
    //   355: iload_3
    //   356: iconst_m1
    //   357: if_icmpeq +70 -> 427
    //   360: aload_1
    //   361: iload_3
    //   362: invokevirtual 181	java/io/ByteArrayOutputStream:write	(I)V
    //   365: goto -15 -> 350
    //   368: astore 4
    //   370: aconst_null
    //   371: astore_2
    //   372: aload_0
    //   373: astore_1
    //   374: aload_2
    //   375: astore_0
    //   376: aload_1
    //   377: astore_2
    //   378: aload 4
    //   380: invokevirtual 184	java/lang/Throwable:printStackTrace	()V
    //   383: aload_1
    //   384: astore_2
    //   385: aload 4
    //   387: invokevirtual 187	java/lang/Throwable:getMessage	()Ljava/lang/String;
    //   390: iconst_0
    //   391: anewarray 4	java/lang/Object
    //   394: invokestatic 143	com/tencent/beacon/e/b:d	(Ljava/lang/String;[Ljava/lang/Object;)V
    //   397: aload_0
    //   398: astore_2
    //   399: aload_1
    //   400: ifnull -180 -> 220
    //   403: aload_1
    //   404: invokevirtual 190	java/io/DataInputStream:close	()V
    //   407: aload_0
    //   408: areturn
    //   409: astore_1
    //   410: aload_1
    //   411: invokevirtual 191	java/io/IOException:printStackTrace	()V
    //   414: aload_1
    //   415: invokevirtual 192	java/io/IOException:getMessage	()Ljava/lang/String;
    //   418: iconst_0
    //   419: anewarray 4	java/lang/Object
    //   422: invokestatic 143	com/tencent/beacon/e/b:d	(Ljava/lang/String;[Ljava/lang/Object;)V
    //   425: aload_0
    //   426: areturn
    //   427: aload_1
    //   428: invokevirtual 195	java/io/ByteArrayOutputStream:flush	()V
    //   431: aload_1
    //   432: invokevirtual 199	java/io/ByteArrayOutputStream:toByteArray	()[B
    //   435: astore_1
    //   436: ldc -55
    //   438: iconst_0
    //   439: anewarray 4	java/lang/Object
    //   442: invokestatic 95	com/tencent/beacon/e/b:a	(Ljava/lang/String;[Ljava/lang/Object;)V
    //   445: aload_0
    //   446: invokevirtual 190	java/io/DataInputStream:close	()V
    //   449: aload_1
    //   450: areturn
    //   451: astore_0
    //   452: aload_0
    //   453: invokevirtual 191	java/io/IOException:printStackTrace	()V
    //   456: aload_0
    //   457: invokevirtual 192	java/io/IOException:getMessage	()Ljava/lang/String;
    //   460: iconst_0
    //   461: anewarray 4	java/lang/Object
    //   464: invokestatic 143	com/tencent/beacon/e/b:d	(Ljava/lang/String;[Ljava/lang/Object;)V
    //   467: aload_1
    //   468: areturn
    //   469: astore_0
    //   470: aload_2
    //   471: ifnull +7 -> 478
    //   474: aload_2
    //   475: invokevirtual 190	java/io/DataInputStream:close	()V
    //   478: aload_0
    //   479: athrow
    //   480: astore_1
    //   481: aload_1
    //   482: invokevirtual 191	java/io/IOException:printStackTrace	()V
    //   485: aload_1
    //   486: invokevirtual 192	java/io/IOException:getMessage	()Ljava/lang/String;
    //   489: iconst_0
    //   490: anewarray 4	java/lang/Object
    //   493: invokestatic 143	com/tencent/beacon/e/b:d	(Ljava/lang/String;[Ljava/lang/Object;)V
    //   496: goto -18 -> 478
    //   499: astore_1
    //   500: aload_0
    //   501: astore_2
    //   502: aload_1
    //   503: astore_0
    //   504: goto -34 -> 470
    //   507: astore 4
    //   509: aconst_null
    //   510: astore_0
    //   511: aload 5
    //   513: astore_1
    //   514: goto -138 -> 376
    //   517: astore 4
    //   519: aload_0
    //   520: astore_2
    //   521: aload_1
    //   522: astore_0
    //   523: aload_2
    //   524: astore_1
    //   525: goto -149 -> 376
    // Local variable table:
    //   start	length	slot	name	signature
    //   0	528	0	paramString1	String
    //   0	528	1	paramArrayOfByte	byte[]
    //   0	528	2	paramString2	String
    //   0	528	3	paramInt	int
    //   0	528	4	paramString3	String
    //   4	508	5	localObject1	Object
    //   1	325	6	localObject2	Object
    //   13	64	7	localBasicHttpParams	org.apache.http.params.BasicHttpParams
    //   37	28	8	localByteArrayEntity	org.apache.http.entity.ByteArrayEntity
    // Exception table:
    //   from	to	target	type
    //   342	350	368	java/lang/Throwable
    //   350	355	368	java/lang/Throwable
    //   360	365	368	java/lang/Throwable
    //   427	436	368	java/lang/Throwable
    //   403	407	409	java/io/IOException
    //   445	449	451	java/io/IOException
    //   72	82	469	finally
    //   90	103	469	finally
    //   106	130	469	finally
    //   133	148	469	finally
    //   151	165	469	finally
    //   168	177	469	finally
    //   180	186	469	finally
    //   189	206	469	finally
    //   209	218	469	finally
    //   288	295	469	finally
    //   302	311	469	finally
    //   316	325	469	finally
    //   328	342	469	finally
    //   378	383	469	finally
    //   385	397	469	finally
    //   474	478	480	java/io/IOException
    //   342	350	499	finally
    //   350	355	499	finally
    //   360	365	499	finally
    //   427	436	499	finally
    //   436	445	499	finally
    //   72	82	507	java/lang/Throwable
    //   90	103	507	java/lang/Throwable
    //   106	130	507	java/lang/Throwable
    //   133	148	507	java/lang/Throwable
    //   151	165	507	java/lang/Throwable
    //   168	177	507	java/lang/Throwable
    //   180	186	507	java/lang/Throwable
    //   189	206	507	java/lang/Throwable
    //   209	218	507	java/lang/Throwable
    //   288	295	507	java/lang/Throwable
    //   302	311	507	java/lang/Throwable
    //   316	325	507	java/lang/Throwable
    //   328	342	507	java/lang/Throwable
    //   436	445	517	java/lang/Throwable
  }
  
  /* Error */
  public final void run()
  {
    // Byte code:
    //   0: aload_0
    //   1: getfield 18	com/tencent/beacon/b/c:a	Landroid/content/Context;
    //   4: ifnull +10 -> 14
    //   7: aload_0
    //   8: getfield 20	com/tencent/beacon/b/c:b	Ljava/util/List;
    //   11: ifnonnull +4 -> 15
    //   14: return
    //   15: invokestatic 208	com/tencent/beacon/a/f:m	()Lcom/tencent/beacon/a/f;
    //   18: astore_1
    //   19: aload_1
    //   20: ifnonnull +13 -> 33
    //   23: ldc -46
    //   25: iconst_0
    //   26: anewarray 4	java/lang/Object
    //   29: invokestatic 143	com/tencent/beacon/e/b:d	(Ljava/lang/String;[Ljava/lang/Object;)V
    //   32: return
    //   33: aload_1
    //   34: monitorenter
    //   35: aload_1
    //   36: invokevirtual 214	com/tencent/beacon/a/f:h	()J
    //   39: lstore 10
    //   41: aload_1
    //   42: invokevirtual 217	com/tencent/beacon/a/f:g	()Ljava/lang/String;
    //   45: astore 5
    //   47: aload_1
    //   48: monitorexit
    //   49: aload_0
    //   50: getfield 18	com/tencent/beacon/b/c:a	Landroid/content/Context;
    //   53: invokestatic 223	com/tencent/beacon/e/c:c	(Landroid/content/Context;)Ljava/lang/String;
    //   56: astore_2
    //   57: aload_2
    //   58: ifnonnull +1726 -> 1784
    //   61: ldc -31
    //   63: astore_2
    //   64: ldc -31
    //   66: astore_1
    //   67: aload_0
    //   68: getfield 18	com/tencent/beacon/b/c:a	Landroid/content/Context;
    //   71: invokestatic 230	com/tencent/beacon/a/h:a	(Landroid/content/Context;)Lcom/tencent/beacon/a/h;
    //   74: ifnull +1705 -> 1779
    //   77: aload_0
    //   78: getfield 18	com/tencent/beacon/b/c:a	Landroid/content/Context;
    //   81: invokestatic 233	com/tencent/beacon/a/h:l	(Landroid/content/Context;)Ljava/lang/String;
    //   84: astore_3
    //   85: aload_3
    //   86: astore_1
    //   87: aload_3
    //   88: ifnonnull +1691 -> 1779
    //   91: ldc -31
    //   93: astore_3
    //   94: new 235	java/util/HashMap
    //   97: dup
    //   98: invokespecial 236	java/util/HashMap:<init>	()V
    //   101: astore 6
    //   103: aload_0
    //   104: getfield 20	com/tencent/beacon/b/c:b	Ljava/util/List;
    //   107: invokeinterface 242 1 0
    //   112: astore 7
    //   114: aload 7
    //   116: invokeinterface 248 1 0
    //   121: ifeq +857 -> 978
    //   124: aload 7
    //   126: invokeinterface 252 1 0
    //   131: checkcast 254	com/tencent/beacon/b/b
    //   134: astore 8
    //   136: new 80	java/lang/StringBuilder
    //   139: dup
    //   140: ldc_w 256
    //   143: invokespecial 83	java/lang/StringBuilder:<init>	(Ljava/lang/String;)V
    //   146: aload 8
    //   148: invokevirtual 258	com/tencent/beacon/b/b:a	()Ljava/lang/String;
    //   151: invokevirtual 87	java/lang/StringBuilder:append	(Ljava/lang/String;)Ljava/lang/StringBuilder;
    //   154: invokevirtual 90	java/lang/StringBuilder:toString	()Ljava/lang/String;
    //   157: iconst_0
    //   158: anewarray 4	java/lang/Object
    //   161: invokestatic 95	com/tencent/beacon/e/b:a	(Ljava/lang/String;[Ljava/lang/Object;)V
    //   164: new 80	java/lang/StringBuilder
    //   167: dup
    //   168: ldc_w 260
    //   171: invokespecial 83	java/lang/StringBuilder:<init>	(Ljava/lang/String;)V
    //   174: aload 8
    //   176: invokevirtual 262	com/tencent/beacon/b/b:b	()Ljava/lang/String;
    //   179: invokevirtual 87	java/lang/StringBuilder:append	(Ljava/lang/String;)Ljava/lang/StringBuilder;
    //   182: invokevirtual 90	java/lang/StringBuilder:toString	()Ljava/lang/String;
    //   185: iconst_0
    //   186: anewarray 4	java/lang/Object
    //   189: invokestatic 264	com/tencent/beacon/e/b:b	(Ljava/lang/String;[Ljava/lang/Object;)V
    //   192: aconst_null
    //   193: astore_1
    //   194: aload 6
    //   196: invokeinterface 269 1 0
    //   201: aload 6
    //   203: ldc_w 271
    //   206: aload 5
    //   208: invokeinterface 275 3 0
    //   213: pop
    //   214: aload 6
    //   216: ldc_w 277
    //   219: new 80	java/lang/StringBuilder
    //   222: dup
    //   223: invokespecial 148	java/lang/StringBuilder:<init>	()V
    //   226: aload_0
    //   227: getfield 18	com/tencent/beacon/b/c:a	Landroid/content/Context;
    //   230: invokestatic 282	com/tencent/beacon/b/a:a	(Landroid/content/Context;)Lcom/tencent/beacon/b/a;
    //   233: invokevirtual 283	com/tencent/beacon/b/a:a	()Ljava/lang/String;
    //   236: invokevirtual 87	java/lang/StringBuilder:append	(Ljava/lang/String;)Ljava/lang/StringBuilder;
    //   239: invokevirtual 90	java/lang/StringBuilder:toString	()Ljava/lang/String;
    //   242: invokeinterface 275 3 0
    //   247: pop
    //   248: aload 6
    //   250: ldc_w 285
    //   253: aload_3
    //   254: invokeinterface 275 3 0
    //   259: pop
    //   260: new 80	java/lang/StringBuilder
    //   263: dup
    //   264: invokespecial 148	java/lang/StringBuilder:<init>	()V
    //   267: astore 4
    //   269: aload_0
    //   270: getfield 18	com/tencent/beacon/b/c:a	Landroid/content/Context;
    //   273: invokestatic 230	com/tencent/beacon/a/h:a	(Landroid/content/Context;)Lcom/tencent/beacon/a/h;
    //   276: pop
    //   277: aload 6
    //   279: ldc_w 287
    //   282: aload 4
    //   284: aload_0
    //   285: getfield 18	com/tencent/beacon/b/c:a	Landroid/content/Context;
    //   288: invokestatic 290	com/tencent/beacon/a/h:f	(Landroid/content/Context;)Ljava/lang/String;
    //   291: invokevirtual 87	java/lang/StringBuilder:append	(Ljava/lang/String;)Ljava/lang/StringBuilder;
    //   294: invokevirtual 90	java/lang/StringBuilder:toString	()Ljava/lang/String;
    //   297: invokeinterface 275 3 0
    //   302: pop
    //   303: new 80	java/lang/StringBuilder
    //   306: dup
    //   307: invokespecial 148	java/lang/StringBuilder:<init>	()V
    //   310: astore 4
    //   312: aload_0
    //   313: getfield 18	com/tencent/beacon/b/c:a	Landroid/content/Context;
    //   316: invokestatic 230	com/tencent/beacon/a/h:a	(Landroid/content/Context;)Lcom/tencent/beacon/a/h;
    //   319: pop
    //   320: aload 6
    //   322: ldc_w 292
    //   325: aload 4
    //   327: aload_0
    //   328: getfield 18	com/tencent/beacon/b/c:a	Landroid/content/Context;
    //   331: invokestatic 295	com/tencent/beacon/a/h:m	(Landroid/content/Context;)I
    //   334: invokevirtual 298	java/lang/StringBuilder:append	(I)Ljava/lang/StringBuilder;
    //   337: invokevirtual 90	java/lang/StringBuilder:toString	()Ljava/lang/String;
    //   340: invokeinterface 275 3 0
    //   345: pop
    //   346: ldc_w 300
    //   349: aload 8
    //   351: invokevirtual 258	com/tencent/beacon/b/b:a	()Ljava/lang/String;
    //   354: invokevirtual 58	java/lang/String:equals	(Ljava/lang/Object;)Z
    //   357: ifeq +553 -> 910
    //   360: aload 8
    //   362: invokevirtual 302	com/tencent/beacon/b/b:f	()Z
    //   365: ifeq +17 -> 382
    //   368: aload 6
    //   370: ldc_w 304
    //   373: ldc_w 306
    //   376: invokeinterface 275 3 0
    //   381: pop
    //   382: aload_2
    //   383: invokevirtual 52	java/lang/String:toLowerCase	()Ljava/lang/String;
    //   386: ldc 74
    //   388: invokevirtual 78	java/lang/String:contains	(Ljava/lang/CharSequence;)Z
    //   391: ifeq +502 -> 893
    //   394: ldc_w 308
    //   397: iconst_0
    //   398: anewarray 4	java/lang/Object
    //   401: invokestatic 95	com/tencent/beacon/e/b:a	(Ljava/lang/String;[Ljava/lang/Object;)V
    //   404: aload 8
    //   406: invokevirtual 262	com/tencent/beacon/b/b:b	()Ljava/lang/String;
    //   409: aload_2
    //   410: invokestatic 311	com/tencent/beacon/b/a:a	(Ljava/lang/String;Ljava/lang/String;)Lcom/tencent/beacon/b/a$b;
    //   413: astore_1
    //   414: aload_1
    //   415: astore 4
    //   417: aload_1
    //   418: ifnonnull +12 -> 430
    //   421: new 313	com/tencent/beacon/b/a$b
    //   424: dup
    //   425: invokespecial 314	com/tencent/beacon/b/a$b:<init>	()V
    //   428: astore 4
    //   430: aload 4
    //   432: getfield 317	com/tencent/beacon/b/a$b:a	J
    //   435: aload 4
    //   437: getfield 319	com/tencent/beacon/b/a$b:b	J
    //   440: ladd
    //   441: aload 4
    //   443: getfield 321	com/tencent/beacon/b/a$b:c	J
    //   446: ladd
    //   447: aload 4
    //   449: getfield 323	com/tencent/beacon/b/a$b:d	J
    //   452: ladd
    //   453: aload 4
    //   455: getfield 326	com/tencent/beacon/b/a$b:e	J
    //   458: ladd
    //   459: lconst_0
    //   460: lcmp
    //   461: ifgt +79 -> 540
    //   464: ldc_w 328
    //   467: iconst_0
    //   468: anewarray 4	java/lang/Object
    //   471: invokestatic 95	com/tencent/beacon/e/b:a	(Ljava/lang/String;[Ljava/lang/Object;)V
    //   474: invokestatic 333	java/lang/System:currentTimeMillis	()J
    //   477: lstore 12
    //   479: aload 8
    //   481: invokevirtual 262	com/tencent/beacon/b/b:b	()Ljava/lang/String;
    //   484: ldc_w 335
    //   487: invokevirtual 338	java/lang/String:getBytes	()[B
    //   490: ldc 54
    //   492: ldc 32
    //   494: aload_2
    //   495: invokestatic 340	com/tencent/beacon/b/c:a	(Ljava/lang/String;[BLjava/lang/String;ILjava/lang/String;)[B
    //   498: ifnull +42 -> 540
    //   501: aload 4
    //   503: invokestatic 333	java/lang/System:currentTimeMillis	()J
    //   506: lload 12
    //   508: lsub
    //   509: putfield 326	com/tencent/beacon/b/a$b:e	J
    //   512: new 80	java/lang/StringBuilder
    //   515: dup
    //   516: ldc_w 342
    //   519: invokespecial 83	java/lang/StringBuilder:<init>	(Ljava/lang/String;)V
    //   522: aload 4
    //   524: getfield 326	com/tencent/beacon/b/a$b:e	J
    //   527: invokevirtual 345	java/lang/StringBuilder:append	(J)Ljava/lang/StringBuilder;
    //   530: invokevirtual 90	java/lang/StringBuilder:toString	()Ljava/lang/String;
    //   533: iconst_0
    //   534: anewarray 4	java/lang/Object
    //   537: invokestatic 95	com/tencent/beacon/e/b:a	(Ljava/lang/String;[Ljava/lang/Object;)V
    //   540: new 347	com/tencent/beacon/event/k
    //   543: dup
    //   544: invokespecial 348	com/tencent/beacon/event/k:<init>	()V
    //   547: astore_1
    //   548: aload_1
    //   549: aload 8
    //   551: invokevirtual 262	com/tencent/beacon/b/b:b	()Ljava/lang/String;
    //   554: invokevirtual 350	com/tencent/beacon/event/k:b	(Ljava/lang/String;)V
    //   557: new 352	java/util/Date
    //   560: dup
    //   561: invokespecial 353	java/util/Date:<init>	()V
    //   564: invokevirtual 356	java/util/Date:getTime	()J
    //   567: lstore 12
    //   569: new 80	java/lang/StringBuilder
    //   572: dup
    //   573: ldc_w 358
    //   576: invokespecial 83	java/lang/StringBuilder:<init>	(Ljava/lang/String;)V
    //   579: lload 12
    //   581: invokevirtual 345	java/lang/StringBuilder:append	(J)Ljava/lang/StringBuilder;
    //   584: invokevirtual 90	java/lang/StringBuilder:toString	()Ljava/lang/String;
    //   587: iconst_0
    //   588: anewarray 4	java/lang/Object
    //   591: invokestatic 95	com/tencent/beacon/e/b:a	(Ljava/lang/String;[Ljava/lang/Object;)V
    //   594: lload 12
    //   596: lload 10
    //   598: ladd
    //   599: lstore 12
    //   601: new 80	java/lang/StringBuilder
    //   604: dup
    //   605: ldc_w 360
    //   608: invokespecial 83	java/lang/StringBuilder:<init>	(Ljava/lang/String;)V
    //   611: lload 12
    //   613: invokevirtual 345	java/lang/StringBuilder:append	(J)Ljava/lang/StringBuilder;
    //   616: invokevirtual 90	java/lang/StringBuilder:toString	()Ljava/lang/String;
    //   619: iconst_0
    //   620: anewarray 4	java/lang/Object
    //   623: invokestatic 95	com/tencent/beacon/e/b:a	(Ljava/lang/String;[Ljava/lang/Object;)V
    //   626: aload_1
    //   627: lload 12
    //   629: invokevirtual 363	com/tencent/beacon/event/k:b	(J)V
    //   632: aload_1
    //   633: ldc_w 365
    //   636: invokevirtual 367	com/tencent/beacon/event/k:a	(Ljava/lang/String;)V
    //   639: aload 6
    //   641: ldc_w 369
    //   644: aload_2
    //   645: invokeinterface 275 3 0
    //   650: pop
    //   651: aload 6
    //   653: ldc_w 371
    //   656: new 80	java/lang/StringBuilder
    //   659: dup
    //   660: invokespecial 148	java/lang/StringBuilder:<init>	()V
    //   663: aload 4
    //   665: getfield 319	com/tencent/beacon/b/a$b:b	J
    //   668: invokevirtual 345	java/lang/StringBuilder:append	(J)Ljava/lang/StringBuilder;
    //   671: invokevirtual 90	java/lang/StringBuilder:toString	()Ljava/lang/String;
    //   674: invokeinterface 275 3 0
    //   679: pop
    //   680: aload 6
    //   682: ldc_w 373
    //   685: ldc_w 375
    //   688: invokeinterface 275 3 0
    //   693: pop
    //   694: aload 6
    //   696: ldc_w 377
    //   699: aload 4
    //   701: getfield 380	com/tencent/beacon/b/a$b:f	Ljava/lang/String;
    //   704: invokeinterface 275 3 0
    //   709: pop
    //   710: aload 6
    //   712: ldc_w 382
    //   715: new 80	java/lang/StringBuilder
    //   718: dup
    //   719: invokespecial 148	java/lang/StringBuilder:<init>	()V
    //   722: aload 4
    //   724: getfield 317	com/tencent/beacon/b/a$b:a	J
    //   727: invokevirtual 345	java/lang/StringBuilder:append	(J)Ljava/lang/StringBuilder;
    //   730: invokevirtual 90	java/lang/StringBuilder:toString	()Ljava/lang/String;
    //   733: invokeinterface 275 3 0
    //   738: pop
    //   739: aload 6
    //   741: ldc_w 384
    //   744: new 80	java/lang/StringBuilder
    //   747: dup
    //   748: invokespecial 148	java/lang/StringBuilder:<init>	()V
    //   751: aload 4
    //   753: getfield 321	com/tencent/beacon/b/a$b:c	J
    //   756: invokevirtual 345	java/lang/StringBuilder:append	(J)Ljava/lang/StringBuilder;
    //   759: invokevirtual 90	java/lang/StringBuilder:toString	()Ljava/lang/String;
    //   762: invokeinterface 275 3 0
    //   767: pop
    //   768: aload 6
    //   770: ldc_w 386
    //   773: new 80	java/lang/StringBuilder
    //   776: dup
    //   777: invokespecial 148	java/lang/StringBuilder:<init>	()V
    //   780: aload 4
    //   782: getfield 326	com/tencent/beacon/b/a$b:e	J
    //   785: invokevirtual 345	java/lang/StringBuilder:append	(J)Ljava/lang/StringBuilder;
    //   788: invokevirtual 90	java/lang/StringBuilder:toString	()Ljava/lang/String;
    //   791: invokeinterface 275 3 0
    //   796: pop
    //   797: aload 6
    //   799: ldc_w 388
    //   802: new 80	java/lang/StringBuilder
    //   805: dup
    //   806: invokespecial 148	java/lang/StringBuilder:<init>	()V
    //   809: aload 4
    //   811: getfield 323	com/tencent/beacon/b/a$b:d	J
    //   814: invokevirtual 345	java/lang/StringBuilder:append	(J)Ljava/lang/StringBuilder;
    //   817: invokevirtual 90	java/lang/StringBuilder:toString	()Ljava/lang/String;
    //   820: invokeinterface 275 3 0
    //   825: pop
    //   826: aload_1
    //   827: aload 6
    //   829: invokevirtual 391	com/tencent/beacon/event/k:a	(Ljava/util/Map;)V
    //   832: aload_1
    //   833: ifnull -719 -> 114
    //   836: new 80	java/lang/StringBuilder
    //   839: dup
    //   840: ldc_w 393
    //   843: invokespecial 83	java/lang/StringBuilder:<init>	(Ljava/lang/String;)V
    //   846: aload 8
    //   848: invokevirtual 258	com/tencent/beacon/b/b:a	()Ljava/lang/String;
    //   851: invokevirtual 87	java/lang/StringBuilder:append	(Ljava/lang/String;)Ljava/lang/StringBuilder;
    //   854: invokevirtual 90	java/lang/StringBuilder:toString	()Ljava/lang/String;
    //   857: iconst_0
    //   858: anewarray 4	java/lang/Object
    //   861: invokestatic 95	com/tencent/beacon/e/b:a	(Ljava/lang/String;[Ljava/lang/Object;)V
    //   864: aload_0
    //   865: getfield 18	com/tencent/beacon/b/c:a	Landroid/content/Context;
    //   868: aload_1
    //   869: invokestatic 396	com/tencent/beacon/a/h:a	(Landroid/content/Context;Lcom/tencent/beacon/event/k;)Z
    //   872: ifne -758 -> 114
    //   875: ldc_w 398
    //   878: iconst_0
    //   879: anewarray 4	java/lang/Object
    //   882: invokestatic 95	com/tencent/beacon/e/b:a	(Ljava/lang/String;[Ljava/lang/Object;)V
    //   885: goto -771 -> 114
    //   888: astore_2
    //   889: aload_1
    //   890: monitorexit
    //   891: aload_2
    //   892: athrow
    //   893: aload 8
    //   895: invokevirtual 262	com/tencent/beacon/b/b:b	()Ljava/lang/String;
    //   898: aload 8
    //   900: invokevirtual 400	com/tencent/beacon/b/b:e	()Z
    //   903: invokestatic 403	com/tencent/beacon/b/a:a	(Ljava/lang/String;Z)Lcom/tencent/beacon/b/a$b;
    //   906: astore_1
    //   907: goto -493 -> 414
    //   910: ldc_w 405
    //   913: aload 8
    //   915: invokevirtual 258	com/tencent/beacon/b/b:a	()Ljava/lang/String;
    //   918: invokevirtual 58	java/lang/String:equals	(Ljava/lang/Object;)Z
    //   921: ifeq +283 -> 1204
    //   924: aload 8
    //   926: invokevirtual 262	com/tencent/beacon/b/b:b	()Ljava/lang/String;
    //   929: invokevirtual 408	java/lang/String:trim	()Ljava/lang/String;
    //   932: astore_1
    //   933: aload_1
    //   934: ldc_w 410
    //   937: invokevirtual 414	java/lang/String:split	(Ljava/lang/String;)[Ljava/lang/String;
    //   940: astore 4
    //   942: aload 4
    //   944: ifnull +10 -> 954
    //   947: aload 4
    //   949: arraylength
    //   950: iconst_2
    //   951: if_icmpeq +69 -> 1020
    //   954: new 80	java/lang/StringBuilder
    //   957: dup
    //   958: ldc_w 416
    //   961: invokespecial 83	java/lang/StringBuilder:<init>	(Ljava/lang/String;)V
    //   964: aload_1
    //   965: invokevirtual 87	java/lang/StringBuilder:append	(Ljava/lang/String;)Ljava/lang/StringBuilder;
    //   968: invokevirtual 90	java/lang/StringBuilder:toString	()Ljava/lang/String;
    //   971: iconst_0
    //   972: anewarray 4	java/lang/Object
    //   975: invokestatic 143	com/tencent/beacon/e/b:d	(Ljava/lang/String;[Ljava/lang/Object;)V
    //   978: aload_0
    //   979: getfield 18	com/tencent/beacon/b/c:a	Landroid/content/Context;
    //   982: astore_1
    //   983: new 352	java/util/Date
    //   986: dup
    //   987: invokespecial 353	java/util/Date:<init>	()V
    //   990: invokevirtual 356	java/util/Date:getTime	()J
    //   993: lstore 10
    //   995: ldc_w 418
    //   998: iconst_0
    //   999: anewarray 4	java/lang/Object
    //   1002: invokestatic 95	com/tencent/beacon/e/b:a	(Ljava/lang/String;[Ljava/lang/Object;)V
    //   1005: aload_1
    //   1006: ifnonnull +755 -> 1761
    //   1009: ldc_w 420
    //   1012: iconst_0
    //   1013: anewarray 4	java/lang/Object
    //   1016: invokestatic 95	com/tencent/beacon/e/b:a	(Ljava/lang/String;[Ljava/lang/Object;)V
    //   1019: return
    //   1020: aload 8
    //   1022: invokevirtual 302	com/tencent/beacon/b/b:f	()Z
    //   1025: ifeq +17 -> 1042
    //   1028: aload 6
    //   1030: ldc_w 304
    //   1033: ldc_w 306
    //   1036: invokeinterface 275 3 0
    //   1041: pop
    //   1042: aload 4
    //   1044: iconst_0
    //   1045: aaload
    //   1046: aload 4
    //   1048: iconst_1
    //   1049: aaload
    //   1050: invokestatic 426	java/lang/Integer:parseInt	(Ljava/lang/String;)I
    //   1053: invokestatic 429	com/tencent/beacon/b/a:a	(Ljava/lang/String;I)J
    //   1056: lstore 12
    //   1058: new 347	com/tencent/beacon/event/k
    //   1061: dup
    //   1062: invokespecial 348	com/tencent/beacon/event/k:<init>	()V
    //   1065: astore_1
    //   1066: aload_1
    //   1067: aload 8
    //   1069: invokevirtual 262	com/tencent/beacon/b/b:b	()Ljava/lang/String;
    //   1072: invokevirtual 350	com/tencent/beacon/event/k:b	(Ljava/lang/String;)V
    //   1075: new 352	java/util/Date
    //   1078: dup
    //   1079: invokespecial 353	java/util/Date:<init>	()V
    //   1082: invokevirtual 356	java/util/Date:getTime	()J
    //   1085: lstore 14
    //   1087: new 80	java/lang/StringBuilder
    //   1090: dup
    //   1091: ldc_w 358
    //   1094: invokespecial 83	java/lang/StringBuilder:<init>	(Ljava/lang/String;)V
    //   1097: lload 14
    //   1099: invokevirtual 345	java/lang/StringBuilder:append	(J)Ljava/lang/StringBuilder;
    //   1102: invokevirtual 90	java/lang/StringBuilder:toString	()Ljava/lang/String;
    //   1105: iconst_0
    //   1106: anewarray 4	java/lang/Object
    //   1109: invokestatic 95	com/tencent/beacon/e/b:a	(Ljava/lang/String;[Ljava/lang/Object;)V
    //   1112: lload 14
    //   1114: lload 10
    //   1116: ladd
    //   1117: lstore 14
    //   1119: new 80	java/lang/StringBuilder
    //   1122: dup
    //   1123: ldc_w 360
    //   1126: invokespecial 83	java/lang/StringBuilder:<init>	(Ljava/lang/String;)V
    //   1129: lload 14
    //   1131: invokevirtual 345	java/lang/StringBuilder:append	(J)Ljava/lang/StringBuilder;
    //   1134: invokevirtual 90	java/lang/StringBuilder:toString	()Ljava/lang/String;
    //   1137: iconst_0
    //   1138: anewarray 4	java/lang/Object
    //   1141: invokestatic 95	com/tencent/beacon/e/b:a	(Ljava/lang/String;[Ljava/lang/Object;)V
    //   1144: aload_1
    //   1145: lload 14
    //   1147: invokevirtual 363	com/tencent/beacon/event/k:b	(J)V
    //   1150: aload_1
    //   1151: ldc_w 405
    //   1154: invokevirtual 367	com/tencent/beacon/event/k:a	(Ljava/lang/String;)V
    //   1157: aload 6
    //   1159: ldc_w 369
    //   1162: aload_2
    //   1163: invokeinterface 275 3 0
    //   1168: pop
    //   1169: aload 6
    //   1171: ldc_w 431
    //   1174: new 80	java/lang/StringBuilder
    //   1177: dup
    //   1178: invokespecial 148	java/lang/StringBuilder:<init>	()V
    //   1181: lload 12
    //   1183: invokevirtual 345	java/lang/StringBuilder:append	(J)Ljava/lang/StringBuilder;
    //   1186: invokevirtual 90	java/lang/StringBuilder:toString	()Ljava/lang/String;
    //   1189: invokeinterface 275 3 0
    //   1194: pop
    //   1195: aload_1
    //   1196: aload 6
    //   1198: invokevirtual 391	com/tencent/beacon/event/k:a	(Ljava/util/Map;)V
    //   1201: goto -369 -> 832
    //   1204: ldc_w 433
    //   1207: aload 8
    //   1209: invokevirtual 258	com/tencent/beacon/b/b:a	()Ljava/lang/String;
    //   1212: invokevirtual 58	java/lang/String:equals	(Ljava/lang/Object;)Z
    //   1215: ifeq -383 -> 832
    //   1218: new 80	java/lang/StringBuilder
    //   1221: dup
    //   1222: ldc_w 435
    //   1225: invokespecial 83	java/lang/StringBuilder:<init>	(Ljava/lang/String;)V
    //   1228: aload 8
    //   1230: invokevirtual 437	com/tencent/beacon/b/b:c	()Ljava/lang/String;
    //   1233: invokevirtual 87	java/lang/StringBuilder:append	(Ljava/lang/String;)Ljava/lang/StringBuilder;
    //   1236: aload 8
    //   1238: invokevirtual 262	com/tencent/beacon/b/b:b	()Ljava/lang/String;
    //   1241: invokevirtual 87	java/lang/StringBuilder:append	(Ljava/lang/String;)Ljava/lang/StringBuilder;
    //   1244: invokevirtual 90	java/lang/StringBuilder:toString	()Ljava/lang/String;
    //   1247: astore 9
    //   1249: new 80	java/lang/StringBuilder
    //   1252: dup
    //   1253: ldc_w 439
    //   1256: invokespecial 83	java/lang/StringBuilder:<init>	(Ljava/lang/String;)V
    //   1259: aload 9
    //   1261: invokevirtual 87	java/lang/StringBuilder:append	(Ljava/lang/String;)Ljava/lang/StringBuilder;
    //   1264: invokevirtual 90	java/lang/StringBuilder:toString	()Ljava/lang/String;
    //   1267: iconst_0
    //   1268: anewarray 4	java/lang/Object
    //   1271: invokestatic 95	com/tencent/beacon/e/b:a	(Ljava/lang/String;[Ljava/lang/Object;)V
    //   1274: aload_2
    //   1275: invokevirtual 52	java/lang/String:toLowerCase	()Ljava/lang/String;
    //   1278: ldc 74
    //   1280: invokevirtual 78	java/lang/String:contains	(Ljava/lang/CharSequence;)Z
    //   1283: ifeq +456 -> 1739
    //   1286: ldc_w 308
    //   1289: iconst_0
    //   1290: anewarray 4	java/lang/Object
    //   1293: invokestatic 95	com/tencent/beacon/e/b:a	(Ljava/lang/String;[Ljava/lang/Object;)V
    //   1296: aload 9
    //   1298: aload_2
    //   1299: invokestatic 311	com/tencent/beacon/b/a:a	(Ljava/lang/String;Ljava/lang/String;)Lcom/tencent/beacon/b/a$b;
    //   1302: astore_1
    //   1303: aload_1
    //   1304: astore 4
    //   1306: aload_1
    //   1307: ifnonnull +12 -> 1319
    //   1310: new 313	com/tencent/beacon/b/a$b
    //   1313: dup
    //   1314: invokespecial 314	com/tencent/beacon/b/a$b:<init>	()V
    //   1317: astore 4
    //   1319: aload 4
    //   1321: getfield 317	com/tencent/beacon/b/a$b:a	J
    //   1324: aload 4
    //   1326: getfield 319	com/tencent/beacon/b/a$b:b	J
    //   1329: ladd
    //   1330: aload 4
    //   1332: getfield 321	com/tencent/beacon/b/a$b:c	J
    //   1335: ladd
    //   1336: aload 4
    //   1338: getfield 323	com/tencent/beacon/b/a$b:d	J
    //   1341: ladd
    //   1342: aload 4
    //   1344: getfield 326	com/tencent/beacon/b/a$b:e	J
    //   1347: ladd
    //   1348: lconst_0
    //   1349: lcmp
    //   1350: ifgt +76 -> 1426
    //   1353: ldc_w 441
    //   1356: iconst_0
    //   1357: anewarray 4	java/lang/Object
    //   1360: invokestatic 95	com/tencent/beacon/e/b:a	(Ljava/lang/String;[Ljava/lang/Object;)V
    //   1363: invokestatic 333	java/lang/System:currentTimeMillis	()J
    //   1366: lstore 12
    //   1368: aload 9
    //   1370: ldc_w 335
    //   1373: invokevirtual 338	java/lang/String:getBytes	()[B
    //   1376: ldc 54
    //   1378: ldc 32
    //   1380: aload_2
    //   1381: invokestatic 340	com/tencent/beacon/b/c:a	(Ljava/lang/String;[BLjava/lang/String;ILjava/lang/String;)[B
    //   1384: ifnull +42 -> 1426
    //   1387: aload 4
    //   1389: invokestatic 333	java/lang/System:currentTimeMillis	()J
    //   1392: lload 12
    //   1394: lsub
    //   1395: putfield 326	com/tencent/beacon/b/a$b:e	J
    //   1398: new 80	java/lang/StringBuilder
    //   1401: dup
    //   1402: ldc_w 342
    //   1405: invokespecial 83	java/lang/StringBuilder:<init>	(Ljava/lang/String;)V
    //   1408: aload 4
    //   1410: getfield 326	com/tencent/beacon/b/a$b:e	J
    //   1413: invokevirtual 345	java/lang/StringBuilder:append	(J)Ljava/lang/StringBuilder;
    //   1416: invokevirtual 90	java/lang/StringBuilder:toString	()Ljava/lang/String;
    //   1419: iconst_0
    //   1420: anewarray 4	java/lang/Object
    //   1423: invokestatic 95	com/tencent/beacon/e/b:a	(Ljava/lang/String;[Ljava/lang/Object;)V
    //   1426: new 347	com/tencent/beacon/event/k
    //   1429: dup
    //   1430: invokespecial 348	com/tencent/beacon/event/k:<init>	()V
    //   1433: astore_1
    //   1434: aload_1
    //   1435: aload 8
    //   1437: invokevirtual 262	com/tencent/beacon/b/b:b	()Ljava/lang/String;
    //   1440: invokevirtual 350	com/tencent/beacon/event/k:b	(Ljava/lang/String;)V
    //   1443: new 352	java/util/Date
    //   1446: dup
    //   1447: invokespecial 353	java/util/Date:<init>	()V
    //   1450: invokevirtual 356	java/util/Date:getTime	()J
    //   1453: lstore 12
    //   1455: new 80	java/lang/StringBuilder
    //   1458: dup
    //   1459: ldc_w 443
    //   1462: invokespecial 83	java/lang/StringBuilder:<init>	(Ljava/lang/String;)V
    //   1465: lload 12
    //   1467: invokevirtual 345	java/lang/StringBuilder:append	(J)Ljava/lang/StringBuilder;
    //   1470: invokevirtual 90	java/lang/StringBuilder:toString	()Ljava/lang/String;
    //   1473: iconst_0
    //   1474: anewarray 4	java/lang/Object
    //   1477: invokestatic 95	com/tencent/beacon/e/b:a	(Ljava/lang/String;[Ljava/lang/Object;)V
    //   1480: lload 12
    //   1482: lload 10
    //   1484: ladd
    //   1485: lstore 12
    //   1487: new 80	java/lang/StringBuilder
    //   1490: dup
    //   1491: ldc_w 445
    //   1494: invokespecial 83	java/lang/StringBuilder:<init>	(Ljava/lang/String;)V
    //   1497: lload 12
    //   1499: invokevirtual 345	java/lang/StringBuilder:append	(J)Ljava/lang/StringBuilder;
    //   1502: invokevirtual 90	java/lang/StringBuilder:toString	()Ljava/lang/String;
    //   1505: iconst_0
    //   1506: anewarray 4	java/lang/Object
    //   1509: invokestatic 95	com/tencent/beacon/e/b:a	(Ljava/lang/String;[Ljava/lang/Object;)V
    //   1512: aload_1
    //   1513: lload 12
    //   1515: invokevirtual 363	com/tencent/beacon/event/k:b	(J)V
    //   1518: aload_1
    //   1519: ldc_w 447
    //   1522: invokevirtual 367	com/tencent/beacon/event/k:a	(Ljava/lang/String;)V
    //   1525: aload 6
    //   1527: ldc_w 369
    //   1530: aload_2
    //   1531: invokeinterface 275 3 0
    //   1536: pop
    //   1537: aload 6
    //   1539: ldc_w 371
    //   1542: new 80	java/lang/StringBuilder
    //   1545: dup
    //   1546: invokespecial 148	java/lang/StringBuilder:<init>	()V
    //   1549: aload 4
    //   1551: getfield 319	com/tencent/beacon/b/a$b:b	J
    //   1554: invokevirtual 345	java/lang/StringBuilder:append	(J)Ljava/lang/StringBuilder;
    //   1557: invokevirtual 90	java/lang/StringBuilder:toString	()Ljava/lang/String;
    //   1560: invokeinterface 275 3 0
    //   1565: pop
    //   1566: aload 6
    //   1568: ldc_w 373
    //   1571: aload 8
    //   1573: invokevirtual 437	com/tencent/beacon/b/b:c	()Ljava/lang/String;
    //   1576: invokeinterface 275 3 0
    //   1581: pop
    //   1582: aload 6
    //   1584: ldc_w 449
    //   1587: aload 8
    //   1589: invokevirtual 451	com/tencent/beacon/b/b:d	()Ljava/lang/String;
    //   1592: invokeinterface 275 3 0
    //   1597: pop
    //   1598: aload 6
    //   1600: ldc_w 377
    //   1603: aload 4
    //   1605: getfield 380	com/tencent/beacon/b/a$b:f	Ljava/lang/String;
    //   1608: invokeinterface 275 3 0
    //   1613: pop
    //   1614: aload 6
    //   1616: ldc_w 382
    //   1619: new 80	java/lang/StringBuilder
    //   1622: dup
    //   1623: invokespecial 148	java/lang/StringBuilder:<init>	()V
    //   1626: aload 4
    //   1628: getfield 317	com/tencent/beacon/b/a$b:a	J
    //   1631: invokevirtual 345	java/lang/StringBuilder:append	(J)Ljava/lang/StringBuilder;
    //   1634: invokevirtual 90	java/lang/StringBuilder:toString	()Ljava/lang/String;
    //   1637: invokeinterface 275 3 0
    //   1642: pop
    //   1643: aload 6
    //   1645: ldc_w 384
    //   1648: new 80	java/lang/StringBuilder
    //   1651: dup
    //   1652: invokespecial 148	java/lang/StringBuilder:<init>	()V
    //   1655: aload 4
    //   1657: getfield 321	com/tencent/beacon/b/a$b:c	J
    //   1660: invokevirtual 345	java/lang/StringBuilder:append	(J)Ljava/lang/StringBuilder;
    //   1663: invokevirtual 90	java/lang/StringBuilder:toString	()Ljava/lang/String;
    //   1666: invokeinterface 275 3 0
    //   1671: pop
    //   1672: aload 6
    //   1674: ldc_w 386
    //   1677: new 80	java/lang/StringBuilder
    //   1680: dup
    //   1681: invokespecial 148	java/lang/StringBuilder:<init>	()V
    //   1684: aload 4
    //   1686: getfield 326	com/tencent/beacon/b/a$b:e	J
    //   1689: invokevirtual 345	java/lang/StringBuilder:append	(J)Ljava/lang/StringBuilder;
    //   1692: invokevirtual 90	java/lang/StringBuilder:toString	()Ljava/lang/String;
    //   1695: invokeinterface 275 3 0
    //   1700: pop
    //   1701: aload 6
    //   1703: ldc_w 388
    //   1706: new 80	java/lang/StringBuilder
    //   1709: dup
    //   1710: invokespecial 148	java/lang/StringBuilder:<init>	()V
    //   1713: aload 4
    //   1715: getfield 323	com/tencent/beacon/b/a$b:d	J
    //   1718: invokevirtual 345	java/lang/StringBuilder:append	(J)Ljava/lang/StringBuilder;
    //   1721: invokevirtual 90	java/lang/StringBuilder:toString	()Ljava/lang/String;
    //   1724: invokeinterface 275 3 0
    //   1729: pop
    //   1730: aload_1
    //   1731: aload 6
    //   1733: invokevirtual 391	com/tencent/beacon/event/k:a	(Ljava/util/Map;)V
    //   1736: goto -904 -> 832
    //   1739: aload 8
    //   1741: invokevirtual 451	com/tencent/beacon/b/b:d	()Ljava/lang/String;
    //   1744: aload 8
    //   1746: invokevirtual 437	com/tencent/beacon/b/b:c	()Ljava/lang/String;
    //   1749: aload 8
    //   1751: invokevirtual 262	com/tencent/beacon/b/b:b	()Ljava/lang/String;
    //   1754: invokestatic 454	com/tencent/beacon/b/a:a	(Ljava/lang/String;Ljava/lang/String;Ljava/lang/String;)Lcom/tencent/beacon/b/a$b;
    //   1757: astore_1
    //   1758: goto -455 -> 1303
    //   1761: aload_1
    //   1762: iconst_1
    //   1763: newarray <illegal type>
    //   1765: dup
    //   1766: iconst_0
    //   1767: iconst_5
    //   1768: iastore
    //   1769: ldc2_w 455
    //   1772: lload 10
    //   1774: invokestatic 461	com/tencent/beacon/a/a/a:a	(Landroid/content/Context;[IJJ)I
    //   1777: pop
    //   1778: return
    //   1779: aload_1
    //   1780: astore_3
    //   1781: goto -1687 -> 94
    //   1784: goto -1720 -> 64
    // Local variable table:
    //   start	length	slot	name	signature
    //   0	1787	0	this	c
    //   18	1762	1	localObject1	Object
    //   56	589	2	str1	String
    //   888	643	2	localObject2	Object
    //   84	1697	3	localObject3	Object
    //   267	1447	4	localObject4	Object
    //   45	162	5	str2	String
    //   101	1631	6	localHashMap	java.util.HashMap
    //   112	13	7	localIterator	java.util.Iterator
    //   134	1616	8	localb	b
    //   1247	122	9	str3	String
    //   39	1734	10	l1	long
    //   477	1037	12	l2	long
    //   1085	61	14	l3	long
    // Exception table:
    //   from	to	target	type
    //   35	49	888	finally
  }
}


/* Location:              E:\apk\dazhihui2\classes-dex2jar.jar!\com\tencent\beacon\b\c.class
 * Java compiler version: 6 (50.0)
 * JD-Core Version:       0.7.1
 */