package com.f.a.a;

import android.content.Context;

public class m
{
  private Context a;
  
  public m(Context paramContext)
  {
    this.a = paramContext;
  }
  
  /* Error */
  public void a(String paramString, byte[] paramArrayOfByte)
  {
    // Byte code:
    //   0: aload_2
    //   1: ifnonnull +4 -> 5
    //   4: return
    //   5: new 23	java/io/FileOutputStream
    //   8: dup
    //   9: aload_1
    //   10: invokespecial 26	java/io/FileOutputStream:<init>	(Ljava/lang/String;)V
    //   13: astore_3
    //   14: aload_3
    //   15: astore_1
    //   16: aload_3
    //   17: aload_2
    //   18: iconst_0
    //   19: aload_2
    //   20: arraylength
    //   21: invokevirtual 30	java/io/FileOutputStream:write	([BII)V
    //   24: aload_3
    //   25: ifnull -21 -> 4
    //   28: aload_3
    //   29: invokevirtual 33	java/io/FileOutputStream:close	()V
    //   32: return
    //   33: astore_1
    //   34: return
    //   35: astore_2
    //   36: aconst_null
    //   37: astore_3
    //   38: aload_3
    //   39: astore_1
    //   40: aload_2
    //   41: invokevirtual 36	java/io/FileNotFoundException:printStackTrace	()V
    //   44: aload_3
    //   45: ifnull -41 -> 4
    //   48: aload_3
    //   49: invokevirtual 33	java/io/FileOutputStream:close	()V
    //   52: return
    //   53: astore_1
    //   54: return
    //   55: astore_2
    //   56: aconst_null
    //   57: astore_3
    //   58: aload_3
    //   59: astore_1
    //   60: aload_2
    //   61: invokevirtual 37	java/io/IOException:printStackTrace	()V
    //   64: aload_3
    //   65: ifnull -61 -> 4
    //   68: aload_3
    //   69: invokevirtual 33	java/io/FileOutputStream:close	()V
    //   72: return
    //   73: astore_1
    //   74: return
    //   75: astore_2
    //   76: aconst_null
    //   77: astore_1
    //   78: aload_1
    //   79: ifnull +7 -> 86
    //   82: aload_1
    //   83: invokevirtual 33	java/io/FileOutputStream:close	()V
    //   86: aload_2
    //   87: athrow
    //   88: astore_1
    //   89: goto -3 -> 86
    //   92: astore_2
    //   93: goto -15 -> 78
    //   96: astore_2
    //   97: goto -39 -> 58
    //   100: astore_2
    //   101: goto -63 -> 38
    // Local variable table:
    //   start	length	slot	name	signature
    //   0	104	0	this	m
    //   0	104	1	paramString	String
    //   0	104	2	paramArrayOfByte	byte[]
    //   13	56	3	localFileOutputStream	java.io.FileOutputStream
    // Exception table:
    //   from	to	target	type
    //   28	32	33	java/lang/Exception
    //   5	14	35	java/io/FileNotFoundException
    //   48	52	53	java/lang/Exception
    //   5	14	55	java/io/IOException
    //   68	72	73	java/lang/Exception
    //   5	14	75	finally
    //   82	86	88	java/lang/Exception
    //   16	24	92	finally
    //   40	44	92	finally
    //   60	64	92	finally
    //   16	24	96	java/io/IOException
    //   16	24	100	java/io/FileNotFoundException
  }
  
  /* Error */
  public byte[] a(int paramInt)
  {
    // Byte code:
    //   0: aconst_null
    //   1: astore 4
    //   3: aconst_null
    //   4: astore 6
    //   6: aconst_null
    //   7: astore 7
    //   9: aconst_null
    //   10: astore 5
    //   12: aload_0
    //   13: getfield 13	com/f/a/a/m:a	Landroid/content/Context;
    //   16: invokevirtual 46	android/content/Context:getResources	()Landroid/content/res/Resources;
    //   19: iload_1
    //   20: invokevirtual 52	android/content/res/Resources:openRawResource	(I)Ljava/io/InputStream;
    //   23: astore_2
    //   24: aload_2
    //   25: astore_3
    //   26: aload 6
    //   28: astore 4
    //   30: aload 7
    //   32: astore 5
    //   34: aload_2
    //   35: invokevirtual 58	java/io/InputStream:available	()I
    //   38: istore_1
    //   39: aload_2
    //   40: astore_3
    //   41: aload 6
    //   43: astore 4
    //   45: aload 7
    //   47: astore 5
    //   49: iload_1
    //   50: newarray <illegal type>
    //   52: astore 6
    //   54: aload_2
    //   55: astore_3
    //   56: aload 6
    //   58: astore 4
    //   60: aload 6
    //   62: astore 5
    //   64: aload_2
    //   65: aload 6
    //   67: iconst_0
    //   68: iload_1
    //   69: invokevirtual 62	java/io/InputStream:read	([BII)I
    //   72: pop
    //   73: aload 6
    //   75: astore_3
    //   76: aload_2
    //   77: ifnull +10 -> 87
    //   80: aload_2
    //   81: invokevirtual 63	java/io/InputStream:close	()V
    //   84: aload 6
    //   86: astore_3
    //   87: aload_3
    //   88: areturn
    //   89: astore_2
    //   90: aload_2
    //   91: invokevirtual 37	java/io/IOException:printStackTrace	()V
    //   94: aload 6
    //   96: areturn
    //   97: astore_2
    //   98: aconst_null
    //   99: astore_2
    //   100: aload_2
    //   101: astore_3
    //   102: new 65	android/app/AlertDialog$Builder
    //   105: dup
    //   106: aload_0
    //   107: getfield 13	com/f/a/a/m:a	Landroid/content/Context;
    //   110: invokespecial 67	android/app/AlertDialog$Builder:<init>	(Landroid/content/Context;)V
    //   113: ldc 69
    //   115: invokevirtual 73	android/app/AlertDialog$Builder:setTitle	(Ljava/lang/CharSequence;)Landroid/app/AlertDialog$Builder;
    //   118: aload_0
    //   119: getfield 13	com/f/a/a/m:a	Landroid/content/Context;
    //   122: invokestatic 77	com/f/a/a/bp:a	()I
    //   125: invokevirtual 81	android/content/Context:getString	(I)Ljava/lang/String;
    //   128: invokevirtual 84	android/app/AlertDialog$Builder:setMessage	(Ljava/lang/CharSequence;)Landroid/app/AlertDialog$Builder;
    //   131: ldc 86
    //   133: new 88	com/f/a/a/p
    //   136: dup
    //   137: aload_0
    //   138: invokespecial 91	com/f/a/a/p:<init>	(Lcom/f/a/a/m;)V
    //   141: invokevirtual 95	android/app/AlertDialog$Builder:setPositiveButton	(Ljava/lang/CharSequence;Landroid/content/DialogInterface$OnClickListener;)Landroid/app/AlertDialog$Builder;
    //   144: invokevirtual 99	android/app/AlertDialog$Builder:show	()Landroid/app/AlertDialog;
    //   147: pop
    //   148: aload 5
    //   150: astore_3
    //   151: aload_2
    //   152: ifnull -65 -> 87
    //   155: aload_2
    //   156: invokevirtual 63	java/io/InputStream:close	()V
    //   159: aload 5
    //   161: areturn
    //   162: astore_2
    //   163: aload_2
    //   164: invokevirtual 37	java/io/IOException:printStackTrace	()V
    //   167: aload 5
    //   169: areturn
    //   170: astore_3
    //   171: aconst_null
    //   172: astore_2
    //   173: aload_3
    //   174: invokevirtual 100	java/lang/Exception:printStackTrace	()V
    //   177: aload 4
    //   179: astore_3
    //   180: aload_2
    //   181: ifnull -94 -> 87
    //   184: aload_2
    //   185: invokevirtual 63	java/io/InputStream:close	()V
    //   188: aload 4
    //   190: areturn
    //   191: astore_2
    //   192: aload_2
    //   193: invokevirtual 37	java/io/IOException:printStackTrace	()V
    //   196: aload 4
    //   198: areturn
    //   199: astore_2
    //   200: aconst_null
    //   201: astore_3
    //   202: aload_3
    //   203: ifnull +7 -> 210
    //   206: aload_3
    //   207: invokevirtual 63	java/io/InputStream:close	()V
    //   210: aload_2
    //   211: athrow
    //   212: astore_3
    //   213: aload_3
    //   214: invokevirtual 37	java/io/IOException:printStackTrace	()V
    //   217: goto -7 -> 210
    //   220: astore_2
    //   221: goto -19 -> 202
    //   224: astore 4
    //   226: aload_2
    //   227: astore_3
    //   228: aload 4
    //   230: astore_2
    //   231: goto -29 -> 202
    //   234: astore_3
    //   235: goto -62 -> 173
    //   238: astore_3
    //   239: goto -139 -> 100
    // Local variable table:
    //   start	length	slot	name	signature
    //   0	242	0	this	m
    //   0	242	1	paramInt	int
    //   23	58	2	localInputStream	java.io.InputStream
    //   89	2	2	localIOException1	java.io.IOException
    //   97	1	2	localNotFoundException1	android.content.res.Resources.NotFoundException
    //   99	57	2	localObject1	Object
    //   162	2	2	localIOException2	java.io.IOException
    //   172	13	2	localObject2	Object
    //   191	2	2	localIOException3	java.io.IOException
    //   199	12	2	localObject3	Object
    //   220	7	2	localObject4	Object
    //   230	1	2	localObject5	Object
    //   25	126	3	localObject6	Object
    //   170	4	3	localException1	Exception
    //   179	28	3	localObject7	Object
    //   212	2	3	localIOException4	java.io.IOException
    //   227	1	3	localObject8	Object
    //   234	1	3	localException2	Exception
    //   238	1	3	localNotFoundException2	android.content.res.Resources.NotFoundException
    //   1	196	4	localObject9	Object
    //   224	5	4	localObject10	Object
    //   10	158	5	localObject11	Object
    //   4	91	6	arrayOfByte	byte[]
    //   7	39	7	localObject12	Object
    // Exception table:
    //   from	to	target	type
    //   80	84	89	java/io/IOException
    //   12	24	97	android/content/res/Resources$NotFoundException
    //   155	159	162	java/io/IOException
    //   12	24	170	java/lang/Exception
    //   184	188	191	java/io/IOException
    //   12	24	199	finally
    //   206	210	212	java/io/IOException
    //   34	39	220	finally
    //   49	54	220	finally
    //   64	73	220	finally
    //   102	148	220	finally
    //   173	177	224	finally
    //   34	39	234	java/lang/Exception
    //   49	54	234	java/lang/Exception
    //   64	73	234	java/lang/Exception
    //   34	39	238	android/content/res/Resources$NotFoundException
    //   49	54	238	android/content/res/Resources$NotFoundException
    //   64	73	238	android/content/res/Resources$NotFoundException
  }
  
  /* Error */
  public byte[] a(String paramString)
  {
    // Byte code:
    //   0: new 103	java/io/FileInputStream
    //   3: dup
    //   4: aload_1
    //   5: invokespecial 104	java/io/FileInputStream:<init>	(Ljava/lang/String;)V
    //   8: astore_3
    //   9: aload_3
    //   10: astore_1
    //   11: aload_3
    //   12: invokevirtual 105	java/io/FileInputStream:available	()I
    //   15: istore 5
    //   17: aload_3
    //   18: astore_1
    //   19: iload 5
    //   21: newarray <illegal type>
    //   23: astore_2
    //   24: aload_3
    //   25: astore_1
    //   26: aload_3
    //   27: aload_2
    //   28: iconst_0
    //   29: iload 5
    //   31: invokevirtual 106	java/io/FileInputStream:read	([BII)I
    //   34: pop
    //   35: aload_2
    //   36: astore_1
    //   37: aload_3
    //   38: ifnull +9 -> 47
    //   41: aload_3
    //   42: invokevirtual 107	java/io/FileInputStream:close	()V
    //   45: aload_2
    //   46: astore_1
    //   47: aload_1
    //   48: areturn
    //   49: astore 4
    //   51: aconst_null
    //   52: astore_3
    //   53: aconst_null
    //   54: astore_2
    //   55: aload_3
    //   56: astore_1
    //   57: aload 4
    //   59: invokevirtual 36	java/io/FileNotFoundException:printStackTrace	()V
    //   62: aload_2
    //   63: astore_1
    //   64: aload_3
    //   65: ifnull -18 -> 47
    //   68: aload_3
    //   69: invokevirtual 107	java/io/FileInputStream:close	()V
    //   72: aload_2
    //   73: areturn
    //   74: astore_1
    //   75: aload_2
    //   76: areturn
    //   77: astore 4
    //   79: aconst_null
    //   80: astore_3
    //   81: aconst_null
    //   82: astore_2
    //   83: aload_3
    //   84: astore_1
    //   85: aload 4
    //   87: invokevirtual 37	java/io/IOException:printStackTrace	()V
    //   90: aload_2
    //   91: astore_1
    //   92: aload_3
    //   93: ifnull -46 -> 47
    //   96: aload_3
    //   97: invokevirtual 107	java/io/FileInputStream:close	()V
    //   100: aload_2
    //   101: areturn
    //   102: astore_1
    //   103: aload_2
    //   104: areturn
    //   105: astore_2
    //   106: aconst_null
    //   107: astore_1
    //   108: aload_1
    //   109: ifnull +7 -> 116
    //   112: aload_1
    //   113: invokevirtual 107	java/io/FileInputStream:close	()V
    //   116: aload_2
    //   117: athrow
    //   118: astore_1
    //   119: aload_2
    //   120: areturn
    //   121: astore_1
    //   122: goto -6 -> 116
    //   125: astore_2
    //   126: goto -18 -> 108
    //   129: astore 4
    //   131: aconst_null
    //   132: astore_2
    //   133: goto -50 -> 83
    //   136: astore 4
    //   138: goto -55 -> 83
    //   141: astore 4
    //   143: aconst_null
    //   144: astore_2
    //   145: goto -90 -> 55
    //   148: astore 4
    //   150: goto -95 -> 55
    // Local variable table:
    //   start	length	slot	name	signature
    //   0	153	0	this	m
    //   0	153	1	paramString	String
    //   23	81	2	arrayOfByte1	byte[]
    //   105	15	2	arrayOfByte2	byte[]
    //   125	1	2	localObject1	Object
    //   132	13	2	localObject2	Object
    //   8	89	3	localFileInputStream	java.io.FileInputStream
    //   49	9	4	localFileNotFoundException1	java.io.FileNotFoundException
    //   77	9	4	localIOException1	java.io.IOException
    //   129	1	4	localIOException2	java.io.IOException
    //   136	1	4	localIOException3	java.io.IOException
    //   141	1	4	localFileNotFoundException2	java.io.FileNotFoundException
    //   148	1	4	localFileNotFoundException3	java.io.FileNotFoundException
    //   15	15	5	i	int
    // Exception table:
    //   from	to	target	type
    //   0	9	49	java/io/FileNotFoundException
    //   68	72	74	java/lang/Exception
    //   0	9	77	java/io/IOException
    //   96	100	102	java/lang/Exception
    //   0	9	105	finally
    //   41	45	118	java/lang/Exception
    //   112	116	121	java/lang/Exception
    //   11	17	125	finally
    //   19	24	125	finally
    //   26	35	125	finally
    //   57	62	125	finally
    //   85	90	125	finally
    //   11	17	129	java/io/IOException
    //   19	24	129	java/io/IOException
    //   26	35	136	java/io/IOException
    //   11	17	141	java/io/FileNotFoundException
    //   19	24	141	java/io/FileNotFoundException
    //   26	35	148	java/io/FileNotFoundException
  }
}


/* Location:              E:\apk\dazhihui2\classes-dex2jar.jar!\com\f\a\a\m.class
 * Java compiler version: 6 (50.0)
 * JD-Core Version:       0.7.1
 */