package com.f.a.a;

import java.util.Vector;

public class y
{
  private String a;
  private String b;
  private byte[] c;
  private byte[] d;
  private String e;
  private String f;
  private byte[] g;
  private byte[] h;
  private String i;
  private byte j;
  private long k;
  private String l;
  private Vector m;
  private Vector n;
  
  public String a()
  {
    return this.a;
  }
  
  /* Error */
  public void a(byte[] paramArrayOfByte)
  {
    // Byte code:
    //   0: new 36	java/io/ByteArrayInputStream
    //   3: dup
    //   4: aload_1
    //   5: invokespecial 38	java/io/ByteArrayInputStream:<init>	([B)V
    //   8: astore_3
    //   9: aload_3
    //   10: astore_2
    //   11: invokestatic 44	android/util/Xml:newPullParser	()Lorg/xmlpull/v1/XmlPullParser;
    //   14: astore 5
    //   16: aload_3
    //   17: astore_2
    //   18: aload 5
    //   20: aload_3
    //   21: ldc 46
    //   23: invokeinterface 52 3 0
    //   28: aload_3
    //   29: astore_2
    //   30: aload 5
    //   32: invokeinterface 56 1 0
    //   37: istore 7
    //   39: ldc 58
    //   41: astore 4
    //   43: goto +723 -> 766
    //   46: aload_3
    //   47: astore_2
    //   48: aload 5
    //   50: invokeinterface 61 1 0
    //   55: istore 7
    //   57: aload_1
    //   58: astore 4
    //   60: goto +706 -> 766
    //   63: aload_3
    //   64: astore_2
    //   65: aload 5
    //   67: invokeinterface 64 1 0
    //   72: astore 6
    //   74: aload_3
    //   75: astore_2
    //   76: aload 6
    //   78: ldc 66
    //   80: invokevirtual 72	java/lang/String:equalsIgnoreCase	(Ljava/lang/String;)Z
    //   83: ifeq +45 -> 128
    //   86: aload_3
    //   87: astore_2
    //   88: aload_0
    //   89: aload 5
    //   91: aconst_null
    //   92: ldc 74
    //   94: invokeinterface 78 3 0
    //   99: putfield 31	com/f/a/a/y:a	Ljava/lang/String;
    //   102: aload 4
    //   104: astore_1
    //   105: goto -59 -> 46
    //   108: astore_2
    //   109: aload_3
    //   110: astore_1
    //   111: aload_2
    //   112: astore_3
    //   113: aload_1
    //   114: astore_2
    //   115: aload_3
    //   116: invokevirtual 81	java/lang/Exception:printStackTrace	()V
    //   119: aload_1
    //   120: ifnull +7 -> 127
    //   123: aload_1
    //   124: invokevirtual 86	java/io/InputStream:close	()V
    //   127: return
    //   128: aload_3
    //   129: astore_2
    //   130: aload 6
    //   132: ldc 88
    //   134: invokevirtual 72	java/lang/String:equalsIgnoreCase	(Ljava/lang/String;)Z
    //   137: ifeq +25 -> 162
    //   140: aload_3
    //   141: astore_2
    //   142: aload_0
    //   143: aload 5
    //   145: aconst_null
    //   146: ldc 74
    //   148: invokeinterface 78 3 0
    //   153: putfield 90	com/f/a/a/y:e	Ljava/lang/String;
    //   156: ldc 88
    //   158: astore_1
    //   159: goto -113 -> 46
    //   162: aload_3
    //   163: astore_2
    //   164: aload 6
    //   166: ldc 92
    //   168: invokevirtual 72	java/lang/String:equalsIgnoreCase	(Ljava/lang/String;)Z
    //   171: ifeq +25 -> 196
    //   174: aload_3
    //   175: astore_2
    //   176: aload_0
    //   177: aload 5
    //   179: aconst_null
    //   180: ldc 74
    //   182: invokeinterface 78 3 0
    //   187: putfield 94	com/f/a/a/y:i	Ljava/lang/String;
    //   190: ldc 92
    //   192: astore_1
    //   193: goto -147 -> 46
    //   196: aload_3
    //   197: astore_2
    //   198: aload 6
    //   200: ldc 96
    //   202: invokevirtual 72	java/lang/String:equalsIgnoreCase	(Ljava/lang/String;)Z
    //   205: ifeq +79 -> 284
    //   208: aload_3
    //   209: astore_2
    //   210: ldc 88
    //   212: aload 4
    //   214: invokevirtual 100	java/lang/String:equals	(Ljava/lang/Object;)Z
    //   217: ifeq +33 -> 250
    //   220: aload_3
    //   221: astore_2
    //   222: aload_0
    //   223: aload 5
    //   225: invokeinterface 103 1 0
    //   230: putfield 105	com/f/a/a/y:b	Ljava/lang/String;
    //   233: aload 4
    //   235: astore_1
    //   236: goto -190 -> 46
    //   239: astore_1
    //   240: aload_2
    //   241: ifnull +7 -> 248
    //   244: aload_2
    //   245: invokevirtual 86	java/io/InputStream:close	()V
    //   248: aload_1
    //   249: athrow
    //   250: aload 4
    //   252: astore_1
    //   253: aload_3
    //   254: astore_2
    //   255: ldc 92
    //   257: aload 4
    //   259: invokevirtual 100	java/lang/String:equals	(Ljava/lang/Object;)Z
    //   262: ifeq -216 -> 46
    //   265: aload_3
    //   266: astore_2
    //   267: aload_0
    //   268: aload 5
    //   270: invokeinterface 103 1 0
    //   275: putfield 107	com/f/a/a/y:f	Ljava/lang/String;
    //   278: aload 4
    //   280: astore_1
    //   281: goto -235 -> 46
    //   284: aload_3
    //   285: astore_2
    //   286: aload 6
    //   288: ldc 108
    //   290: invokevirtual 72	java/lang/String:equalsIgnoreCase	(Ljava/lang/String;)Z
    //   293: ifeq +74 -> 367
    //   296: aload_3
    //   297: astore_2
    //   298: ldc 88
    //   300: aload 4
    //   302: invokevirtual 100	java/lang/String:equals	(Ljava/lang/Object;)Z
    //   305: ifeq +25 -> 330
    //   308: aload_3
    //   309: astore_2
    //   310: aload_0
    //   311: aload 5
    //   313: invokeinterface 103 1 0
    //   318: invokestatic 113	com/f/a/a/ce:a	(Ljava/lang/String;)[B
    //   321: putfield 115	com/f/a/a/y:c	[B
    //   324: aload 4
    //   326: astore_1
    //   327: goto -281 -> 46
    //   330: aload 4
    //   332: astore_1
    //   333: aload_3
    //   334: astore_2
    //   335: ldc 92
    //   337: aload 4
    //   339: invokevirtual 100	java/lang/String:equals	(Ljava/lang/Object;)Z
    //   342: ifeq -296 -> 46
    //   345: aload_3
    //   346: astore_2
    //   347: aload_0
    //   348: aload 5
    //   350: invokeinterface 103 1 0
    //   355: invokestatic 113	com/f/a/a/ce:a	(Ljava/lang/String;)[B
    //   358: putfield 117	com/f/a/a/y:g	[B
    //   361: aload 4
    //   363: astore_1
    //   364: goto -318 -> 46
    //   367: aload_3
    //   368: astore_2
    //   369: aload 6
    //   371: ldc 118
    //   373: invokevirtual 72	java/lang/String:equalsIgnoreCase	(Ljava/lang/String;)Z
    //   376: ifeq +74 -> 450
    //   379: aload_3
    //   380: astore_2
    //   381: ldc 88
    //   383: aload 4
    //   385: invokevirtual 100	java/lang/String:equals	(Ljava/lang/Object;)Z
    //   388: ifeq +25 -> 413
    //   391: aload_3
    //   392: astore_2
    //   393: aload_0
    //   394: aload 5
    //   396: invokeinterface 103 1 0
    //   401: invokestatic 113	com/f/a/a/ce:a	(Ljava/lang/String;)[B
    //   404: putfield 120	com/f/a/a/y:d	[B
    //   407: aload 4
    //   409: astore_1
    //   410: goto -364 -> 46
    //   413: aload 4
    //   415: astore_1
    //   416: aload_3
    //   417: astore_2
    //   418: ldc 92
    //   420: aload 4
    //   422: invokevirtual 100	java/lang/String:equals	(Ljava/lang/Object;)Z
    //   425: ifeq -379 -> 46
    //   428: aload_3
    //   429: astore_2
    //   430: aload_0
    //   431: aload 5
    //   433: invokeinterface 103 1 0
    //   438: invokestatic 113	com/f/a/a/ce:a	(Ljava/lang/String;)[B
    //   441: putfield 122	com/f/a/a/y:h	[B
    //   444: aload 4
    //   446: astore_1
    //   447: goto -401 -> 46
    //   450: aload_3
    //   451: astore_2
    //   452: aload 6
    //   454: ldc 124
    //   456: invokevirtual 72	java/lang/String:equalsIgnoreCase	(Ljava/lang/String;)Z
    //   459: ifeq +32 -> 491
    //   462: aload_3
    //   463: astore_2
    //   464: aload_0
    //   465: new 126	java/lang/Byte
    //   468: dup
    //   469: aload 5
    //   471: invokeinterface 103 1 0
    //   476: invokespecial 129	java/lang/Byte:<init>	(Ljava/lang/String;)V
    //   479: invokevirtual 133	java/lang/Byte:byteValue	()B
    //   482: putfield 135	com/f/a/a/y:j	B
    //   485: aload 4
    //   487: astore_1
    //   488: goto -442 -> 46
    //   491: aload_3
    //   492: astore_2
    //   493: aload 6
    //   495: ldc -119
    //   497: invokevirtual 72	java/lang/String:equalsIgnoreCase	(Ljava/lang/String;)Z
    //   500: ifeq +22 -> 522
    //   503: aload_3
    //   504: astore_2
    //   505: aload_0
    //   506: aload 5
    //   508: invokeinterface 103 1 0
    //   513: putfield 139	com/f/a/a/y:l	Ljava/lang/String;
    //   516: aload 4
    //   518: astore_1
    //   519: goto -473 -> 46
    //   522: aload_3
    //   523: astore_2
    //   524: aload 6
    //   526: ldc -115
    //   528: invokevirtual 72	java/lang/String:equalsIgnoreCase	(Ljava/lang/String;)Z
    //   531: ifeq +22 -> 553
    //   534: aload_3
    //   535: astore_2
    //   536: aload_0
    //   537: new 143	java/util/Vector
    //   540: dup
    //   541: invokespecial 144	java/util/Vector:<init>	()V
    //   544: putfield 146	com/f/a/a/y:m	Ljava/util/Vector;
    //   547: ldc -115
    //   549: astore_1
    //   550: goto -504 -> 46
    //   553: aload_3
    //   554: astore_2
    //   555: aload 6
    //   557: ldc -108
    //   559: invokevirtual 72	java/lang/String:equalsIgnoreCase	(Ljava/lang/String;)Z
    //   562: ifeq +22 -> 584
    //   565: aload_3
    //   566: astore_2
    //   567: aload_0
    //   568: new 143	java/util/Vector
    //   571: dup
    //   572: invokespecial 144	java/util/Vector:<init>	()V
    //   575: putfield 150	com/f/a/a/y:n	Ljava/util/Vector;
    //   578: ldc -108
    //   580: astore_1
    //   581: goto -535 -> 46
    //   584: aload_3
    //   585: astore_2
    //   586: aload 6
    //   588: ldc -104
    //   590: invokevirtual 72	java/lang/String:equalsIgnoreCase	(Ljava/lang/String;)Z
    //   593: ifeq +100 -> 693
    //   596: aload_3
    //   597: astore_2
    //   598: ldc -115
    //   600: aload 4
    //   602: invokevirtual 100	java/lang/String:equals	(Ljava/lang/Object;)Z
    //   605: ifeq +38 -> 643
    //   608: aload 4
    //   610: astore_1
    //   611: aload_3
    //   612: astore_2
    //   613: aload_0
    //   614: getfield 146	com/f/a/a/y:m	Ljava/util/Vector;
    //   617: ifnull -571 -> 46
    //   620: aload_3
    //   621: astore_2
    //   622: aload_0
    //   623: getfield 146	com/f/a/a/y:m	Ljava/util/Vector;
    //   626: aload 5
    //   628: invokeinterface 103 1 0
    //   633: invokevirtual 155	java/util/Vector:add	(Ljava/lang/Object;)Z
    //   636: pop
    //   637: aload 4
    //   639: astore_1
    //   640: goto -594 -> 46
    //   643: aload 4
    //   645: astore_1
    //   646: aload_3
    //   647: astore_2
    //   648: ldc -108
    //   650: aload 4
    //   652: invokevirtual 100	java/lang/String:equals	(Ljava/lang/Object;)Z
    //   655: ifeq -609 -> 46
    //   658: aload 4
    //   660: astore_1
    //   661: aload_3
    //   662: astore_2
    //   663: aload_0
    //   664: getfield 150	com/f/a/a/y:n	Ljava/util/Vector;
    //   667: ifnull -621 -> 46
    //   670: aload_3
    //   671: astore_2
    //   672: aload_0
    //   673: getfield 150	com/f/a/a/y:n	Ljava/util/Vector;
    //   676: aload 5
    //   678: invokeinterface 103 1 0
    //   683: invokevirtual 155	java/util/Vector:add	(Ljava/lang/Object;)Z
    //   686: pop
    //   687: aload 4
    //   689: astore_1
    //   690: goto -644 -> 46
    //   693: aload 4
    //   695: astore_1
    //   696: aload_3
    //   697: astore_2
    //   698: aload 6
    //   700: ldc -99
    //   702: invokevirtual 72	java/lang/String:equalsIgnoreCase	(Ljava/lang/String;)Z
    //   705: ifeq -659 -> 46
    //   708: aload_3
    //   709: astore_2
    //   710: aload_0
    //   711: new 159	java/lang/Long
    //   714: dup
    //   715: aload 5
    //   717: invokeinterface 103 1 0
    //   722: invokespecial 160	java/lang/Long:<init>	(Ljava/lang/String;)V
    //   725: invokevirtual 164	java/lang/Long:longValue	()J
    //   728: putfield 166	com/f/a/a/y:k	J
    //   731: aload 4
    //   733: astore_1
    //   734: goto -688 -> 46
    //   737: aload_3
    //   738: ifnull -611 -> 127
    //   741: aload_3
    //   742: invokevirtual 86	java/io/InputStream:close	()V
    //   745: return
    //   746: astore_1
    //   747: return
    //   748: astore_1
    //   749: return
    //   750: astore_2
    //   751: goto -503 -> 248
    //   754: astore_1
    //   755: aconst_null
    //   756: astore_2
    //   757: goto -517 -> 240
    //   760: astore_3
    //   761: aconst_null
    //   762: astore_1
    //   763: goto -650 -> 113
    //   766: iload 7
    //   768: iconst_1
    //   769: if_icmpeq -32 -> 737
    //   772: aload 4
    //   774: astore_1
    //   775: iload 7
    //   777: tableswitch	default:+31->808, 0:+-731->46, 1:+-731->46, 2:+-714->63, 3:+-731->46
    //   808: aload 4
    //   810: astore_1
    //   811: goto -765 -> 46
    // Local variable table:
    //   start	length	slot	name	signature
    //   0	814	0	this	y
    //   0	814	1	paramArrayOfByte	byte[]
    //   10	78	2	localObject1	Object
    //   108	4	2	localException1	Exception
    //   114	596	2	localObject2	Object
    //   750	1	2	localException2	Exception
    //   756	1	2	localObject3	Object
    //   8	734	3	localObject4	Object
    //   760	1	3	localException3	Exception
    //   41	768	4	localObject5	Object
    //   14	702	5	localXmlPullParser	org.xmlpull.v1.XmlPullParser
    //   72	627	6	str	String
    //   37	739	7	i1	int
    // Exception table:
    //   from	to	target	type
    //   11	16	108	java/lang/Exception
    //   18	28	108	java/lang/Exception
    //   30	39	108	java/lang/Exception
    //   48	57	108	java/lang/Exception
    //   65	74	108	java/lang/Exception
    //   76	86	108	java/lang/Exception
    //   88	102	108	java/lang/Exception
    //   130	140	108	java/lang/Exception
    //   142	156	108	java/lang/Exception
    //   164	174	108	java/lang/Exception
    //   176	190	108	java/lang/Exception
    //   198	208	108	java/lang/Exception
    //   210	220	108	java/lang/Exception
    //   222	233	108	java/lang/Exception
    //   255	265	108	java/lang/Exception
    //   267	278	108	java/lang/Exception
    //   286	296	108	java/lang/Exception
    //   298	308	108	java/lang/Exception
    //   310	324	108	java/lang/Exception
    //   335	345	108	java/lang/Exception
    //   347	361	108	java/lang/Exception
    //   369	379	108	java/lang/Exception
    //   381	391	108	java/lang/Exception
    //   393	407	108	java/lang/Exception
    //   418	428	108	java/lang/Exception
    //   430	444	108	java/lang/Exception
    //   452	462	108	java/lang/Exception
    //   464	485	108	java/lang/Exception
    //   493	503	108	java/lang/Exception
    //   505	516	108	java/lang/Exception
    //   524	534	108	java/lang/Exception
    //   536	547	108	java/lang/Exception
    //   555	565	108	java/lang/Exception
    //   567	578	108	java/lang/Exception
    //   586	596	108	java/lang/Exception
    //   598	608	108	java/lang/Exception
    //   613	620	108	java/lang/Exception
    //   622	637	108	java/lang/Exception
    //   648	658	108	java/lang/Exception
    //   663	670	108	java/lang/Exception
    //   672	687	108	java/lang/Exception
    //   698	708	108	java/lang/Exception
    //   710	731	108	java/lang/Exception
    //   11	16	239	finally
    //   18	28	239	finally
    //   30	39	239	finally
    //   48	57	239	finally
    //   65	74	239	finally
    //   76	86	239	finally
    //   88	102	239	finally
    //   115	119	239	finally
    //   130	140	239	finally
    //   142	156	239	finally
    //   164	174	239	finally
    //   176	190	239	finally
    //   198	208	239	finally
    //   210	220	239	finally
    //   222	233	239	finally
    //   255	265	239	finally
    //   267	278	239	finally
    //   286	296	239	finally
    //   298	308	239	finally
    //   310	324	239	finally
    //   335	345	239	finally
    //   347	361	239	finally
    //   369	379	239	finally
    //   381	391	239	finally
    //   393	407	239	finally
    //   418	428	239	finally
    //   430	444	239	finally
    //   452	462	239	finally
    //   464	485	239	finally
    //   493	503	239	finally
    //   505	516	239	finally
    //   524	534	239	finally
    //   536	547	239	finally
    //   555	565	239	finally
    //   567	578	239	finally
    //   586	596	239	finally
    //   598	608	239	finally
    //   613	620	239	finally
    //   622	637	239	finally
    //   648	658	239	finally
    //   663	670	239	finally
    //   672	687	239	finally
    //   698	708	239	finally
    //   710	731	239	finally
    //   741	745	746	java/lang/Exception
    //   123	127	748	java/lang/Exception
    //   244	248	750	java/lang/Exception
    //   0	9	754	finally
    //   0	9	760	java/lang/Exception
  }
  
  public String b()
  {
    return this.e;
  }
  
  public byte c()
  {
    return this.j;
  }
  
  public byte[] d()
  {
    return this.c;
  }
  
  public byte[] e()
  {
    return this.d;
  }
  
  public byte[] f()
  {
    return this.g;
  }
  
  public byte[] g()
  {
    return this.h;
  }
  
  public Vector h()
  {
    return this.n;
  }
}


/* Location:              E:\apk\dazhihui2\classes-dex2jar.jar!\com\f\a\a\y.class
 * Java compiler version: 6 (50.0)
 * JD-Core Version:       0.7.1
 */