package qalsdk;

class ai
  extends Thread
{
  ai(ah paramah, String paramString1, boolean paramBoolean, String paramString2) {}
  
  /* Error */
  public void run()
  {
    // Byte code:
    //   0: new 32	com/tencent/qalsdk/im_open/mobroute$MobRouteSSOListReq
    //   3: dup
    //   4: invokespecial 33	com/tencent/qalsdk/im_open/mobroute$MobRouteSSOListReq:<init>	()V
    //   7: astore_2
    //   8: invokestatic 38	com/tencent/qalsdk/core/k:a	()Ljava/lang/String;
    //   11: ifnull +13 -> 24
    //   14: aload_2
    //   15: getfield 42	com/tencent/qalsdk/im_open/mobroute$MobRouteSSOListReq:string_imei	Lcom/tencent/mobileqq/pb/PBStringField;
    //   18: invokestatic 38	com/tencent/qalsdk/core/k:a	()Ljava/lang/String;
    //   21: invokevirtual 48	com/tencent/mobileqq/pb/PBStringField:set	(Ljava/lang/String;)V
    //   24: invokestatic 50	com/tencent/qalsdk/core/k:b	()Ljava/lang/String;
    //   27: ifnull +13 -> 40
    //   30: aload_2
    //   31: getfield 53	com/tencent/qalsdk/im_open/mobroute$MobRouteSSOListReq:string_imsi	Lcom/tencent/mobileqq/pb/PBStringField;
    //   34: invokestatic 50	com/tencent/qalsdk/core/k:b	()Ljava/lang/String;
    //   37: invokevirtual 48	com/tencent/mobileqq/pb/PBStringField:set	(Ljava/lang/String;)V
    //   40: aload_0
    //   41: getfield 17	qalsdk/ai:a	Ljava/lang/String;
    //   44: ifnull +14 -> 58
    //   47: aload_2
    //   48: getfield 56	com/tencent/qalsdk/im_open/mobroute$MobRouteSSOListReq:string_uin	Lcom/tencent/mobileqq/pb/PBStringField;
    //   51: aload_0
    //   52: getfield 17	qalsdk/ai:a	Ljava/lang/String;
    //   55: invokevirtual 48	com/tencent/mobileqq/pb/PBStringField:set	(Ljava/lang/String;)V
    //   58: aload_0
    //   59: getfield 19	qalsdk/ai:b	Z
    //   62: ifeq +976 -> 1038
    //   65: iconst_1
    //   66: istore 5
    //   68: aload_2
    //   69: getfield 60	com/tencent/qalsdk/im_open/mobroute$MobRouteSSOListReq:uint32_nettype	Lcom/tencent/mobileqq/pb/PBUInt32Field;
    //   72: iload 5
    //   74: invokevirtual 65	com/tencent/mobileqq/pb/PBUInt32Field:set	(I)V
    //   77: aload_2
    //   78: getfield 68	com/tencent/qalsdk/im_open/mobroute$MobRouteSSOListReq:uint32_uintype	Lcom/tencent/mobileqq/pb/PBUInt32Field;
    //   81: bipush 20
    //   83: invokevirtual 65	com/tencent/mobileqq/pb/PBUInt32Field:set	(I)V
    //   86: ldc 70
    //   88: new 72	java/lang/StringBuilder
    //   91: dup
    //   92: invokespecial 73	java/lang/StringBuilder:<init>	()V
    //   95: ldc 75
    //   97: invokevirtual 79	java/lang/StringBuilder:append	(Ljava/lang/String;)Ljava/lang/StringBuilder;
    //   100: invokestatic 38	com/tencent/qalsdk/core/k:a	()Ljava/lang/String;
    //   103: invokevirtual 79	java/lang/StringBuilder:append	(Ljava/lang/String;)Ljava/lang/StringBuilder;
    //   106: ldc 81
    //   108: invokevirtual 79	java/lang/StringBuilder:append	(Ljava/lang/String;)Ljava/lang/StringBuilder;
    //   111: invokestatic 50	com/tencent/qalsdk/core/k:b	()Ljava/lang/String;
    //   114: invokevirtual 79	java/lang/StringBuilder:append	(Ljava/lang/String;)Ljava/lang/StringBuilder;
    //   117: ldc 81
    //   119: invokevirtual 79	java/lang/StringBuilder:append	(Ljava/lang/String;)Ljava/lang/StringBuilder;
    //   122: aload_0
    //   123: getfield 17	qalsdk/ai:a	Ljava/lang/String;
    //   126: invokevirtual 79	java/lang/StringBuilder:append	(Ljava/lang/String;)Ljava/lang/StringBuilder;
    //   129: invokevirtual 84	java/lang/StringBuilder:toString	()Ljava/lang/String;
    //   132: invokestatic 89	com/tencent/qalsdk/util/QLog:d	(Ljava/lang/String;Ljava/lang/String;)V
    //   135: aload_2
    //   136: getfield 92	com/tencent/qalsdk/im_open/mobroute$MobRouteSSOListReq:uint32_appid	Lcom/tencent/mobileqq/pb/PBUInt32Field;
    //   139: aload_0
    //   140: getfield 15	qalsdk/ai:d	Lqalsdk/ah;
    //   143: getfield 97	qalsdk/ah:c	Lcom/tencent/qalsdk/core/j;
    //   146: invokevirtual 103	com/tencent/qalsdk/core/j:i	()I
    //   149: invokevirtual 65	com/tencent/mobileqq/pb/PBUInt32Field:set	(I)V
    //   152: aload_2
    //   153: invokevirtual 106	com/tencent/qalsdk/im_open/mobroute$MobRouteSSOListReq:getSerializedSize	()I
    //   156: bipush 14
    //   158: iadd
    //   159: istore 5
    //   161: iload 5
    //   163: invokestatic 112	java/nio/ByteBuffer:allocate	(I)Ljava/nio/ByteBuffer;
    //   166: astore_1
    //   167: aload_1
    //   168: iconst_2
    //   169: invokevirtual 116	java/nio/ByteBuffer:put	(B)Ljava/nio/ByteBuffer;
    //   172: pop
    //   173: aload_1
    //   174: iload 5
    //   176: invokevirtual 119	java/nio/ByteBuffer:putInt	(I)Ljava/nio/ByteBuffer;
    //   179: pop
    //   180: aload_1
    //   181: iconst_1
    //   182: invokevirtual 123	java/nio/ByteBuffer:putShort	(S)Ljava/nio/ByteBuffer;
    //   185: pop
    //   186: aload_1
    //   187: iconst_2
    //   188: invokevirtual 123	java/nio/ByteBuffer:putShort	(S)Ljava/nio/ByteBuffer;
    //   191: pop
    //   192: aload_1
    //   193: invokestatic 126	com/tencent/qalsdk/core/j:f	()I
    //   196: invokevirtual 119	java/nio/ByteBuffer:putInt	(I)Ljava/nio/ByteBuffer;
    //   199: pop
    //   200: aload_1
    //   201: aload_2
    //   202: invokevirtual 130	com/tencent/qalsdk/im_open/mobroute$MobRouteSSOListReq:toByteArray	()[B
    //   205: invokevirtual 133	java/nio/ByteBuffer:put	([B)Ljava/nio/ByteBuffer;
    //   208: pop
    //   209: aload_1
    //   210: iconst_3
    //   211: invokevirtual 116	java/nio/ByteBuffer:put	(B)Ljava/nio/ByteBuffer;
    //   214: pop
    //   215: aload_1
    //   216: invokevirtual 137	java/nio/ByteBuffer:flip	()Ljava/nio/Buffer;
    //   219: pop
    //   220: aload_1
    //   221: invokevirtual 140	java/nio/ByteBuffer:limit	()I
    //   224: newarray <illegal type>
    //   226: astore_2
    //   227: aload_1
    //   228: aload_2
    //   229: invokevirtual 143	java/nio/ByteBuffer:get	([B)Ljava/nio/ByteBuffer;
    //   232: pop
    //   233: new 145	com/tencent/qalsdk/util/Cryptor
    //   236: dup
    //   237: invokespecial 146	com/tencent/qalsdk/util/Cryptor:<init>	()V
    //   240: aload_2
    //   241: invokestatic 149	qalsdk/ah:x	()[B
    //   244: invokevirtual 153	com/tencent/qalsdk/util/Cryptor:encrypt	([B[B)[B
    //   247: astore_1
    //   248: aconst_null
    //   249: astore_3
    //   250: new 155	java/net/URL
    //   253: dup
    //   254: ldc -99
    //   256: invokespecial 159	java/net/URL:<init>	(Ljava/lang/String;)V
    //   259: astore_2
    //   260: invokestatic 165	java/lang/System:currentTimeMillis	()J
    //   263: lstore 7
    //   265: ldc 70
    //   267: iconst_1
    //   268: ldc -89
    //   270: invokestatic 170	com/tencent/qalsdk/util/QLog:i	(Ljava/lang/String;ILjava/lang/String;)V
    //   273: aload_2
    //   274: invokevirtual 174	java/net/URL:openConnection	()Ljava/net/URLConnection;
    //   277: checkcast 176	java/net/HttpURLConnection
    //   280: astore_2
    //   281: aload_2
    //   282: iconst_1
    //   283: invokevirtual 180	java/net/HttpURLConnection:setDoOutput	(Z)V
    //   286: aload_2
    //   287: ldc -74
    //   289: invokevirtual 185	java/net/HttpURLConnection:setRequestMethod	(Ljava/lang/String;)V
    //   292: aload_2
    //   293: sipush 20000
    //   296: invokevirtual 188	java/net/HttpURLConnection:setConnectTimeout	(I)V
    //   299: aload_2
    //   300: sipush 20000
    //   303: invokevirtual 191	java/net/HttpURLConnection:setReadTimeout	(I)V
    //   306: aload_2
    //   307: invokevirtual 195	java/net/HttpURLConnection:getOutputStream	()Ljava/io/OutputStream;
    //   310: aload_1
    //   311: invokevirtual 201	java/io/OutputStream:write	([B)V
    //   314: aload_2
    //   315: invokevirtual 195	java/net/HttpURLConnection:getOutputStream	()Ljava/io/OutputStream;
    //   318: invokevirtual 204	java/io/OutputStream:flush	()V
    //   321: aload_2
    //   322: invokevirtual 195	java/net/HttpURLConnection:getOutputStream	()Ljava/io/OutputStream;
    //   325: invokevirtual 207	java/io/OutputStream:close	()V
    //   328: aload_2
    //   329: invokevirtual 210	java/net/HttpURLConnection:getResponseCode	()I
    //   332: istore 5
    //   334: iload 5
    //   336: sipush 200
    //   339: if_icmpne +561 -> 900
    //   342: sipush 128
    //   345: newarray <illegal type>
    //   347: astore_1
    //   348: iconst_0
    //   349: istore 5
    //   351: new 212	java/util/ArrayList
    //   354: dup
    //   355: invokespecial 213	java/util/ArrayList:<init>	()V
    //   358: astore_3
    //   359: aload_2
    //   360: invokevirtual 217	java/net/HttpURLConnection:getInputStream	()Ljava/io/InputStream;
    //   363: aload_1
    //   364: invokevirtual 223	java/io/InputStream:read	([B)I
    //   367: istore 6
    //   369: iload 6
    //   371: iconst_m1
    //   372: if_icmpeq +36 -> 408
    //   375: iload 6
    //   377: newarray <illegal type>
    //   379: astore 4
    //   381: aload_1
    //   382: iconst_0
    //   383: aload 4
    //   385: iconst_0
    //   386: iload 6
    //   388: invokestatic 227	java/lang/System:arraycopy	(Ljava/lang/Object;ILjava/lang/Object;II)V
    //   391: aload_3
    //   392: aload 4
    //   394: invokevirtual 231	java/util/ArrayList:add	(Ljava/lang/Object;)Z
    //   397: pop
    //   398: iload 5
    //   400: iload 6
    //   402: iadd
    //   403: istore 5
    //   405: goto -46 -> 359
    //   408: aload_3
    //   409: invokevirtual 234	java/util/ArrayList:size	()I
    //   412: iconst_1
    //   413: if_icmpne +317 -> 730
    //   416: aload_3
    //   417: iconst_0
    //   418: invokevirtual 237	java/util/ArrayList:get	(I)Ljava/lang/Object;
    //   421: checkcast 239	[B
    //   424: astore_1
    //   425: invokestatic 243	com/tencent/qalsdk/util/QLog:isDevelopLevel	()Z
    //   428: ifeq +43 -> 471
    //   431: ldc 70
    //   433: iconst_4
    //   434: new 72	java/lang/StringBuilder
    //   437: dup
    //   438: invokespecial 73	java/lang/StringBuilder:<init>	()V
    //   441: ldc -11
    //   443: invokevirtual 79	java/lang/StringBuilder:append	(Ljava/lang/String;)Ljava/lang/StringBuilder;
    //   446: invokestatic 165	java/lang/System:currentTimeMillis	()J
    //   449: lload 7
    //   451: lsub
    //   452: invokevirtual 248	java/lang/StringBuilder:append	(J)Ljava/lang/StringBuilder;
    //   455: ldc -6
    //   457: invokevirtual 79	java/lang/StringBuilder:append	(Ljava/lang/String;)Ljava/lang/StringBuilder;
    //   460: aload_1
    //   461: arraylength
    //   462: invokevirtual 253	java/lang/StringBuilder:append	(I)Ljava/lang/StringBuilder;
    //   465: invokevirtual 84	java/lang/StringBuilder:toString	()Ljava/lang/String;
    //   468: invokestatic 255	com/tencent/qalsdk/util/QLog:d	(Ljava/lang/String;ILjava/lang/String;)V
    //   471: new 145	com/tencent/qalsdk/util/Cryptor
    //   474: dup
    //   475: invokespecial 146	com/tencent/qalsdk/util/Cryptor:<init>	()V
    //   478: aload_1
    //   479: invokestatic 149	qalsdk/ah:x	()[B
    //   482: invokevirtual 258	com/tencent/qalsdk/util/Cryptor:decrypt	([B[B)[B
    //   485: invokestatic 261	qalsdk/ah:a	([B)Z
    //   488: ifeq +298 -> 786
    //   491: invokestatic 165	java/lang/System:currentTimeMillis	()J
    //   494: putstatic 264	qalsdk/ah:i	J
    //   497: aload_0
    //   498: getfield 15	qalsdk/ai:d	Lqalsdk/ah;
    //   501: getfield 97	qalsdk/ah:c	Lcom/tencent/qalsdk/core/j;
    //   504: getfield 267	com/tencent/qalsdk/core/j:c	Lcom/tencent/qalsdk/core/o;
    //   507: getfield 272	com/tencent/qalsdk/core/o:a	Lqalsdk/av;
    //   510: iconst_1
    //   511: putfield 278	qalsdk/av:m	I
    //   514: aload_0
    //   515: getfield 19	qalsdk/ai:b	Z
    //   518: ifne +343 -> 861
    //   521: invokestatic 165	java/lang/System:currentTimeMillis	()J
    //   524: ldc_w 279
    //   527: i2l
    //   528: ladd
    //   529: putstatic 282	qalsdk/ah:g	J
    //   532: aload_0
    //   533: getfield 15	qalsdk/ai:d	Lqalsdk/ah;
    //   536: invokevirtual 285	qalsdk/ah:v	()V
    //   539: ldc_w 287
    //   542: astore_1
    //   543: aload_2
    //   544: ifnull +486 -> 1030
    //   547: aload_2
    //   548: invokevirtual 290	java/net/HttpURLConnection:disconnect	()V
    //   551: aload_1
    //   552: astore_2
    //   553: aload_0
    //   554: getfield 21	qalsdk/ai:c	Ljava/lang/String;
    //   557: ifnull +172 -> 729
    //   560: aload_0
    //   561: getfield 21	qalsdk/ai:c	Ljava/lang/String;
    //   564: invokevirtual 295	java/lang/String:length	()I
    //   567: ifle +162 -> 729
    //   570: new 212	java/util/ArrayList
    //   573: dup
    //   574: invokespecial 213	java/util/ArrayList:<init>	()V
    //   577: astore_1
    //   578: new 72	java/lang/StringBuilder
    //   581: dup
    //   582: invokespecial 73	java/lang/StringBuilder:<init>	()V
    //   585: aload_0
    //   586: getfield 15	qalsdk/ai:d	Lqalsdk/ah;
    //   589: getfield 97	qalsdk/ah:c	Lcom/tencent/qalsdk/core/j;
    //   592: getfield 298	com/tencent/qalsdk/core/j:m	Ljava/text/SimpleDateFormat;
    //   595: invokestatic 165	java/lang/System:currentTimeMillis	()J
    //   598: invokestatic 304	java/lang/Long:valueOf	(J)Ljava/lang/Long;
    //   601: invokevirtual 310	java/text/SimpleDateFormat:format	(Ljava/lang/Object;)Ljava/lang/String;
    //   604: invokevirtual 79	java/lang/StringBuilder:append	(Ljava/lang/String;)Ljava/lang/StringBuilder;
    //   607: ldc_w 312
    //   610: invokevirtual 79	java/lang/StringBuilder:append	(Ljava/lang/String;)Ljava/lang/StringBuilder;
    //   613: lconst_0
    //   614: invokevirtual 248	java/lang/StringBuilder:append	(J)Ljava/lang/StringBuilder;
    //   617: ldc_w 312
    //   620: invokevirtual 79	java/lang/StringBuilder:append	(Ljava/lang/String;)Ljava/lang/StringBuilder;
    //   623: iconst_0
    //   624: invokevirtual 253	java/lang/StringBuilder:append	(I)Ljava/lang/StringBuilder;
    //   627: ldc_w 312
    //   630: invokevirtual 79	java/lang/StringBuilder:append	(Ljava/lang/String;)Ljava/lang/StringBuilder;
    //   633: aload_0
    //   634: getfield 21	qalsdk/ai:c	Ljava/lang/String;
    //   637: invokevirtual 79	java/lang/StringBuilder:append	(Ljava/lang/String;)Ljava/lang/StringBuilder;
    //   640: ldc_w 312
    //   643: invokevirtual 79	java/lang/StringBuilder:append	(Ljava/lang/String;)Ljava/lang/StringBuilder;
    //   646: aload_2
    //   647: invokevirtual 79	java/lang/StringBuilder:append	(Ljava/lang/String;)Ljava/lang/StringBuilder;
    //   650: invokevirtual 84	java/lang/StringBuilder:toString	()Ljava/lang/String;
    //   653: astore_2
    //   654: invokestatic 315	com/tencent/qalsdk/util/QLog:isColorLevel	()Z
    //   657: ifeq +29 -> 686
    //   660: ldc 70
    //   662: iconst_2
    //   663: new 72	java/lang/StringBuilder
    //   666: dup
    //   667: invokespecial 73	java/lang/StringBuilder:<init>	()V
    //   670: ldc_w 317
    //   673: invokevirtual 79	java/lang/StringBuilder:append	(Ljava/lang/String;)Ljava/lang/StringBuilder;
    //   676: aload_2
    //   677: invokevirtual 79	java/lang/StringBuilder:append	(Ljava/lang/String;)Ljava/lang/StringBuilder;
    //   680: invokevirtual 84	java/lang/StringBuilder:toString	()Ljava/lang/String;
    //   683: invokestatic 255	com/tencent/qalsdk/util/QLog:d	(Ljava/lang/String;ILjava/lang/String;)V
    //   686: aload_1
    //   687: aload_2
    //   688: ldc_w 319
    //   691: invokevirtual 323	java/lang/String:getBytes	(Ljava/lang/String;)[B
    //   694: invokevirtual 231	java/util/ArrayList:add	(Ljava/lang/Object;)Z
    //   697: pop
    //   698: new 325	java/util/HashMap
    //   701: dup
    //   702: invokespecial 326	java/util/HashMap:<init>	()V
    //   705: astore_2
    //   706: aload_2
    //   707: ldc_w 328
    //   710: aload_1
    //   711: invokevirtual 331	java/util/HashMap:put	(Ljava/lang/Object;Ljava/lang/Object;)Ljava/lang/Object;
    //   714: pop
    //   715: aload_0
    //   716: getfield 15	qalsdk/ai:d	Lqalsdk/ah;
    //   719: getfield 97	qalsdk/ah:c	Lcom/tencent/qalsdk/core/j;
    //   722: getfield 267	com/tencent/qalsdk/core/j:c	Lcom/tencent/qalsdk/core/o;
    //   725: aload_2
    //   726: invokevirtual 334	com/tencent/qalsdk/core/o:a	(Ljava/util/HashMap;)V
    //   729: return
    //   730: iload 5
    //   732: newarray <illegal type>
    //   734: astore_1
    //   735: aload_3
    //   736: invokevirtual 338	java/util/ArrayList:iterator	()Ljava/util/Iterator;
    //   739: astore_3
    //   740: iconst_0
    //   741: istore 5
    //   743: aload_3
    //   744: invokeinterface 343 1 0
    //   749: ifeq +286 -> 1035
    //   752: aload_3
    //   753: invokeinterface 347 1 0
    //   758: checkcast 239	[B
    //   761: astore 4
    //   763: aload 4
    //   765: iconst_0
    //   766: aload_1
    //   767: iload 5
    //   769: aload 4
    //   771: arraylength
    //   772: invokestatic 227	java/lang/System:arraycopy	(Ljava/lang/Object;ILjava/lang/Object;II)V
    //   775: aload 4
    //   777: arraylength
    //   778: iload 5
    //   780: iadd
    //   781: istore 5
    //   783: goto -40 -> 743
    //   786: ldc 70
    //   788: iconst_1
    //   789: ldc_w 349
    //   792: invokestatic 255	com/tencent/qalsdk/util/QLog:d	(Ljava/lang/String;ILjava/lang/String;)V
    //   795: aload_0
    //   796: getfield 15	qalsdk/ai:d	Lqalsdk/ah;
    //   799: getfield 97	qalsdk/ah:c	Lcom/tencent/qalsdk/core/j;
    //   802: getfield 267	com/tencent/qalsdk/core/j:c	Lcom/tencent/qalsdk/core/o;
    //   805: getfield 272	com/tencent/qalsdk/core/o:a	Lqalsdk/av;
    //   808: iconst_3
    //   809: putfield 278	qalsdk/av:m	I
    //   812: goto -298 -> 514
    //   815: astore_3
    //   816: aload_2
    //   817: astore_1
    //   818: aload_3
    //   819: astore_2
    //   820: aload_2
    //   821: invokevirtual 350	java/lang/Throwable:toString	()Ljava/lang/String;
    //   824: astore_3
    //   825: aload_2
    //   826: invokevirtual 353	java/lang/Throwable:printStackTrace	()V
    //   829: aload_0
    //   830: getfield 15	qalsdk/ai:d	Lqalsdk/ah;
    //   833: getfield 97	qalsdk/ah:c	Lcom/tencent/qalsdk/core/j;
    //   836: getfield 267	com/tencent/qalsdk/core/j:c	Lcom/tencent/qalsdk/core/o;
    //   839: getfield 272	com/tencent/qalsdk/core/o:a	Lqalsdk/av;
    //   842: iconst_0
    //   843: putfield 278	qalsdk/av:m	I
    //   846: aload_3
    //   847: astore_2
    //   848: aload_1
    //   849: ifnull -296 -> 553
    //   852: aload_1
    //   853: invokevirtual 290	java/net/HttpURLConnection:disconnect	()V
    //   856: aload_3
    //   857: astore_2
    //   858: goto -305 -> 553
    //   861: aload_0
    //   862: getfield 19	qalsdk/ai:b	Z
    //   865: ifeq -326 -> 539
    //   868: invokestatic 165	java/lang/System:currentTimeMillis	()J
    //   871: ldc_w 279
    //   874: i2l
    //   875: ladd
    //   876: putstatic 356	qalsdk/ah:h	J
    //   879: aload_0
    //   880: getfield 15	qalsdk/ai:d	Lqalsdk/ah;
    //   883: invokevirtual 359	qalsdk/ah:w	()V
    //   886: goto -347 -> 539
    //   889: astore_1
    //   890: aload_2
    //   891: ifnull +7 -> 898
    //   894: aload_2
    //   895: invokevirtual 290	java/net/HttpURLConnection:disconnect	()V
    //   898: aload_1
    //   899: athrow
    //   900: new 72	java/lang/StringBuilder
    //   903: dup
    //   904: invokespecial 73	java/lang/StringBuilder:<init>	()V
    //   907: ldc_w 361
    //   910: invokevirtual 79	java/lang/StringBuilder:append	(Ljava/lang/String;)Ljava/lang/StringBuilder;
    //   913: iload 5
    //   915: invokevirtual 253	java/lang/StringBuilder:append	(I)Ljava/lang/StringBuilder;
    //   918: invokevirtual 84	java/lang/StringBuilder:toString	()Ljava/lang/String;
    //   921: astore_1
    //   922: invokestatic 243	com/tencent/qalsdk/util/QLog:isDevelopLevel	()Z
    //   925: ifeq +30 -> 955
    //   928: ldc 70
    //   930: iconst_4
    //   931: new 72	java/lang/StringBuilder
    //   934: dup
    //   935: invokespecial 73	java/lang/StringBuilder:<init>	()V
    //   938: ldc_w 363
    //   941: invokevirtual 79	java/lang/StringBuilder:append	(Ljava/lang/String;)Ljava/lang/StringBuilder;
    //   944: iload 5
    //   946: invokevirtual 253	java/lang/StringBuilder:append	(I)Ljava/lang/StringBuilder;
    //   949: invokevirtual 84	java/lang/StringBuilder:toString	()Ljava/lang/String;
    //   952: invokestatic 255	com/tencent/qalsdk/util/QLog:d	(Ljava/lang/String;ILjava/lang/String;)V
    //   955: ldc 70
    //   957: iconst_1
    //   958: new 72	java/lang/StringBuilder
    //   961: dup
    //   962: invokespecial 73	java/lang/StringBuilder:<init>	()V
    //   965: ldc_w 363
    //   968: invokevirtual 79	java/lang/StringBuilder:append	(Ljava/lang/String;)Ljava/lang/StringBuilder;
    //   971: iload 5
    //   973: invokevirtual 253	java/lang/StringBuilder:append	(I)Ljava/lang/StringBuilder;
    //   976: invokevirtual 84	java/lang/StringBuilder:toString	()Ljava/lang/String;
    //   979: invokestatic 366	com/tencent/qalsdk/util/QLog:e	(Ljava/lang/String;ILjava/lang/String;)V
    //   982: aload_0
    //   983: getfield 15	qalsdk/ai:d	Lqalsdk/ah;
    //   986: getfield 97	qalsdk/ah:c	Lcom/tencent/qalsdk/core/j;
    //   989: getfield 267	com/tencent/qalsdk/core/j:c	Lcom/tencent/qalsdk/core/o;
    //   992: getfield 272	com/tencent/qalsdk/core/o:a	Lqalsdk/av;
    //   995: iconst_3
    //   996: putfield 278	qalsdk/av:m	I
    //   999: goto -456 -> 543
    //   1002: astore_2
    //   1003: aload_2
    //   1004: invokevirtual 367	java/io/UnsupportedEncodingException:printStackTrace	()V
    //   1007: goto -309 -> 698
    //   1010: astore_1
    //   1011: aload_3
    //   1012: astore_2
    //   1013: goto -123 -> 890
    //   1016: astore_3
    //   1017: aload_1
    //   1018: astore_2
    //   1019: aload_3
    //   1020: astore_1
    //   1021: goto -131 -> 890
    //   1024: astore_2
    //   1025: aconst_null
    //   1026: astore_1
    //   1027: goto -207 -> 820
    //   1030: aload_1
    //   1031: astore_2
    //   1032: goto -479 -> 553
    //   1035: goto -610 -> 425
    //   1038: iconst_2
    //   1039: istore 5
    //   1041: goto -973 -> 68
    // Local variable table:
    //   start	length	slot	name	signature
    //   0	1044	0	this	ai
    //   166	687	1	localObject1	Object
    //   889	10	1	localObject2	Object
    //   921	1	1	str1	String
    //   1010	8	1	localObject3	Object
    //   1020	11	1	localObject4	Object
    //   7	888	2	localObject5	Object
    //   1002	2	2	localUnsupportedEncodingException	java.io.UnsupportedEncodingException
    //   1012	7	2	localObject6	Object
    //   1024	1	2	localThrowable1	Throwable
    //   1031	1	2	localObject7	Object
    //   249	504	3	localObject8	Object
    //   815	4	3	localThrowable2	Throwable
    //   824	188	3	str2	String
    //   1016	4	3	localObject9	Object
    //   379	397	4	arrayOfByte	byte[]
    //   66	974	5	i	int
    //   367	36	6	j	int
    //   263	187	7	l	long
    // Exception table:
    //   from	to	target	type
    //   281	334	815	java/lang/Throwable
    //   342	348	815	java/lang/Throwable
    //   351	359	815	java/lang/Throwable
    //   359	369	815	java/lang/Throwable
    //   375	398	815	java/lang/Throwable
    //   408	425	815	java/lang/Throwable
    //   425	471	815	java/lang/Throwable
    //   471	514	815	java/lang/Throwable
    //   514	539	815	java/lang/Throwable
    //   730	740	815	java/lang/Throwable
    //   743	783	815	java/lang/Throwable
    //   786	812	815	java/lang/Throwable
    //   861	886	815	java/lang/Throwable
    //   900	955	815	java/lang/Throwable
    //   955	999	815	java/lang/Throwable
    //   281	334	889	finally
    //   342	348	889	finally
    //   351	359	889	finally
    //   359	369	889	finally
    //   375	398	889	finally
    //   408	425	889	finally
    //   425	471	889	finally
    //   471	514	889	finally
    //   514	539	889	finally
    //   730	740	889	finally
    //   743	783	889	finally
    //   786	812	889	finally
    //   861	886	889	finally
    //   900	955	889	finally
    //   955	999	889	finally
    //   686	698	1002	java/io/UnsupportedEncodingException
    //   250	281	1010	finally
    //   820	846	1016	finally
    //   250	281	1024	java/lang/Throwable
  }
}


/* Location:              E:\apk\dazhihui2\classes2-dex2jar.jar!\qalsdk\ai.class
 * Java compiler version: 6 (50.0)
 * JD-Core Version:       0.7.1
 */