package com.alipay.sdk.app;

import android.app.Activity;
import android.content.Intent;
import android.os.Bundle;
import android.text.TextUtils;
import com.alipay.sdk.c.c;
import com.alipay.sdk.j.d;
import java.util.HashMap;
import java.util.Map;

public class b
{
  static final Object a = d.class;
  private Activity b;
  private com.alipay.sdk.k.a c;
  private String d = "wappaygw.alipay.com/service/rest.htm";
  private String e = "mclient.alipay.com/service/rest.htm";
  private String f = "mclient.alipay.com/home/exterfaceAssign.htm";
  private Map<String, Object> g = new HashMap();
  
  public b(Activity paramActivity)
  {
    this.b = paramActivity;
    com.alipay.sdk.h.b localb = com.alipay.sdk.h.b.a();
    Activity localActivity = this.b;
    c.a();
    localb.a(localActivity);
    com.alipay.sdk.app.a.a.a(paramActivity);
    this.c = new com.alipay.sdk.k.a(paramActivity, "去支付宝付款");
  }
  
  private String a(com.alipay.sdk.g.b arg1)
  {
    ??? = ???.b;
    Object localObject1 = new Intent(this.b, H5PayActivity.class);
    Bundle localBundle = new Bundle();
    localBundle.putString("url", ???[0]);
    if (???.length == 2) {
      localBundle.putString("cookie", ???[1]);
    }
    ((Intent)localObject1).putExtras(localBundle);
    this.b.startActivity((Intent)localObject1);
    synchronized (a)
    {
      try
      {
        a.wait();
        localObject1 = i.a;
        ??? = (com.alipay.sdk.g.b)localObject1;
        if (TextUtils.isEmpty((CharSequence)localObject1)) {
          ??? = i.a();
        }
        return (String)???;
      }
      catch (InterruptedException localInterruptedException)
      {
        String str = i.a();
        return str;
      }
    }
  }
  
  /* Error */
  private String a(String paramString)
  {
    // Byte code:
    //   0: iconst_0
    //   1: istore 6
    //   3: aload_0
    //   4: invokespecial 133	com/alipay/sdk/app/b:a	()V
    //   7: new 135	com/alipay/sdk/f/a/c
    //   10: dup
    //   11: invokespecial 136	com/alipay/sdk/f/a/c:<init>	()V
    //   14: aload_0
    //   15: getfield 47	com/alipay/sdk/app/b:b	Landroid/app/Activity;
    //   18: aload_1
    //   19: invokevirtual 139	com/alipay/sdk/f/a/c:a	(Landroid/content/Context;Ljava/lang/String;)Lcom/alipay/sdk/f/b;
    //   22: invokevirtual 144	com/alipay/sdk/f/b:a	()Lorg/json/JSONObject;
    //   25: ldc -110
    //   27: invokevirtual 152	org/json/JSONObject:optJSONObject	(Ljava/lang/String;)Lorg/json/JSONObject;
    //   30: ldc -102
    //   32: invokevirtual 152	org/json/JSONObject:optJSONObject	(Ljava/lang/String;)Lorg/json/JSONObject;
    //   35: invokestatic 157	com/alipay/sdk/g/b:a	(Lorg/json/JSONObject;)Ljava/util/List;
    //   38: astore_1
    //   39: iconst_0
    //   40: istore 5
    //   42: iload 5
    //   44: aload_1
    //   45: invokeinterface 163 1 0
    //   50: if_icmpge +239 -> 289
    //   53: aload_1
    //   54: iload 5
    //   56: invokeinterface 167 2 0
    //   61: checkcast 77	com/alipay/sdk/g/b
    //   64: getfield 170	com/alipay/sdk/g/b:a	Lcom/alipay/sdk/g/a;
    //   67: getstatic 174	com/alipay/sdk/g/a:c	Lcom/alipay/sdk/g/a;
    //   70: if_acmpne +298 -> 368
    //   73: aload_1
    //   74: iload 5
    //   76: invokeinterface 167 2 0
    //   81: checkcast 77	com/alipay/sdk/g/b
    //   84: getfield 80	com/alipay/sdk/g/b:b	[Ljava/lang/String;
    //   87: astore_2
    //   88: aload_2
    //   89: arraylength
    //   90: iconst_3
    //   91: if_icmpne +277 -> 368
    //   94: ldc -80
    //   96: aload_2
    //   97: iconst_0
    //   98: aaload
    //   99: invokestatic 180	android/text/TextUtils:equals	(Ljava/lang/CharSequence;Ljava/lang/CharSequence;)Z
    //   102: ifeq +266 -> 368
    //   105: invokestatic 52	com/alipay/sdk/h/b:a	()Lcom/alipay/sdk/h/b;
    //   108: getfield 183	com/alipay/sdk/h/b:a	Landroid/content/Context;
    //   111: astore_3
    //   112: invokestatic 188	com/alipay/sdk/i/b:a	()Lcom/alipay/sdk/i/b;
    //   115: astore 4
    //   117: aload_2
    //   118: iconst_1
    //   119: aaload
    //   120: invokestatic 121	android/text/TextUtils:isEmpty	(Ljava/lang/CharSequence;)Z
    //   123: ifne +245 -> 368
    //   126: aload_2
    //   127: iconst_2
    //   128: aaload
    //   129: invokestatic 121	android/text/TextUtils:isEmpty	(Ljava/lang/CharSequence;)Z
    //   132: ifeq +6 -> 138
    //   135: goto +233 -> 368
    //   138: aload 4
    //   140: aload_2
    //   141: iconst_1
    //   142: aaload
    //   143: putfield 189	com/alipay/sdk/i/b:a	Ljava/lang/String;
    //   146: aload 4
    //   148: aload_2
    //   149: iconst_2
    //   150: aaload
    //   151: putfield 191	com/alipay/sdk/i/b:b	Ljava/lang/String;
    //   154: new 193	com/alipay/sdk/i/a
    //   157: dup
    //   158: aload_3
    //   159: invokespecial 195	com/alipay/sdk/i/a:<init>	(Landroid/content/Context;)V
    //   162: astore_2
    //   163: aload_2
    //   164: aload_3
    //   165: invokestatic 200	com/alipay/sdk/j/a:a	(Landroid/content/Context;)Lcom/alipay/sdk/j/a;
    //   168: invokevirtual 201	com/alipay/sdk/j/a:a	()Ljava/lang/String;
    //   171: aload_3
    //   172: invokestatic 200	com/alipay/sdk/j/a:a	(Landroid/content/Context;)Lcom/alipay/sdk/j/a;
    //   175: invokevirtual 203	com/alipay/sdk/j/a:b	()Ljava/lang/String;
    //   178: aload 4
    //   180: getfield 189	com/alipay/sdk/i/b:a	Ljava/lang/String;
    //   183: aload 4
    //   185: getfield 191	com/alipay/sdk/i/b:b	Ljava/lang/String;
    //   188: invokevirtual 206	com/alipay/sdk/i/a:a	(Ljava/lang/String;Ljava/lang/String;Ljava/lang/String;Ljava/lang/String;)V
    //   191: aload_2
    //   192: invokevirtual 209	com/alipay/sdk/i/a:close	()V
    //   195: goto +173 -> 368
    //   198: astore_2
    //   199: getstatic 214	com/alipay/sdk/app/j:d	Lcom/alipay/sdk/app/j;
    //   202: getfield 218	com/alipay/sdk/app/j:h	I
    //   205: invokestatic 221	com/alipay/sdk/app/j:a	(I)Lcom/alipay/sdk/app/j;
    //   208: astore_1
    //   209: ldc -33
    //   211: aload_2
    //   212: invokestatic 226	com/alipay/sdk/app/a/a:a	(Ljava/lang/String;Ljava/lang/Throwable;)V
    //   215: aload_0
    //   216: invokespecial 228	com/alipay/sdk/app/b:b	()V
    //   219: aload_1
    //   220: astore_2
    //   221: aload_1
    //   222: ifnonnull +13 -> 235
    //   225: getstatic 230	com/alipay/sdk/app/j:b	Lcom/alipay/sdk/app/j;
    //   228: getfield 218	com/alipay/sdk/app/j:h	I
    //   231: invokestatic 221	com/alipay/sdk/app/j:a	(I)Lcom/alipay/sdk/app/j;
    //   234: astore_2
    //   235: aload_2
    //   236: getfield 218	com/alipay/sdk/app/j:h	I
    //   239: aload_2
    //   240: getfield 233	com/alipay/sdk/app/j:i	Ljava/lang/String;
    //   243: ldc -21
    //   245: invokestatic 238	com/alipay/sdk/app/i:a	(ILjava/lang/String;Ljava/lang/String;)Ljava/lang/String;
    //   248: areturn
    //   249: astore_3
    //   250: aload_2
    //   251: invokevirtual 209	com/alipay/sdk/i/a:close	()V
    //   254: goto +114 -> 368
    //   257: astore_1
    //   258: ldc -16
    //   260: ldc -14
    //   262: aload_1
    //   263: invokestatic 245	com/alipay/sdk/app/a/a:a	(Ljava/lang/String;Ljava/lang/String;Ljava/lang/Throwable;)V
    //   266: aload_0
    //   267: invokespecial 228	com/alipay/sdk/app/b:b	()V
    //   270: aconst_null
    //   271: astore_1
    //   272: goto -53 -> 219
    //   275: astore_1
    //   276: aload_2
    //   277: invokevirtual 209	com/alipay/sdk/i/a:close	()V
    //   280: aload_1
    //   281: athrow
    //   282: astore_1
    //   283: aload_0
    //   284: invokespecial 228	com/alipay/sdk/app/b:b	()V
    //   287: aload_1
    //   288: athrow
    //   289: aload_0
    //   290: invokespecial 228	com/alipay/sdk/app/b:b	()V
    //   293: iload 6
    //   295: istore 5
    //   297: iload 5
    //   299: aload_1
    //   300: invokeinterface 163 1 0
    //   305: if_icmpge +54 -> 359
    //   308: aload_1
    //   309: iload 5
    //   311: invokeinterface 167 2 0
    //   316: checkcast 77	com/alipay/sdk/g/b
    //   319: getfield 170	com/alipay/sdk/g/b:a	Lcom/alipay/sdk/g/a;
    //   322: getstatic 247	com/alipay/sdk/g/a:b	Lcom/alipay/sdk/g/a;
    //   325: if_acmpne +25 -> 350
    //   328: aload_0
    //   329: aload_1
    //   330: iload 5
    //   332: invokeinterface 167 2 0
    //   337: checkcast 77	com/alipay/sdk/g/b
    //   340: invokespecial 249	com/alipay/sdk/app/b:a	(Lcom/alipay/sdk/g/b;)Ljava/lang/String;
    //   343: astore_1
    //   344: aload_0
    //   345: invokespecial 228	com/alipay/sdk/app/b:b	()V
    //   348: aload_1
    //   349: areturn
    //   350: iload 5
    //   352: iconst_1
    //   353: iadd
    //   354: istore 5
    //   356: goto -59 -> 297
    //   359: aload_0
    //   360: invokespecial 228	com/alipay/sdk/app/b:b	()V
    //   363: aconst_null
    //   364: astore_1
    //   365: goto -146 -> 219
    //   368: iload 5
    //   370: iconst_1
    //   371: iadd
    //   372: istore 5
    //   374: goto -332 -> 42
    // Local variable table:
    //   start	length	slot	name	signature
    //   0	377	0	this	b
    //   0	377	1	paramString	String
    //   87	105	2	localObject1	Object
    //   198	14	2	localIOException	java.io.IOException
    //   220	57	2	localObject2	Object
    //   111	61	3	localContext	android.content.Context
    //   249	1	3	localException	Exception
    //   115	69	4	localb	com.alipay.sdk.i.b
    //   40	333	5	i	int
    //   1	293	6	j	int
    // Exception table:
    //   from	to	target	type
    //   7	39	198	java/io/IOException
    //   42	135	198	java/io/IOException
    //   138	163	198	java/io/IOException
    //   191	195	198	java/io/IOException
    //   250	254	198	java/io/IOException
    //   276	282	198	java/io/IOException
    //   289	293	198	java/io/IOException
    //   297	344	198	java/io/IOException
    //   163	191	249	java/lang/Exception
    //   7	39	257	java/lang/Throwable
    //   42	135	257	java/lang/Throwable
    //   138	163	257	java/lang/Throwable
    //   191	195	257	java/lang/Throwable
    //   250	254	257	java/lang/Throwable
    //   276	282	257	java/lang/Throwable
    //   289	293	257	java/lang/Throwable
    //   297	344	257	java/lang/Throwable
    //   163	191	275	finally
    //   7	39	282	finally
    //   42	135	282	finally
    //   138	163	282	finally
    //   191	195	282	finally
    //   199	215	282	finally
    //   250	254	282	finally
    //   258	266	282	finally
    //   276	282	282	finally
    //   289	293	282	finally
    //   297	344	282	finally
  }
  
  private void a()
  {
    if (this.c != null) {
      this.c.a();
    }
  }
  
  private void b()
  {
    if (this.c != null) {
      this.c.b();
    }
  }
  
  /* Error */
  public String a(String paramString, boolean paramBoolean)
  {
    // Byte code:
    //   0: aconst_null
    //   1: astore 4
    //   3: aconst_null
    //   4: astore 5
    //   6: aload_0
    //   7: monitorenter
    //   8: iload_2
    //   9: ifeq +7 -> 16
    //   12: aload_0
    //   13: invokespecial 133	com/alipay/sdk/app/b:a	()V
    //   16: new 255	com/alipay/sdk/h/a
    //   19: dup
    //   20: aload_0
    //   21: getfield 47	com/alipay/sdk/app/b:b	Landroid/app/Activity;
    //   24: invokespecial 256	com/alipay/sdk/h/a:<init>	(Landroid/content/Context;)V
    //   27: aload_1
    //   28: invokevirtual 258	com/alipay/sdk/h/a:a	(Ljava/lang/String;)Ljava/lang/String;
    //   31: astore_3
    //   32: aload_3
    //   33: ldc_w 260
    //   36: invokevirtual 265	java/lang/String:contains	(Ljava/lang/CharSequence;)Z
    //   39: ifne +131 -> 170
    //   42: aload_0
    //   43: getfield 47	com/alipay/sdk/app/b:b	Landroid/app/Activity;
    //   46: invokestatic 270	com/alipay/sdk/j/j:b	(Landroid/content/Context;)Z
    //   49: ifeq +121 -> 170
    //   52: new 21	com/alipay/sdk/j/d
    //   55: dup
    //   56: aload_0
    //   57: getfield 47	com/alipay/sdk/app/b:b	Landroid/app/Activity;
    //   60: new 272	com/alipay/sdk/app/h
    //   63: dup
    //   64: aload_0
    //   65: invokespecial 274	com/alipay/sdk/app/h:<init>	(Lcom/alipay/sdk/app/b;)V
    //   68: invokespecial 277	com/alipay/sdk/j/d:<init>	(Landroid/app/Activity;Lcom/alipay/sdk/j/e;)V
    //   71: astore 7
    //   73: aload 7
    //   75: aload_3
    //   76: invokevirtual 278	com/alipay/sdk/j/d:a	(Ljava/lang/String;)Ljava/lang/String;
    //   79: astore 6
    //   81: aload 7
    //   83: aconst_null
    //   84: putfield 280	com/alipay/sdk/j/d:a	Landroid/app/Activity;
    //   87: aload 6
    //   89: ldc_w 282
    //   92: invokestatic 180	android/text/TextUtils:equals	(Ljava/lang/CharSequence;Ljava/lang/CharSequence;)Z
    //   95: ifne +75 -> 170
    //   98: aload 6
    //   100: astore_3
    //   101: aload 6
    //   103: invokestatic 121	android/text/TextUtils:isEmpty	(Ljava/lang/CharSequence;)Z
    //   106: ifeq +7 -> 113
    //   109: invokestatic 124	com/alipay/sdk/app/i:a	()Ljava/lang/String;
    //   112: astore_3
    //   113: aload_0
    //   114: getfield 47	com/alipay/sdk/app/b:b	Landroid/app/Activity;
    //   117: astore 6
    //   119: aload_3
    //   120: invokestatic 121	android/text/TextUtils:isEmpty	(Ljava/lang/CharSequence;)Z
    //   123: ifeq +56 -> 179
    //   126: aload 5
    //   128: invokestatic 121	android/text/TextUtils:isEmpty	(Ljava/lang/CharSequence;)Z
    //   131: ifne +13 -> 144
    //   134: aload 6
    //   136: ldc_w 284
    //   139: aload 5
    //   141: invokestatic 289	com/alipay/sdk/j/h:a	(Landroid/content/Context;Ljava/lang/String;Ljava/lang/String;)V
    //   144: invokestatic 294	com/alipay/sdk/c/a:b	()Lcom/alipay/sdk/c/a;
    //   147: aload_0
    //   148: getfield 47	com/alipay/sdk/app/b:b	Landroid/app/Activity;
    //   151: invokevirtual 295	com/alipay/sdk/c/a:a	(Landroid/content/Context;)V
    //   154: aload_0
    //   155: invokespecial 228	com/alipay/sdk/app/b:b	()V
    //   158: aload_0
    //   159: getfield 47	com/alipay/sdk/app/b:b	Landroid/app/Activity;
    //   162: aload_1
    //   163: invokestatic 298	com/alipay/sdk/app/a/a:a	(Landroid/content/Context;Ljava/lang/String;)V
    //   166: aload_0
    //   167: monitorexit
    //   168: aload_3
    //   169: areturn
    //   170: aload_0
    //   171: aload_3
    //   172: invokespecial 299	com/alipay/sdk/app/b:a	(Ljava/lang/String;)Ljava/lang/String;
    //   175: astore_3
    //   176: goto -63 -> 113
    //   179: aload_3
    //   180: ldc_w 301
    //   183: invokevirtual 305	java/lang/String:split	(Ljava/lang/String;)[Ljava/lang/String;
    //   186: astore 7
    //   188: iconst_0
    //   189: istore 9
    //   191: aload 4
    //   193: astore 5
    //   195: iload 9
    //   197: aload 7
    //   199: arraylength
    //   200: if_icmpge -74 -> 126
    //   203: aload 4
    //   205: astore 5
    //   207: aload 7
    //   209: iload 9
    //   211: aaload
    //   212: ldc_w 307
    //   215: invokevirtual 311	java/lang/String:startsWith	(Ljava/lang/String;)Z
    //   218: ifeq +230 -> 448
    //   221: aload 4
    //   223: astore 5
    //   225: aload 7
    //   227: iload 9
    //   229: aaload
    //   230: ldc_w 313
    //   233: invokevirtual 316	java/lang/String:endsWith	(Ljava/lang/String;)Z
    //   236: ifeq +212 -> 448
    //   239: aload 7
    //   241: iload 9
    //   243: aaload
    //   244: bipush 8
    //   246: aload 7
    //   248: iload 9
    //   250: aaload
    //   251: invokevirtual 319	java/lang/String:length	()I
    //   254: iconst_1
    //   255: isub
    //   256: invokevirtual 323	java/lang/String:substring	(II)Ljava/lang/String;
    //   259: ldc_w 325
    //   262: invokevirtual 305	java/lang/String:split	(Ljava/lang/String;)[Ljava/lang/String;
    //   265: astore 8
    //   267: iconst_0
    //   268: istore 10
    //   270: aload 4
    //   272: astore 5
    //   274: iload 10
    //   276: aload 8
    //   278: arraylength
    //   279: if_icmpge +169 -> 448
    //   282: aload 8
    //   284: iload 10
    //   286: aaload
    //   287: ldc_w 327
    //   290: invokevirtual 311	java/lang/String:startsWith	(Ljava/lang/String;)Z
    //   293: ifeq +42 -> 335
    //   296: aload 8
    //   298: iload 10
    //   300: aaload
    //   301: ldc_w 329
    //   304: invokevirtual 316	java/lang/String:endsWith	(Ljava/lang/String;)Z
    //   307: ifeq +28 -> 335
    //   310: aload 8
    //   312: iload 10
    //   314: aaload
    //   315: bipush 13
    //   317: aload 8
    //   319: iload 10
    //   321: aaload
    //   322: invokevirtual 319	java/lang/String:length	()I
    //   325: iconst_1
    //   326: isub
    //   327: invokevirtual 323	java/lang/String:substring	(II)Ljava/lang/String;
    //   330: astore 5
    //   332: goto +116 -> 448
    //   335: aload 8
    //   337: iload 10
    //   339: aaload
    //   340: ldc_w 331
    //   343: invokevirtual 311	java/lang/String:startsWith	(Ljava/lang/String;)Z
    //   346: ifeq +18 -> 364
    //   349: aload 8
    //   351: iload 10
    //   353: aaload
    //   354: bipush 12
    //   356: invokevirtual 334	java/lang/String:substring	(I)Ljava/lang/String;
    //   359: astore 5
    //   361: goto +87 -> 448
    //   364: iload 10
    //   366: iconst_1
    //   367: iadd
    //   368: istore 10
    //   370: goto -100 -> 270
    //   373: astore 4
    //   375: ldc -16
    //   377: ldc_w 336
    //   380: aload 4
    //   382: invokestatic 245	com/alipay/sdk/app/a/a:a	(Ljava/lang/String;Ljava/lang/String;Ljava/lang/Throwable;)V
    //   385: goto -241 -> 144
    //   388: astore_3
    //   389: invokestatic 124	com/alipay/sdk/app/i:a	()Ljava/lang/String;
    //   392: astore_3
    //   393: invokestatic 294	com/alipay/sdk/c/a:b	()Lcom/alipay/sdk/c/a;
    //   396: aload_0
    //   397: getfield 47	com/alipay/sdk/app/b:b	Landroid/app/Activity;
    //   400: invokevirtual 295	com/alipay/sdk/c/a:a	(Landroid/content/Context;)V
    //   403: aload_0
    //   404: invokespecial 228	com/alipay/sdk/app/b:b	()V
    //   407: aload_0
    //   408: getfield 47	com/alipay/sdk/app/b:b	Landroid/app/Activity;
    //   411: aload_1
    //   412: invokestatic 298	com/alipay/sdk/app/a/a:a	(Landroid/content/Context;Ljava/lang/String;)V
    //   415: goto -249 -> 166
    //   418: astore_1
    //   419: aload_0
    //   420: monitorexit
    //   421: aload_1
    //   422: athrow
    //   423: astore_3
    //   424: invokestatic 294	com/alipay/sdk/c/a:b	()Lcom/alipay/sdk/c/a;
    //   427: aload_0
    //   428: getfield 47	com/alipay/sdk/app/b:b	Landroid/app/Activity;
    //   431: invokevirtual 295	com/alipay/sdk/c/a:a	(Landroid/content/Context;)V
    //   434: aload_0
    //   435: invokespecial 228	com/alipay/sdk/app/b:b	()V
    //   438: aload_0
    //   439: getfield 47	com/alipay/sdk/app/b:b	Landroid/app/Activity;
    //   442: aload_1
    //   443: invokestatic 298	com/alipay/sdk/app/a/a:a	(Landroid/content/Context;Ljava/lang/String;)V
    //   446: aload_3
    //   447: athrow
    //   448: iload 9
    //   450: iconst_1
    //   451: iadd
    //   452: istore 9
    //   454: aload 5
    //   456: astore 4
    //   458: goto -267 -> 191
    // Local variable table:
    //   start	length	slot	name	signature
    //   0	461	0	this	b
    //   0	461	1	paramString	String
    //   0	461	2	paramBoolean	boolean
    //   31	149	3	localObject1	Object
    //   388	1	3	localThrowable1	Throwable
    //   392	1	3	str	String
    //   423	24	3	localObject2	Object
    //   1	270	4	localObject3	Object
    //   373	8	4	localThrowable2	Throwable
    //   456	1	4	localObject4	Object
    //   4	451	5	localObject5	Object
    //   79	56	6	localObject6	Object
    //   71	176	7	localObject7	Object
    //   265	85	8	arrayOfString	String[]
    //   189	264	9	i	int
    //   268	101	10	j	int
    // Exception table:
    //   from	to	target	type
    //   119	126	373	java/lang/Throwable
    //   126	144	373	java/lang/Throwable
    //   179	188	373	java/lang/Throwable
    //   195	203	373	java/lang/Throwable
    //   207	221	373	java/lang/Throwable
    //   225	267	373	java/lang/Throwable
    //   274	332	373	java/lang/Throwable
    //   335	361	373	java/lang/Throwable
    //   16	98	388	java/lang/Throwable
    //   101	113	388	java/lang/Throwable
    //   113	119	388	java/lang/Throwable
    //   170	176	388	java/lang/Throwable
    //   375	385	388	java/lang/Throwable
    //   12	16	418	finally
    //   144	166	418	finally
    //   393	415	418	finally
    //   424	448	418	finally
    //   16	98	423	finally
    //   101	113	423	finally
    //   113	119	423	finally
    //   119	126	423	finally
    //   126	144	423	finally
    //   170	176	423	finally
    //   179	188	423	finally
    //   195	203	423	finally
    //   207	221	423	finally
    //   225	267	423	finally
    //   274	332	423	finally
    //   335	361	423	finally
    //   375	385	423	finally
    //   389	393	423	finally
  }
}


/* Location:              E:\apk\dazhihui2\classes-dex2jar.jar!\com\alipay\sdk\app\b.class
 * Java compiler version: 6 (50.0)
 * JD-Core Version:       0.7.1
 */